Workbook

Sheet Raw_Data
A1: Transaction_ID | B1: Date | C1: Description | D1: Amount | E1: Clerk_Suggested_Account | F1: Settlement_Terms | G1: Counterparty | H1: Counterparty_Area | I1: Document_Reference | J1: Supporting_Detail
A2: VVV-2024-001 | B2: 45292 | C2: Initial owner capital contribution | D2: 50000 | E2: Owner's Capital | F2: Owner funds received in business bank account | G2: VVV owner | H2: Verde Valley | I2: CAP-0101 | J2: The sole owner contributed cash to begin operations. VVV operates from Verde Valley. Opening business balances were zero. Owner reference O01.
A3: VVV-2024-002 | B3: 45293 | C3: Monthly facility rent | D3: 5400 | E3: Rent Expense | F3: Automatic bank transfer; settled | G3: Canyon Ridge Properties | H3: Verde Valley | I3: RENT-2024-01 | J3: Facility rent for 2024-01; the monthly charge is paid in full.
A4: VVV-2024-003 | B4: 45294 | C4: Annual business license and operating permits | D4: 1500 | E4: License and Permit Expense | F4: Business debit card; settled | G4: Town of Verde Valley | H4: Verde Valley | I4: PERMIT-2024 | J4: Business licence and operating permits for the 2024 calendar year; paid in full.
A5: VVV-2024-004 | B5: 45295 | C5: Refundable facility security deposit | D5: 6000 | E5: Rent Expense | F5: Bank transfer; refundable at lease end | G5: Canyon Ridge Properties | H5: Verde Valley | I5: LEASE-DEP-01 | J5: Refundable deposit for the facility lease ending December 2026; no rent is included.
A6: VVV-2024-005 | B6: 45297 | C6: Bank loan proceeds received | D6: 50000 | E6: Tour Revenue | F6: Five-year note; cash received | G6: Mesa Community Bank | H6: Verde Valley | I6: NOTE-2401 | J6: Principal $50,000. Instalments of $7,500 are due July 2024 and July 2025; the remaining $35,000 is due January 2029. Interest is billed separately.
A7: VVV-2024-006 | B7: 45297 | C7: Monthly business insurance premium | D7: 600 | E7: Insurance Expense | F7: Automatic bank transfer; settled | G7: Aspen Mutual | H7: Verde Valley | I7: INS-01 | J7: Insurance for 2024-01 only; the monthly charge is paid in full.
A8: VVV-2024-007 | B8: 45299 | C8: Purchased mountain-bike fleet | D8: 30000 | E8: Repairs and Maintenance Expense | F8: $10,000 cash; $20,000 financed by seller | G8: High Desert Cycles | H8: North Mesa | I8: HDC-1048 | J8: 20 new mountain bikes for business use; expected use exceeds one year. Seller principal $20,000 is interest-free and due January 2027.
A9: VVV-2024-008 | B9: 45301 | C9: Purchased kayak fleet | D9: 18000 | E9: Equipment | F9: Bank transfer; settled | G9: Riverline Outfitters | H9: Pine Crossing | I9: RO-7712 | J9: 20 new kayaks for business use; expected use exceeds one year.
A10: VVV-2024-009 | B10: 45303 | C10: Purchased computer and point-of-sale system | D10: 5000 | E10: Office Supplies Expense | F10: Business card; due next month | G10: Summit Technology | H10: North Mesa | I10: ST-22014 | J10: Computer and POS hardware for business use; expected use exceeds one year. Card balance due February 5.
A11: VVV-2024-010 | B11: 45303 | C11: Equipment rental receipts batch | D11: 4500 | E11: Rental Revenue | F11: Cash and card receipts; settled | G11: Multiple customers | H11: Various locations | I11: RENTAL-01 | J11: Services in this receipts batch were completed by the transaction date; all cash and customer-card receipts were deposited.
A12: VVV-2024-011 | B12: 45305 | C12: Purchased office supplies | D12: 1800 | E12: Office Supplies Expense | F12: Business debit card; settled | G12: Pine Office Supply | H12: North Mesa | I12: POS-4811 | J12: Front-desk paper, forms and printer materials; all supplies in this purchase were used during 2024.
A13: VVV-2024-012 | B13: 45307 | C13: Purchased initial retail inventory | D13: 12000 | E13: Inventory | F13: Bank transfer; settled | G13: Trail Goods Cooperative | H13: Pine Crossing | I13: TGC-1001 | J13: Camping supplies held for resale.
... A121: VVV-2024-120 | B121: 45657 | C121: Monthly utility settlement | D121: 682 | E121: Utilities Expense | F121: Paid from business bank account | G121: Verde Valley Utilities | H121: Verde Valley | I121: VVU-12 | J121: Meter V01: 2410 kWh at $0.20/kWh; water and internet $200. Facility open 140 h. Covers 2024-12-01 to 2024-12-31.

Sheet Chart_of_Accounts
A1: Chart of accounts | K1: How the account number works
A2: Assets | D2: Liabilities | G2: Equity | K2: Numbers | L2: Type | M2: What it means | N2: Accounts in this group
A3: No. | B3: Account | C3: Description | D3: No. | E3: Account | F3: Description | G3: No. | H3: Account | I3: Description | K3: 1xx | L3: Asset | M3: stuff we own or are owed | N3: 101 Cash, 110 AR, 120 Inventory, 130 Security Deposit, 150 Equipment
A4: 101 | B4: Cash | C4: bank account (debit card + card receipts too) | D4: 201 | E4: Accounts Payable | F4: what we owe suppliers (inventory + the credit card) | G4: 301 | H4: Owner's Capital | I4: owner's own money put in | K4: 2xx | L4: Liability | M4: what we owe others | N4: 201 AP, 210 Unearned Revenue, 220 Notes Payable
A5: 110 | B5: Accounts Receivable | C5: customers who owe us for tours already done | D5: 210 | E5: Unearned Revenue | F5: deposits for stuff we haven't done yet | H5: + Revenue | K5: 3xx | L5: Equity | M5: the owner's part of the business | N5: 301 Owner's Capital
A6: 120 | B6: Inventory | C6: camping stuff we bought to resell | D6: 220 | E6: Notes Payable | F6: loans: 50k bank loan + 20k owed to the bike seller | G6: 401 | H6: Equipment Rental Revenue | I6: renting bikes/kayaks | K6: 4xx | L6: Revenue | M6: money earned from customers | N6: 401 Equipment Rental, 402 Tour, 403 Retail Sales, 404 Event
A7: 130 | B7: Security Deposit | C7: lease deposit, we get it back in 2026 | G7: 402 | H7: Tour Revenue | I7: guided tours | K7: 5xx | L7: Expense | M7: costs of running the business | N7: 501 COGS, 510-580 operating expenses
A8: 150 | B8: Equipment | C8: bikes, kayaks, POS, paddles, handrails | G8: 403 | H8: Retail Sales Revenue | I8: selling camping supplies | K8: Rule | L8: first digit = type. inside each group, most liquid / most important first
G9: 404 | H9: Event Revenue | I9: seasonal events | K9: Gaps | L9: numbers skip on purpose (e.g. 130 -> 150) so new accounts can be added later, like 151 Accumulated Depreciation
H10: - Expenses | K10: (suggested by AI)
G11: 501 | H11: Cost of Goods Sold | I11: what the stuff we sold cost us
G12: 510 | H12: Wages Expense | I12: staff pay (incl. E04's monthly travel claim)
G13: 520 | H13: Rent Expense | I13: monthly rent
G14: 525 | H14: Insurance Expense | I14: monthly insurance
G15: 530 | H15: Utilities Expense | I15: electricity, water, internet
G16: 535 | H16: License and Permit Expense | I16: yearly licence/permits
G17: 540 | H17: Office and Admin Expense | I17: paper, forms, printer stuff + card fees
G18: 545 | H18: Marketing Expense | I18: ads
G19: 550 | H19: Repairs and Maintenance Expense | I19: workshop labour on the fleet
G20: 555 | H20: School Group Expense | I20: shuttles + materials for the school groups
G21: 565 | H21: Training Expense | I21: guide safety course
G22: 580 | H22: Interest Expense | I22: interest on the bank loan
A25: Accounts from journal | B25: How many used | C25: How many available
A26: {=UNIQUE({Journal!E3:E143;Journal!F3:F143})} -> Cash | B26: =COUNTA(A26:A60) -> 25 | C26: =COUNTA(B4:B8,E4:E6,H4:H22)-2 -> 25
A27: Rent Expense
A28: License and Permit Expense
A29: Security Deposit
A30: Insurance Expense
A31: Equipment
A32: Office and Admin Expense
A33: Inventory
A34: Marketing Expense
A35: Cost of Goods Sold
A36: Wages Expense
A37: Utilities Expense
A38: Accounts Payable
... A50: Event Revenue

Sheet Journal
A1: Journal
A2: Transaction_ID | B2: Date | C2: Description | D2: Amount | E2: Debit Account | F2: Credit Account | G2: Note | H2: Check | J2: Total Debits
A3: =IFERROR(__xludf.DUMMYFUNCTION("FILTER(FLATTEN({Entries!A2:A121,Entries!A2:A121,Entries!A2:A121}),FLATTEN(Entries!R2:T121)<>"""")"),"VVV-2024-001") -> VVV-2024-001 | B3: {=IF(A3:A1001="",,VLOOKUP(A3:A1001,Raw_Data!$A$2:$D$121,2,FALSE))} -> 45292 | C3: {=IF(A3:A1001="",,VLOOKUP(A3:A1001,Raw_Data!$A$2:$D$121,3,FALSE))} -> Initial owner capital contribution | D3: =IFERROR(__xludf.DUMMYFUNCTION("FILTER(FLATTEN(Entries!X2:Z121),FLATTEN(Entries!R2:T121)<>"""")"),50000.0) -> 50000 | E3: =IFERROR(__xludf.DUMMYFUNCTION("FILTER({FLATTEN(Entries!R2:T121),FLATTEN(Entries!U2:W121)},FLATTEN(Entries!R2:T121)<>"""")"),"Cash") -> Cash | F3: =IFERROR(__xludf.DUMMYFUNCTION("""COMPUTED_VALUE"""),"Owner's Capital") -> Owner's Capital | H3: =IF(SUMIFS($D$3:$D$200,$A$3:$A$200,A3,$E$3:$E$200,"<>")=SUMIFS($D$3:$D$200,$A$3:$A$200,A3,$F$3:$F$200,"<>"),"OK","ERROR") -> OK | J3: =SUMIF(E3:E200,"<>",D3:D200) -> 809330
A4: =IFERROR(__xludf.DUMMYFUNCTION("""COMPUTED_VALUE"""),"VVV-2024-002") -> VVV-2024-002 | B4: 45293 | C4: Monthly facility rent | D4: =IFERROR(__xludf.DUMMYFUNCTION("""COMPUTED_VALUE"""),5400.0) -> 5400 | E4: =IFERROR(__xludf.DUMMYFUNCTION("""COMPUTED_VALUE"""),"Rent Expense") -> Rent Expense | F4: =IFERROR(__xludf.DUMMYFUNCTION("""COMPUTED_VALUE"""),"Cash") -> Cash | H4: =IF(SUMIFS($D$3:$D$200,$A$3:$A$200,A4,$E$3:$E$200,"<>")=SUMIFS($D$3:$D$200,$A$3:$A$200,A4,$F$3:$F$200,"<>"),"OK","ERROR") -> OK | J4: Total Credits
A5: =IFERROR(__xludf.DUMMYFUNCTION("""COMPUTED_VALUE"""),"VVV-2024-003") -> VVV-2024-003 | B5: 45294 | C5: Annual business license and operating permits | D5: =IFERROR(__xludf.DUMMYFUNCTION("""COMPUTED_VALUE"""),1500.0) -> 1500 | E5: =IFERROR(__xludf.DUMMYFUNCTION("""COMPUTED_VALUE"""),"License and Permit Expense") -> License and Permit Expense | F5: =IFERROR(__xludf.DUMMYFUNCTION("""COMPUTED_VALUE"""),"Cash") -> Cash | G5: covers just 2024 so i put it straight to expense | H5: =IF(SUMIFS($D$3:$D$200,$A$3:$A$200,A5,$E$3:$E$200,"<>")=SUMIFS($D$3:$D$200,$A$3:$A$200,A5,$F$3:$F$200,"<>"),"OK","ERROR") -> OK | J5: =SUMIF(F3:F200,"<>",D3:D200) -> 809330
A6: =IFERROR(__xludf.DUMMYFUNCTION("""COMPUTED_VALUE"""),"VVV-2024-004") -> VVV-2024-004 | B6: 45295 | C6: Refundable facility security deposit | D6: =IFERROR(__xludf.DUMMYFUNCTION("""COMPUTED_VALUE"""),6000.0) -> 6000 | E6: =IFERROR(__xludf.DUMMYFUNCTION("""COMPUTED_VALUE"""),"Security Deposit") -> Security Deposit | F6: =IFERROR(__xludf.DUMMYFUNCTION("""COMPUTED_VALUE"""),"Cash") -> Cash | G6: clerk had rent exp but it's refundable so it's an asset | H6: =IF(SUMIFS($D$3:$D$200,$A$3:$A$200,A6,$E$3:$E$200,"<>")=SUMIFS($D$3:$D$200,$A$3:$A$200,A6,$F$3:$F$200,"<>"),"OK","ERROR") -> OK | J6: Status
A7: =IFERROR(__xludf.DUMMYFUNCTION("""COMPUTED_VALUE"""),"VVV-2024-005") -> VVV-2024-005 | B7: 45297 | C7: Bank loan proceeds received | D7: =IFERROR(__xludf.DUMMYFUNCTION("""COMPUTED_VALUE"""),50000.0) -> 50000 | E7: =IFERROR(__xludf.DUMMYFUNCTION("""COMPUTED_VALUE"""),"Cash") -> Cash | F7: =IFERROR(__xludf.DUMMYFUNCTION("""COMPUTED_VALUE"""),"Notes Payable") -> Notes Payable | G7: loan not revenue, we have to pay it back | H7: =IF(SUMIFS($D$3:$D$200,$A$3:$A$200,A7,$E$3:$E$200,"<>")=SUMIFS($D$3:$D$200,$A$3:$A$200,A7,$F$3:$F$200,"<>"),"OK","ERROR") -> OK | J7: =IF(J3=J5,"BALANCED","NOT BALANCED") -> BALANCED
A8: =IFERROR(__xludf.DUMMYFUNCTION("""COMPUTED_VALUE"""),"VVV-2024-006") -> VVV-2024-006 | B8: 45297 | C8: Monthly business insurance premium | D8: =IFERROR(__xludf.DUMMYFUNCTION("""COMPUTED_VALUE"""),600.0) -> 600 | E8: =IFERROR(__xludf.DUMMYFUNCTION("""COMPUTED_VALUE"""),"Insurance Expense") -> Insurance Expense | F8: =IFERROR(__xludf.DUMMYFUNCTION("""COMPUTED_VALUE"""),"Cash") -> Cash | H8: =IF(SUMIFS($D$3:$D$200,$A$3:$A$200,A8,$E$3:$E$200,"<>")=SUMIFS($D$3:$D$200,$A$3:$A$200,A8,$F$3:$F$200,"<>"),"OK","ERROR") -> OK
A9: =IFERROR(__xludf.DUMMYFUNCTION("""COMPUTED_VALUE"""),"VVV-2024-007") -> VVV-2024-007 | B9: 45299 | C9: Purchased mountain-bike fleet | D9: =IFERROR(__xludf.DUMMYFUNCTION("""COMPUTED_VALUE"""),10000.0) -> 10000 | E9: =IFERROR(__xludf.DUMMYFUNCTION("""COMPUTED_VALUE"""),"Equipment") -> Equipment | F9: =IFERROR(__xludf.DUMMYFUNCTION("""COMPUTED_VALUE"""),"Cash") -> Cash | G9: bikes last years -> equipment. 20k owed to seller goes in notes payable | H9: =IF(SUMIFS($D$3:$D$200,$A$3:$A$200,A9,$E$3:$E$200,"<>")=SUMIFS($D$3:$D$200,$A$3:$A$200,A9,$F$3:$F$200,"<>"),"OK","ERROR") -> OK
A10: =IFERROR(__xludf.DUMMYFUNCTION("""COMPUTED_VALUE"""),"VVV-2024-007") -> VVV-2024-007 | B10: 45299 | C10: Purchased mountain-bike fleet | D10: =IFERROR(__xludf.DUMMYFUNCTION("""COMPUTED_VALUE"""),20000.0) -> 20000 | E10: =IFERROR(__xludf.DUMMYFUNCTION("""COMPUTED_VALUE"""),"Equipment") -> Equipment | F10: =IFERROR(__xludf.DUMMYFUNCTION("""COMPUTED_VALUE"""),"Notes Payable") -> Notes Payable | H10: =IF(SUMIFS($D$3:$D$200,$A$3:$A$200,A10,$E$3:$E$200,"<>")=SUMIFS($D$3:$D$200,$A$3:$A$200,A10,$F$3:$F$200,"<>"),"OK","ERROR") -> OK
A11: =IFERROR(__xludf.DUMMYFUNCTION("""COMPUTED_VALUE"""),"VVV-2024-008") -> VVV-2024-008 | B11: 45301 | C11: Purchased kayak fleet | D11: =IFERROR(__xludf.DUMMYFUNCTION("""COMPUTED_VALUE"""),18000.0) -> 18000 | E11: =IFERROR(__xludf.DUMMYFUNCTION("""COMPUTED_VALUE"""),"Equipment") -> Equipment | F11: =IFERROR(__xludf.DUMMYFUNCTION("""COMPUTED_VALUE"""),"Cash") -> Cash | H11: =IF(SUMIFS($D$3:$D$200,$A$3:$A$200,A11,$E$3:$E$200,"<>")=SUMIFS($D$3:$D$200,$A$3:$A$200,A11,$F$3:$F$200,"<>"),"OK","ERROR") -> OK
A12: =IFERROR(__xludf.DUMMYFUNCTION("""COMPUTED_VALUE"""),"VVV-2024-009") -> VVV-2024-009 | B12: 45303 | C12: Purchased computer and point-of-sale system | D12: =IFERROR(__xludf.DUMMYFUNCTION("""COMPUTED_VALUE"""),5000.0) -> 5000 | E12: =IFERROR(__xludf.DUMMYFUNCTION("""COMPUTED_VALUE"""),"Equipment") -> Equipment | F12: =IFERROR(__xludf.DUMMYFUNCTION("""COMPUTED_VALUE"""),"Accounts Payable") -> Accounts Payable | G12: not supplies, POS is equipment. paid by card -> AP till we pay it off | H12: =IF(SUMIFS($D$3:$D$200,$A$3:$A$200,A12,$E$3:$E$200,"<>")=SUMIFS($D$3:$D$200,$A$3:$A$200,A12,$F$3:$F$200,"<>"),"OK","ERROR") -> OK
A13: =IFERROR(__xludf.DUMMYFUNCTION("""COMPUTED_VALUE"""),"VVV-2024-010") -> VVV-2024-010 | B13: 45303 | C13: Equipment rental receipts batch | D13: =IFERROR(__xludf.DUMMYFUNCTION("""COMPUTED_VALUE"""),4500.0) -> 4500 | E13: =IFERROR(__xludf.DUMMYFUNCTION("""COMPUTED_VALUE"""),"Cash") -> Cash | F13: =IFERROR(__xludf.DUMMYFUNCTION("""COMPUTED_VALUE"""),"Equipment Rental Revenue") -> Equipment Rental Revenue | H13: =IF(SUMIFS($D$3:$D$200,$A$3:$A$200,A13,$E$3:$E$200,"<>")=SUMIFS($D$3:$D$200,$A$3:$A$200,A13,$F$3:$F$200,"<>"),"OK","ERROR") -> OK
A14: =IFERROR(__xludf.DUMMYFUNCTION("""COMPUTED_VALUE"""),"VVV-2024-011") -> VVV-2024-011 | B14: 45305 | C14: Purchased office supplies | D14: =IFERROR(__xludf.DUMMYFUNCTION("""COMPUTED_VALUE"""),1800.0) -> 1800 | E14: =IFERROR(__xludf.DUMMYFUNCTION("""COMPUTED_VALUE"""),"Office and Admin Expense") -> Office and Admin Expense | F14: =IFERROR(__xludf.DUMMYFUNCTION("""COMPUTED_VALUE"""),"Cash") -> Cash | G14: all used up in 2024 | H14: =IF(SUMIFS($D$3:$D$200,$A$3:$A$200,A14,$E$3:$E$200,"<>")=SUMIFS($D$3:$D$200,$A$3:$A$200,A14,$F$3:$F$200,"<>"),"OK","ERROR") -> OK
A15: =IFERROR(__xludf.DUMMYFUNCTION("""COMPUTED_VALUE"""),"VVV-2024-012") -> VVV-2024-012 | B15: 45307 | C15: Purchased initial retail inventory | D15: =IFERROR(__xludf.DUMMYFUNCTION("""COMPUTED_VALUE"""),12000.0) -> 12000 | E15: =IFERROR(__xludf.DUMMYFUNCTION("""COMPUTED_VALUE"""),"Inventory") -> Inventory | F15: =IFERROR(__xludf.DUMMYFUNCTION("""COMPUTED_VALUE"""),"Cash") -> Cash | H15: =IF(SUMIFS($D$3:$D$200,$A$3:$A$200,A15,$E$3:$E$200,"<>")=SUMIFS($D$3:$D$200,$A$3:$A$200,A15,$F$3:$F$200,"<>"),"OK","ERROR") -> OK
A16: =IFERROR(__xludf.DUMMYFUNCTION("""COMPUTED_VALUE"""),"VVV-2024-013") -> VVV-2024-013 | B16: 45309 | C16: Opening advertising campaign | D16: =IFERROR(__xludf.DUMMYFUNCTION("""COMPUTED_VALUE"""),2200.0) -> 2200 | E16: =IFERROR(__xludf.DUMMYFUNCTION("""COMPUTED_VALUE"""),"Marketing Expense") -> Marketing Expense | F16: =IFERROR(__xludf.DUMMYFUNCTION("""COMPUTED_VALUE"""),"Cash") -> Cash | H16: =IF(SUMIFS($D$3:$D$200,$A$3:$A$200,A16,$E$3:$E$200,"<>")=SUMIFS($D$3:$D$200,$A$3:$A$200,A16,$F$3:$F$200,"<>"),"OK","ERROR") -> OK
A17: =IFERROR(__xludf.DUMMYFUNCTION("""COMPUTED_VALUE"""),"VVV-2024-014") -> VVV-2024-014 | B17: 45310 | C17: Retail camping-supply sales | D17: =IFERROR(__xludf.DUMMYFUNCTION("""COMPUTED_VALUE"""),3000.0) -> 3000 | E17: =IFERROR(__xludf.DUMMYFUNCTION("""COMPUTED_VALUE"""),"Cash") -> Cash | F17: =IFERROR(__xludf.DUMMYFUNCTION("""COMPUTED_VALUE"""),"Retail Sales Revenue") -> Retail Sales Revenue | G17: sale + take cost out of inventory (COGS) | H17: =IF(SUMIFS($D$3:$D$200,$A$3:$A$200,A17,$E$3:$E$200,"<>")=SUMIFS($D$3:$D$200,$A$3:$A$200,A17,$F$3:$F$200,"<>"),"OK","ERROR") -> OK
A18: =IFERROR(__xludf.DUMMYFUNCTION("""COMPUTED_VALUE"""),"VVV-2024-014") -> VVV-2024-014 | B18: 45310 | C18: Retail camping-supply sales | D18: =IFERROR(__xludf.DUMMYFUNCTION("""COMPUTED_VALUE"""),1800.0) -> 1800 | E18: =IFERROR(__xludf.DUMMYFUNCTION("""COMPUTED_VALUE"""),"Cost of Goods Sold") -> Cost of Goods Sold | F18: =IFERROR(__xludf.DUMMYFUNCTION("""COMPUTED_VALUE"""),"Inventory") -> Inventory | H18: =IF(SUMIFS($D$3:$D$200,$A$3:$A$200,A18,$E$3:$E$200,"<>")=SUMIFS($D$3:$D$200,$A$3:$A$200,A18,$F$3:$F$200,"<>"),"OK","ERROR") -> OK
A19: =IFERROR(__xludf.DUMMYFUNCTION("""COMPUTED_VALUE"""),"VVV-2024-015") -> VVV-2024-015 | B19: 45315 | C19: Employee payroll settlement | D19: =IFERROR(__xludf.DUMMYFUNCTION("""COMPUTED_VALUE"""),7200.0) -> 7200 | E19: =IFERROR(__xludf.DUMMYFUNCTION("""COMPUTED_VALUE"""),"Wages Expense") -> Wages Expense | F19: =IFERROR(__xludf.DUMMYFUNCTION("""COMPUTED_VALUE"""),"Cash") -> Cash | G19: includes E04's $200 travel claim | H19: =IF(SUMIFS($D$3:$D$200,$A$3:$A$200,A19,$E$3:$E$200,"<>")=SUMIFS($D$3:$D$200,$A$3:$A$200,A19,$F$3:$F$200,"<>"),"OK","ERROR") -> OK
A20: =IFERROR(__xludf.DUMMYFUNCTION("""COMPUTED_VALUE"""),"VVV-2024-016") -> VVV-2024-016 | B20: 45322 | C20: Monthly utility settlement | D20: =IFERROR(__xludf.DUMMYFUNCTION("""COMPUTED_VALUE"""),694.0) -> 694 | E20: =IFERROR(__xludf.DUMMYFUNCTION("""COMPUTED_VALUE"""),"Utilities Expense") -> Utilities Expense | F20: =IFERROR(__xludf.DUMMYFUNCTION("""COMPUTED_VALUE"""),"Cash") -> Cash | H20: =IF(SUMIFS($D$3:$D$200,$A$3:$A$200,A20,$E$3:$E$200,"<>")=SUMIFS($D$3:$D$200,$A$3:$A$200,A20,$F$3:$F$200,"<>"),"OK","ERROR") -> OK
A21: =IFERROR(__xludf.DUMMYFUNCTION("""COMPUTED_VALUE"""),"VVV-2024-017") -> VVV-2024-017 | B21: 45323 | C21: Monthly facility rent | D21: =IFERROR(__xludf.DUMMYFUNCTION("""COMPUTED_VALUE"""),5400.0) -> 5400 | E21: =IFERROR(__xludf.DUMMYFUNCTION("""COMPUTED_VALUE"""),"Rent Expense") -> Rent Expense | F21: =IFERROR(__xludf.DUMMYFUNCTION("""COMPUTED_VALUE"""),"Cash") -> Cash | G21: blank in raw data, just feb rent | H21: =IF(SUMIFS($D$3:$D$200,$A$3:$A$200,A21,$E$3:$E$200,"<>")=SUMIFS($D$3:$D$200,$A$3:$A$200,A21,$F$3:$F$200,"<>"),"OK","ERROR") -> OK
A22: =IFERROR(__xludf.DUMMYFUNCTION("""COMPUTED_VALUE"""),"VVV-2024-018") -> VVV-2024-018 | B22: 45327 | C22: Paid business card balance for computer/POS purchase | D22: =IFERROR(__xludf.DUMMYFUNCTION("""COMPUTED_VALUE"""),5000.0) -> 5000 | E22: =IFERROR(__xludf.DUMMYFUNCTION("""COMPUTED_VALUE"""),"Accounts Payable") -> Accounts Payable | F22: =IFERROR(__xludf.DUMMYFUNCTION("""COMPUTED_VALUE"""),"Cash") -> Cash | G22: paying off the card from the POS purchase (009) | H22: =IF(SUMIFS($D$3:$D$200,$A$3:$A$200,A22,$E$3:$E$200,"<>")=SUMIFS($D$3:$D$200,$A$3:$A$200,A22,$F$3:$F$200,"<>"),"OK","ERROR") -> OK
A23: =IFERROR(__xludf.DUMMYFUNCTION("""COMPUTED_VALUE"""),"VVV-2024-019") -> VVV-2024-019 | B23: 45328 | C23: Monthly business insurance premium | D23: =IFERROR(__xludf.DUMMYFUNCTION("""COMPUTED_VALUE"""),600.0) -> 600 | E23: =IFERROR(__xludf.DUMMYFUNCTION("""COMPUTED_VALUE"""),"Insurance Expense") -> Insurance Expense | F23: =IFERROR(__xludf.DUMMYFUNCTION("""COMPUTED_VALUE"""),"Cash") -> Cash | H23: =IF(SUMIFS($D$3:$D$200,$A$3:$A$200,A23,$E$3:$E$200,"<>")=SUMIFS($D$3:$D$200,$A$3:$A$200,A23,$F$3:$F$200,"<>"),"OK","ERROR") -> OK
A24: =IFERROR(__xludf.DUMMYFUNCTION("""COMPUTED_VALUE"""),"VVV-2024-020") -> VVV-2024-020 | B24: 45334 | C24: Equipment rental receipts batch | D24: =IFERROR(__xludf.DUMMYFUNCTION("""COMPUTED_VALUE"""),5500.0) -> 5500 | E24: =IFERROR(__xludf.DUMMYFUNCTION("""COMPUTED_VALUE"""),"Cash") -> Cash | F24: =IFERROR(__xludf.DUMMYFUNCTION("""COMPUTED_VALUE"""),"Equipment Rental Revenue") -> Equipment Rental Revenue | H24: =IF(SUMIFS($D$3:$D$200,$A$3:$A$200,A24,$E$3:$E$200,"<>")=SUMIFS($D$3:$D$200,$A$3:$A$200,A24,$F$3:$F$200,"<>"),"OK","ERROR") -> OK
A25: =IFERROR(__xludf.DUMMYFUNCTION("""COMPUTED_VALUE"""),"VVV-2024-021") -> VVV-2024-021 | B25: 45335 | C25: Customer deposit for May corporate tour | D25: =IFERROR(__xludf.DUMMYFUNCTION("""COMPUTED_VALUE"""),4000.0) -> 4000 | E25: =IFERROR(__xludf.DUMMYFUNCTION("""COMPUTED_VALUE"""),"Cash") -> Cash | F25: =IFERROR(__xludf.DUMMYFUNCTION("""COMPUTED_VALUE"""),"Unearned Revenue") -> Unearned Revenue | G25: tour is in may, not earned yet -> unearned | H25: =IF(SUMIFS($D$3:$D$200,$A$3:$A$200,A25,$E$3:$E$200,"<>")=SUMIFS($D$3:$D$200,$A$3:$A$200,A25,$F$3:$F$200,"<>"),"OK","ERROR") -> OK
A26: =IFERROR(__xludf.DUMMYFUNCTION("""COMPUTED_VALUE"""),"VVV-2024-022") -> VVV-2024-022 | B26: 45337 | C26: Purchased retail inventory on account | D26: =IFERROR(__xludf.DUMMYFUNCTION("""COMPUTED_VALUE"""),6000.0) -> 6000 | E26: =IFERROR(__xludf.DUMMYFUNCTION("""COMPUTED_VALUE"""),"Inventory") -> Inventory | F26: =IFERROR(__xludf.DUMMYFUNCTION("""COMPUTED_VALUE"""),"Accounts Payable") -> Accounts Payable | G26: clerk said COGS but nothing sold yet, goes to inventory | H26: =IF(SUMIFS($D$3:$D$200,$A$3:$A$200,A26,$E$3:$E$200,"<>")=SUMIFS($D$3:$D$200,$A$3:$A$200,A26,$F$3:$F$200,"<>"),"OK","ERROR") -> OK
A27: =IFERROR(__xludf.DUMMYFUNCTION("""COMPUTED_VALUE"""),"VVV-2024-023") -> VVV-2024-023 | B27: 45340 | C27: Retail camping-supply sales | D27: =IFERROR(__xludf.DUMMYFUNCTION("""COMPUTED_VALUE"""),4000.0) -> 4000 | E27: =IFERROR(__xludf.DUMMYFUNCTION("""COMPUTED_VALUE"""),"Cash") -> Cash | F27: =IFERROR(__xludf.DUMMYFUNCTION("""COMPUTED_VALUE"""),"Retail Sales Revenue") -> Retail Sales Revenue | H27: =IF(SUMIFS($D$3:$D$200,$A$3:$A$200,A27,$E$3:$E$200,"<>")=SUMIFS($D$3:$D$200,$A$3:$A$200,A27,$F$3:$F$200,"<>"),"OK","ERROR") -> OK
A28: =IFERROR(__xludf.DUMMYFUNCTION("""COMPUTED_VALUE"""),"VVV-2024-023") -> VVV-2024-023 | B28: 45340 | C28: Retail camping-supply sales | D28: =IFERROR(__xludf.DUMMYFUNCTION("""COMPUTED_VALUE"""),2400.0) -> 2400 | E28: =IFERROR(__xludf.DUMMYFUNCTION("""COMPUTED_VALUE"""),"Cost of Goods Sold") -> Cost of Goods Sold | F28: =IFERROR(__xludf.DUMMYFUNCTION("""COMPUTED_VALUE"""),"Inventory") -> Inventory | H28: =IF(SUMIFS($D$3:$D$200,$A$3:$A$200,A28,$E$3:$E$200,"<>")=SUMIFS($D$3:$D$200,$A$3:$A$200,A28,$F$3:$F$200,"<>"),"OK","ERROR") -> OK
A29: =IFERROR(__xludf.DUMMYFUNCTION("""COMPUTED_VALUE"""),"VVV-2024-024") -> VVV-2024-024 | B29: 45342 | C29: Guided tour revenue | D29: =IFERROR(__xludf.DUMMYFUNCTION("""COMPUTED_VALUE"""),3500.0) -> 3500 | E29: =IFERROR(__xludf.DUMMYFUNCTION("""COMPUTED_VALUE"""),"Cash") -> Cash | F29: =IFERROR(__xludf.DUMMYFUNCTION("""COMPUTED_VALUE"""),"Tour Revenue") -> Tour Revenue | H29: =IF(SUMIFS($D$3:$D$200,$A$3:$A$200,A29,$E$3:$E$200,"<>")=SUMIFS($D$3:$D$200,$A$3:$A$200,A29,$F$3:$F$200,"<>"),"OK","ERROR") -> OK
A30: =IFERROR(__xludf.DUMMYFUNCTION("""COMPUTED_VALUE"""),"VVV-2024-025") -> VVV-2024-025 | B30: 45346 | C30: Employee payroll settlement | D30: =IFERROR(__xludf.DUMMYFUNCTION("""COMPUTED_VALUE"""),8200.0) -> 8200 | E30: =IFERROR(__xludf.DUMMYFUNCTION("""COMPUTED_VALUE"""),"Wages Expense") -> Wages Expense | F30: =IFERROR(__xludf.DUMMYFUNCTION("""COMPUTED_VALUE"""),"Cash") -> Cash | G30: includes E04's $200 travel claim | H30: =IF(SUMIFS($D$3:$D$200,$A$3:$A$200,A30,$E$3:$E$200,"<>")=SUMIFS($D$3:$D$200,$A$3:$A$200,A30,$F$3:$F$200,"<>"),"OK","ERROR") -> OK
A31: =IFERROR(__xludf.DUMMYFUNCTION("""COMPUTED_VALUE"""),"VVV-2024-026") -> VVV-2024-026 | B31: 45351 | C31: Monthly utility settlement | D31: =IFERROR(__xludf.DUMMYFUNCTION("""COMPUTED_VALUE"""),754.0) -> 754 | E31: =IFERROR(__xludf.DUMMYFUNCTION("""COMPUTED_VALUE"""),"Utilities Expense") -> Utilities Expense | F31: =IFERROR(__xludf.DUMMYFUNCTION("""COMPUTED_VALUE"""),"Cash") -> Cash | G31: blank, normal utilities | H31: =IF(SUMIFS($D$3:$D$200,$A$3:$A$200,A31,$E$3:$E$200,"<>")=SUMIFS($D$3:$D$200,$A$3:$A$200,A31,$F$3:$F$200,"<>"),"OK","ERROR") -> OK
A32: =IFERROR(__xludf.DUMMYFUNCTION("""COMPUTED_VALUE"""),"VVV-2024-027") -> VVV-2024-027 | B32: 45352 | C32: Monthly facility rent | D32: =IFERROR(__xludf.DUMMYFUNCTION("""COMPUTED_VALUE"""),5400.0) -> 5400 | E32: =IFERROR(__xludf.DUMMYFUNCTION("""COMPUTED_VALUE"""),"Rent Expense") -> Rent Expense | F32: =IFERROR(__xludf.DUMMYFUNCTION("""COMPUTED_VALUE"""),"Cash") -> Cash | H32: =IF(SUMIFS($D$3:$D$200,$A$3:$A$200,A32,$E$3:$E$200,"<>")=SUMIFS($D$3:$D$200,$A$3:$A$200,A32,$F$3:$F$200,"<>"),"OK","ERROR") -> OK
A33: =IFERROR(__xludf.DUMMYFUNCTION("""COMPUTED_VALUE"""),"VVV-2024-028") -> VVV-2024-028 | B33: 45357 | C33: Monthly business insurance premium | D33: =IFERROR(__xludf.DUMMYFUNCTION("""COMPUTED_VALUE"""),600.0) -> 600 | E33: =IFERROR(__xludf.DUMMYFUNCTION("""COMPUTED_VALUE"""),"Insurance Expense") -> Insurance Expense | F33: =IFERROR(__xludf.DUMMYFUNCTION("""COMPUTED_VALUE"""),"Cash") -> Cash | H33: =IF(SUMIFS($D$3:$D$200,$A$3:$A$200,A33,$E$3:$E$200,"<>")=SUMIFS($D$3:$D$200,$A$3:$A$200,A33,$F$3:$F$200,"<>"),"OK","ERROR") -> OK
A34: =IFERROR(__xludf.DUMMYFUNCTION("""COMPUTED_VALUE"""),"VVV-2024-029") -> VVV-2024-029 | B34: 45357 | C34: Partial payment to inventory supplier | D34: =IFERROR(__xludf.DUMMYFUNCTION("""COMPUTED_VALUE"""),4000.0) -> 4000 | E34: =IFERROR(__xludf.DUMMYFUNCTION("""COMPUTED_VALUE"""),"Accounts Payable") -> Accounts Payable | F34: =IFERROR(__xludf.DUMMYFUNCTION("""COMPUTED_VALUE"""),"Cash") -> Cash | H34: =IF(SUMIFS($D$3:$D$200,$A$3:$A$200,A34,$E$3:$E$200,"<>")=SUMIFS($D$3:$D$200,$A$3:$A$200,A34,$F$3:$F$200,"<>"),"OK","ERROR") -> OK
A35: =IFERROR(__xludf.DUMMYFUNCTION("""COMPUTED_VALUE"""),"VVV-2024-030") -> VVV-2024-030 | B35: 45363 | C35: Equipment rental receipts batch | D35: =IFERROR(__xludf.DUMMYFUNCTION("""COMPUTED_VALUE"""),7500.0) -> 7500 | E35: =IFERROR(__xludf.DUMMYFUNCTION("""COMPUTED_VALUE"""),"Cash") -> Cash | F35: =IFERROR(__xludf.DUMMYFUNCTION("""COMPUTED_VALUE"""),"Equipment Rental Revenue") -> Equipment Rental Revenue | H35: =IF(SUMIFS($D$3:$D$200,$A$3:$A$200,A35,$E$3:$E$200,"<>")=SUMIFS($D$3:$D$200,$A$3:$A$200,A35,$F$3:$F$200,"<>"),"OK","ERROR") -> OK
A36: =IFERROR(__xludf.DUMMYFUNCTION("""COMPUTED_VALUE"""),"VVV-2024-031") -> VVV-2024-031 | B36: 45369 | C36: Retail camping-supply sales | D36: =IFERROR(__xludf.DUMMYFUNCTION("""COMPUTED_VALUE"""),5000.0) -> 5000 | E36: =IFERROR(__xludf.DUMMYFUNCTION("""COMPUTED_VALUE"""),"Cash") -> Cash | F36: =IFERROR(__xludf.DUMMYFUNCTION("""COMPUTED_VALUE"""),"Retail Sales Revenue") -> Retail Sales Revenue | H36: =IF(SUMIFS($D$3:$D$200,$A$3:$A$200,A36,$E$3:$E$200,"<>")=SUMIFS($D$3:$D$200,$A$3:$A$200,A36,$F$3:$F$200,"<>"),"OK","ERROR") -> OK
A37: =IFERROR(__xludf.DUMMYFUNCTION("""COMPUTED_VALUE"""),"VVV-2024-031") -> VVV-2024-031 | B37: 45369 | C37: Retail camping-supply sales | D37: =IFERROR(__xludf.DUMMYFUNCTION("""COMPUTED_VALUE"""),3000.0) -> 3000 | E37: =IFERROR(__xludf.DUMMYFUNCTION("""COMPUTED_VALUE"""),"Cost of Goods Sold") -> Cost of Goods Sold | F37: =IFERROR(__xludf.DUMMYFUNCTION("""COMPUTED_VALUE"""),"Inventory") -> Inventory | H37: =IF(SUMIFS($D$3:$D$200,$A$3:$A$200,A37,$E$3:$E$200,"<>")=SUMIFS($D$3:$D$200,$A$3:$A$200,A37,$F$3:$F$200,"<>"),"OK","ERROR") -> OK
A38: =IFERROR(__xludf.DUMMYFUNCTION("""COMPUTED_VALUE"""),"VVV-2024-032") -> VVV-2024-032 | B38: 45369 | C38: Fleet service and dispatch | D38: =IFERROR(__xludf.DUMMYFUNCTION("""COMPUTED_VALUE"""),2800.0) -> 2800 | E38: =IFERROR(__xludf.DUMMYFUNCTION("""COMPUTED_VALUE"""),"Repairs and Maintenance Expense") -> Repairs and Maintenance Expense | F38: =IFERROR(__xludf.DUMMYFUNCTION("""COMPUTED_VALUE"""),"Cash") -> Cash | G38: only the workshop labour is repairs, shuttle for the school group split out | H38: =IF(SUMIFS($D$3:$D$200,$A$3:$A$200,A38,$E$3:$E$200,"<>")=SUMIFS($D$3:$D$200,$A$3:$A$200,A38,$F$3:$F$200,"<>"),"OK","ERROR") -> OK
A39: =IFERROR(__xludf.DUMMYFUNCTION("""COMPUTED_VALUE"""),"VVV-2024-032") -> VVV-2024-032 | B39: 45369 | C39: Fleet service and dispatch | D39: =IFERROR(__xludf.DUMMYFUNCTION("""COMPUTED_VALUE"""),600.0) -> 600 | E39: =IFERROR(__xludf.DUMMYFUNCTION("""COMPUTED_VALUE"""),"School Group Expense") -> School Group Expense | F39: =IFERROR(__xludf.DUMMYFUNCTION("""COMPUTED_VALUE"""),"Cash") -> Cash | H39: =IF(SUMIFS($D$3:$D$200,$A$3:$A$200,A39,$E$3:$E$200,"<>")=SUMIFS($D$3:$D$200,$A$3:$A$200,A39,$F$3:$F$200,"<>"),"OK","ERROR") -> OK
A40: =IFERROR(__xludf.DUMMYFUNCTION("""COMPUTED_VALUE"""),"VVV-2024-033") -> VVV-2024-033 | B40: 45369 | C40: Fleet service and dispatch | D40: =IFERROR(__xludf.DUMMYFUNCTION("""COMPUTED_VALUE"""),1800.0) -> 1800 | E40: =IFERROR(__xludf.DUMMYFUNCTION("""COMPUTED_VALUE"""),"Repairs and Maintenance Expense") -> Repairs and Maintenance Expense | F40: =IFERROR(__xludf.DUMMYFUNCTION("""COMPUTED_VALUE"""),"Cash") -> Cash | G40: school group materials split out of repairs | H40: =IF(SUMIFS($D$3:$D$200,$A$3:$A$200,A40,$E$3:$E$200,"<>")=SUMIFS($D$3:$D$200,$A$3:$A$200,A40,$F$3:$F$200,"<>"),"OK","ERROR") -> OK
A41: =IFERROR(__xludf.DUMMYFUNCTION("""COMPUTED_VALUE"""),"VVV-2024-033") -> VVV-2024-033 | B41: 45369 | C41: Fleet service and dispatch | D41: =IFERROR(__xludf.DUMMYFUNCTION("""COMPUTED_VALUE"""),650.0) -> 650 | E41: =IFERROR(__xludf.DUMMYFUNCTION("""COMPUTED_VALUE"""),"School Group Expense") -> School Group Expense | F41: =IFERROR(__xludf.DUMMYFUNCTION("""COMPUTED_VALUE"""),"Cash") -> Cash | H41: =IF(SUMIFS($D$3:$D$200,$A$3:$A$200,A41,$E$3:$E$200,"<>")=SUMIFS($D$3:$D$200,$A$3:$A$200,A41,$F$3:$F$200,"<>"),"OK","ERROR") -> OK
A42: =IFERROR(__xludf.DUMMYFUNCTION("""COMPUTED_VALUE"""),"VVV-2024-034") -> VVV-2024-034 | B42: 45371 | C42: Corporate guided tour completed on account | D42: =IFERROR(__xludf.DUMMYFUNCTION("""COMPUTED_VALUE"""),6000.0) -> 6000 | E42: =IFERROR(__xludf.DUMMYFUNCTION("""COMPUTED_VALUE"""),"Accounts Receivable") -> Accounts Receivable | F42: =IFERROR(__xludf.DUMMYFUNCTION("""COMPUTED_VALUE"""),"Tour Revenue") -> Tour Revenue | G42: blank. tour done so revenue now, cash later | H42: =IF(SUMIFS($D$3:$D$200,$A$3:$A$200,A42,$E$3:$E$200,"<>")=SUMIFS($D$3:$D$200,$A$3:$A$200,A42,$F$3:$F$200,"<>"),"OK","ERROR") -> OK
A43: =IFERROR(__xludf.DUMMYFUNCTION("""COMPUTED_VALUE"""),"VVV-2024-035") -> VVV-2024-035 | B43: 45375 | C43: Employee payroll settlement | D43: =IFERROR(__xludf.DUMMYFUNCTION("""COMPUTED_VALUE"""),9200.0) -> 9200 | E43: =IFERROR(__xludf.DUMMYFUNCTION("""COMPUTED_VALUE"""),"Wages Expense") -> Wages Expense | F43: =IFERROR(__xludf.DUMMYFUNCTION("""COMPUTED_VALUE"""),"Cash") -> Cash | G43: includes E04's $200 travel claim | H43: =IF(SUMIFS($D$3:$D$200,$A$3:$A$200,A43,$E$3:$E$200,"<>")=SUMIFS($D$3:$D$200,$A$3:$A$200,A43,$F$3:$F$200,"<>"),"OK","ERROR") -> OK
A44: =IFERROR(__xludf.DUMMYFUNCTION("""COMPUTED_VALUE"""),"VVV-2024-036") -> VVV-2024-036 | B44: 45382 | C44: Monthly utility settlement | D44: =IFERROR(__xludf.DUMMYFUNCTION("""COMPUTED_VALUE"""),833.0) -> 833 | E44: =IFERROR(__xludf.DUMMYFUNCTION("""COMPUTED_VALUE"""),"Utilities Expense") -> Utilities Expense | F44: =IFERROR(__xludf.DUMMYFUNCTION("""COMPUTED_VALUE"""),"Cash") -> Cash | H44: =IF(SUMIFS($D$3:$D$200,$A$3:$A$200,A44,$E$3:$E$200,"<>")=SUMIFS($D$3:$D$200,$A$3:$A$200,A44,$F$3:$F$200,"<>"),"OK","ERROR") -> OK
A45: =IFERROR(__xludf.DUMMYFUNCTION("""COMPUTED_VALUE"""),"VVV-2024-037") -> VVV-2024-037 | B45: 45383 | C45: Monthly facility rent | D45: =IFERROR(__xludf.DUMMYFUNCTION("""COMPUTED_VALUE"""),5400.0) -> 5400 | E45: =IFERROR(__xludf.DUMMYFUNCTION("""COMPUTED_VALUE"""),"Rent Expense") -> Rent Expense | F45: =IFERROR(__xludf.DUMMYFUNCTION("""COMPUTED_VALUE"""),"Cash") -> Cash | H45: =IF(SUMIFS($D$3:$D$200,$A$3:$A$200,A45,$E$3:$E$200,"<>")=SUMIFS($D$3:$D$200,$A$3:$A$200,A45,$F$3:$F$200,"<>"),"OK","ERROR") -> OK
A46: =IFERROR(__xludf.DUMMYFUNCTION("""COMPUTED_VALUE"""),"VVV-2024-038") -> VVV-2024-038 | B46: 45387 | C46: Fleet service work order | D46: =IFERROR(__xludf.DUMMYFUNCTION("""COMPUTED_VALUE"""),2000.0) -> 2000 | E46: =IFERROR(__xludf.DUMMYFUNCTION("""COMPUTED_VALUE"""),"Repairs and Maintenance Expense") -> Repairs and Maintenance Expense | F46: =IFERROR(__xludf.DUMMYFUNCTION("""COMPUTED_VALUE"""),"Cash") -> Cash | H46: =IF(SUMIFS($D$3:$D$200,$A$3:$A$200,A46,$E$3:$E$200,"<>")=SUMIFS($D$3:$D$200,$A$3:$A$200,A46,$F$3:$F$200,"<>"),"OK","ERROR") -> OK
A47: =IFERROR(__xludf.DUMMYFUNCTION("""COMPUTED_VALUE"""),"VVV-2024-039") -> VVV-2024-039 | B47: 45388 | C47: Monthly business insurance premium | D47: =IFERROR(__xludf.DUMMYFUNCTION("""COMPUTED_VALUE"""),600.0) -> 600 | E47: =IFERROR(__xludf.DUMMYFUNCTION("""COMPUTED_VALUE"""),"Insurance Expense") -> Insurance Expense | F47: =IFERROR(__xludf.DUMMYFUNCTION("""COMPUTED_VALUE"""),"Cash") -> Cash | H47: =IF(SUMIFS($D$3:$D$200,$A$3:$A$200,A47,$E$3:$E$200,"<>")=SUMIFS($D$3:$D$200,$A$3:$A$200,A47,$F$3:$F$200,"<>"),"OK","ERROR") -> OK
A48: =IFERROR(__xludf.DUMMYFUNCTION("""COMPUTED_VALUE"""),"VVV-2024-040") -> VVV-2024-040 | B48: 45394 | C48: Equipment rental receipts batch | D48: =IFERROR(__xludf.DUMMYFUNCTION("""COMPUTED_VALUE"""),10000.0) -> 10000 | E48: =IFERROR(__xludf.DUMMYFUNCTION("""COMPUTED_VALUE"""),"Cash") -> Cash | F48: =IFERROR(__xludf.DUMMYFUNCTION("""COMPUTED_VALUE"""),"Equipment Rental Revenue") -> Equipment Rental Revenue | H48: =IF(SUMIFS($D$3:$D$200,$A$3:$A$200,A48,$E$3:$E$200,"<>")=SUMIFS($D$3:$D$200,$A$3:$A$200,A48,$F$3:$F$200,"<>"),"OK","ERROR") -> OK
A49: =IFERROR(__xludf.DUMMYFUNCTION("""COMPUTED_VALUE"""),"VVV-2024-041") -> VVV-2024-041 | B49: 45397 | C49: Purchased additional retail inventory | D49: =IFERROR(__xludf.DUMMYFUNCTION("""COMPUTED_VALUE"""),8000.0) -> 8000 | E49: =IFERROR(__xludf.DUMMYFUNCTION("""COMPUTED_VALUE"""),"Inventory") -> Inventory | F49: =IFERROR(__xludf.DUMMYFUNCTION("""COMPUTED_VALUE"""),"Cash") -> Cash | H49: =IF(SUMIFS($D$3:$D$200,$A$3:$A$200,A49,$E$3:$E$200,"<>")=SUMIFS($D$3:$D$200,$A$3:$A$200,A49,$F$3:$F$200,"<>"),"OK","ERROR") -> OK
A50: =IFERROR(__xludf.DUMMYFUNCTION("""COMPUTED_VALUE"""),"VVV-2024-042") -> VVV-2024-042 | B50: 45400 | C50: Retail camping-supply sales | D50: =IFERROR(__xludf.DUMMYFUNCTION("""COMPUTED_VALUE"""),6500.0) -> 6500 | E50: =IFERROR(__xludf.DUMMYFUNCTION("""COMPUTED_VALUE"""),"Cash") -> Cash | F50: =IFERROR(__xludf.DUMMYFUNCTION("""COMPUTED_VALUE"""),"Retail Sales Revenue") -> Retail Sales Revenue | H50: =IF(SUMIFS($D$3:$D$200,$A$3:$A$200,A50,$E$3:$E$200,"<>")=SUMIFS($D$3:$D$200,$A$3:$A$200,A50,$F$3:$F$200,"<>"),"OK","ERROR") -> OK
A51: =IFERROR(__xludf.DUMMYFUNCTION("""COMPUTED_VALUE"""),"VVV-2024-042") -> VVV-2024-042 | B51: 45400 | C51: Retail camping-supply sales | D51: =IFERROR(__xludf.DUMMYFUNCTION("""COMPUTED_VALUE"""),3900.0) -> 3900 | E51: =IFERROR(__xludf.DUMMYFUNCTION("""COMPUTED_VALUE"""),"Cost of Goods Sold") -> Cost of Goods Sold | F51: =IFERROR(__xludf.DUMMYFUNCTION("""COMPUTED_VALUE"""),"Inventory") -> Inventory | H51: =IF(SUMIFS($D$3:$D$200,$A$3:$A$200,A51,$E$3:$E$200,"<>")=SUMIFS($D$3:$D$200,$A$3:$A$200,A51,$F$3:$F$200,"<>"),"OK","ERROR") -> OK
A52: =IFERROR(__xludf.DUMMYFUNCTION("""COMPUTED_VALUE"""),"VVV-2024-043") -> VVV-2024-043 | B52: 45402 | C52: Guided tour revenue | D52: =IFERROR(__xludf.DUMMYFUNCTION("""COMPUTED_VALUE"""),7000.0) -> 7000 | E52: =IFERROR(__xludf.DUMMYFUNCTION("""COMPUTED_VALUE"""),"Cash") -> Cash | F52: =IFERROR(__xludf.DUMMYFUNCTION("""COMPUTED_VALUE"""),"Tour Revenue") -> Tour Revenue | H52: =IF(SUMIFS($D$3:$D$200,$A$3:$A$200,A52,$E$3:$E$200,"<>")=SUMIFS($D$3:$D$200,$A$3:$A$200,A52,$F$3:$F$200,"<>"),"OK","ERROR") -> OK
A53: =IFERROR(__xludf.DUMMYFUNCTION("""COMPUTED_VALUE"""),"VVV-2024-044") -> VVV-2024-044 | B53: 45404 | C53: Seasonal guide safety course | D53: =IFERROR(__xludf.DUMMYFUNCTION("""COMPUTED_VALUE"""),1800.0) -> 1800 | E53: =IFERROR(__xludf.DUMMYFUNCTION("""COMPUTED_VALUE"""),"Training Expense") -> Training Expense | F53: =IFERROR(__xludf.DUMMYFUNCTION("""COMPUTED_VALUE"""),"Cash") -> Cash | H53: =IF(SUMIFS($D$3:$D$200,$A$3:$A$200,A53,$E$3:$E$200,"<>")=SUMIFS($D$3:$D$200,$A$3:$A$200,A53,$F$3:$F$200,"<>"),"OK","ERROR") -> OK
A54: =IFERROR(__xludf.DUMMYFUNCTION("""COMPUTED_VALUE"""),"VVV-2024-045") -> VVV-2024-045 | B54: 45406 | C54: Employee payroll settlement | D54: =IFERROR(__xludf.DUMMYFUNCTION("""COMPUTED_VALUE"""),10200.0) -> 10200 | E54: =IFERROR(__xludf.DUMMYFUNCTION("""COMPUTED_VALUE"""),"Wages Expense") -> Wages Expense | F54: =IFERROR(__xludf.DUMMYFUNCTION("""COMPUTED_VALUE"""),"Cash") -> Cash | G54: includes E04's $200 travel claim | H54: =IF(SUMIFS($D$3:$D$200,$A$3:$A$200,A54,$E$3:$E$200,"<>")=SUMIFS($D$3:$D$200,$A$3:$A$200,A54,$F$3:$F$200,"<>"),"OK","ERROR") -> OK
A55: =IFERROR(__xludf.DUMMYFUNCTION("""COMPUTED_VALUE"""),"VVV-2024-046") -> VVV-2024-046 | B55: 45407 | C55: Customer deposits for June solstice event | D55: =IFERROR(__xludf.DUMMYFUNCTION("""COMPUTED_VALUE"""),3000.0) -> 3000 | E55: =IFERROR(__xludf.DUMMYFUNCTION("""COMPUTED_VALUE"""),"Cash") -> Cash | F55: =IFERROR(__xludf.DUMMYFUNCTION("""COMPUTED_VALUE"""),"Unearned Revenue") -> Unearned Revenue | H55: =IF(SUMIFS($D$3:$D$200,$A$3:$A$200,A55,$E$3:$E$200,"<>")=SUMIFS($D$3:$D$200,$A$3:$A$200,A55,$F$3:$F$200,"<>"),"OK","ERROR") -> OK
A56: =IFERROR(__xludf.DUMMYFUNCTION("""COMPUTED_VALUE"""),"VVV-2024-047") -> VVV-2024-047 | B56: 45412 | C56: Monthly utility settlement | D56: =IFERROR(__xludf.DUMMYFUNCTION("""COMPUTED_VALUE"""),898.0) -> 898 | E56: =IFERROR(__xludf.DUMMYFUNCTION("""COMPUTED_VALUE"""),"Utilities Expense") -> Utilities Expense | F56: =IFERROR(__xludf.DUMMYFUNCTION("""COMPUTED_VALUE"""),"Cash") -> Cash | H56: =IF(SUMIFS($D$3:$D$200,$A$3:$A$200,A56,$E$3:$E$200,"<>")=SUMIFS($D$3:$D$200,$A$3:$A$200,A56,$F$3:$F$200,"<>"),"OK","ERROR") -> OK
A57: =IFERROR(__xludf.DUMMYFUNCTION("""COMPUTED_VALUE"""),"VVV-2024-048") -> VVV-2024-048 | B57: 45413 | C57: Monthly facility rent | D57: =IFERROR(__xludf.DUMMYFUNCTION("""COMPUTED_VALUE"""),5400.0) -> 5400 | E57: =IFERROR(__xludf.DUMMYFUNCTION("""COMPUTED_VALUE"""),"Rent Expense") -> Rent Expense | F57: =IFERROR(__xludf.DUMMYFUNCTION("""COMPUTED_VALUE"""),"Cash") -> Cash | H57: =IF(SUMIFS($D$3:$D$200,$A$3:$A$200,A57,$E$3:$E$200,"<>")=SUMIFS($D$3:$D$200,$A$3:$A$200,A57,$F$3:$F$200,"<>"),"OK","ERROR") -> OK
A58: =IFERROR(__xludf.DUMMYFUNCTION("""COMPUTED_VALUE"""),"VVV-2024-049") -> VVV-2024-049 | B58: 45417 | C58: Collected part of March corporate tour receivable | D58: =IFERROR(__xludf.DUMMYFUNCTION("""COMPUTED_VALUE"""),4000.0) -> 4000 | E58: =IFERROR(__xludf.DUMMYFUNCTION("""COMPUTED_VALUE"""),"Cash") -> Cash | F58: =IFERROR(__xludf.DUMMYFUNCTION("""COMPUTED_VALUE"""),"Accounts Receivable") -> Accounts Receivable | H58: =IF(SUMIFS($D$3:$D$200,$A$3:$A$200,A58,$E$3:$E$200,"<>")=SUMIFS($D$3:$D$200,$A$3:$A$200,A58,$F$3:$F$200,"<>"),"OK","ERROR") -> OK
A59: =IFERROR(__xludf.DUMMYFUNCTION("""COMPUTED_VALUE"""),"VVV-2024-050") -> VVV-2024-050 | B59: 45418 | C59: Monthly business insurance premium | D59: =IFERROR(__xludf.DUMMYFUNCTION("""COMPUTED_VALUE"""),600.0) -> 600 | E59: =IFERROR(__xludf.DUMMYFUNCTION("""COMPUTED_VALUE"""),"Insurance Expense") -> Insurance Expense | F59: =IFERROR(__xludf.DUMMYFUNCTION("""COMPUTED_VALUE"""),"Cash") -> Cash | H59: =IF(SUMIFS($D$3:$D$200,$A$3:$A$200,A59,$E$3:$E$200,"<>")=SUMIFS($D$3:$D$200,$A$3:$A$200,A59,$F$3:$F$200,"<>"),"OK","ERROR") -> OK
A60: =IFERROR(__xludf.DUMMYFUNCTION("""COMPUTED_VALUE"""),"VVV-2024-051") -> VVV-2024-051 | B60: 45424 | C60: Equipment rental receipts batch | D60: =IFERROR(__xludf.DUMMYFUNCTION("""COMPUTED_VALUE"""),13000.0) -> 13000 | E60: =IFERROR(__xludf.DUMMYFUNCTION("""COMPUTED_VALUE"""),"Cash") -> Cash | F60: =IFERROR(__xludf.DUMMYFUNCTION("""COMPUTED_VALUE"""),"Equipment Rental Revenue") -> Equipment Rental Revenue | H60: =IF(SUMIFS($D$3:$D$200,$A$3:$A$200,A60,$E$3:$E$200,"<>")=SUMIFS($D$3:$D$200,$A$3:$A$200,A60,$F$3:$F$200,"<>"),"OK","ERROR") -> OK
A61: =IFERROR(__xludf.DUMMYFUNCTION("""COMPUTED_VALUE"""),"VVV-2024-052") -> VVV-2024-052 | B61: 45430 | C61: Retail camping-supply sales | D61: =IFERROR(__xludf.DUMMYFUNCTION("""COMPUTED_VALUE"""),7760.0) -> 7760 | E61: =IFERROR(__xludf.DUMMYFUNCTION("""COMPUTED_VALUE"""),"Cash") -> Cash | F61: =IFERROR(__xludf.DUMMYFUNCTION("""COMPUTED_VALUE"""),"Retail Sales Revenue") -> Retail Sales Revenue | G61: processor kept 240, put it as admin expense | H61: =IF(SUMIFS($D$3:$D$200,$A$3:$A$200,A61,$E$3:$E$200,"<>")=SUMIFS($D$3:$D$200,$A$3:$A$200,A61,$F$3:$F$200,"<>"),"OK","ERROR") -> OK
A62: =IFERROR(__xludf.DUMMYFUNCTION("""COMPUTED_VALUE"""),"VVV-2024-052") -> VVV-2024-052 | B62: 45430 | C62: Retail camping-supply sales | D62: =IFERROR(__xludf.DUMMYFUNCTION("""COMPUTED_VALUE"""),240.0) -> 240 | E62: =IFERROR(__xludf.DUMMYFUNCTION("""COMPUTED_VALUE"""),"Office and Admin Expense") -> Office and Admin Expense | F62: =IFERROR(__xludf.DUMMYFUNCTION("""COMPUTED_VALUE"""),"Retail Sales Revenue") -> Retail Sales Revenue | H62: =IF(SUMIFS($D$3:$D$200,$A$3:$A$200,A62,$E$3:$E$200,"<>")=SUMIFS($D$3:$D$200,$A$3:$A$200,A62,$F$3:$F$200,"<>"),"OK","ERROR") -> OK
A63: =IFERROR(__xludf.DUMMYFUNCTION("""COMPUTED_VALUE"""),"VVV-2024-052") -> VVV-2024-052 | B63: 45430 | C63: Retail camping-supply sales | D63: =IFERROR(__xludf.DUMMYFUNCTION("""COMPUTED_VALUE"""),4800.0) -> 4800 | E63: =IFERROR(__xludf.DUMMYFUNCTION("""COMPUTED_VALUE"""),"Cost of Goods Sold") -> Cost of Goods Sold | F63: =IFERROR(__xludf.DUMMYFUNCTION("""COMPUTED_VALUE"""),"Inventory") -> Inventory | H63: =IF(SUMIFS($D$3:$D$200,$A$3:$A$200,A63,$E$3:$E$200,"<>")=SUMIFS($D$3:$D$200,$A$3:$A$200,A63,$F$3:$F$200,"<>"),"OK","ERROR") -> OK
A64: =IFERROR(__xludf.DUMMYFUNCTION("""COMPUTED_VALUE"""),"VVV-2024-053") -> VVV-2024-053 | B64: 45432 | C64: Corporate guided tour delivered; deposit applied | D64: =IFERROR(__xludf.DUMMYFUNCTION("""COMPUTED_VALUE"""),4000.0) -> 4000 | E64: =IFERROR(__xludf.DUMMYFUNCTION("""COMPUTED_VALUE"""),"Unearned Revenue") -> Unearned Revenue | F64: =IFERROR(__xludf.DUMMYFUNCTION("""COMPUTED_VALUE"""),"Tour Revenue") -> Tour Revenue | G64: clerk said cash but no cash came in. deposit used + rest billed | H64: =IF(SUMIFS($D$3:$D$200,$A$3:$A$200,A64,$E$3:$E$200,"<>")=SUMIFS($D$3:$D$200,$A$3:$A$200,A64,$F$3:$F$200,"<>"),"OK","ERROR") -> OK
A65: =IFERROR(__xludf.DUMMYFUNCTION("""COMPUTED_VALUE"""),"VVV-2024-053") -> VVV-2024-053 | B65: 45432 | C65: Corporate guided tour delivered; deposit applied | D65: =IFERROR(__xludf.DUMMYFUNCTION("""COMPUTED_VALUE"""),5000.0) -> 5000 | E65: =IFERROR(__xludf.DUMMYFUNCTION("""COMPUTED_VALUE"""),"Accounts Receivable") -> Accounts Receivable | F65: =IFERROR(__xludf.DUMMYFUNCTION("""COMPUTED_VALUE"""),"Tour Revenue") -> Tour Revenue | H65: =IF(SUMIFS($D$3:$D$200,$A$3:$A$200,A65,$E$3:$E$200,"<>")=SUMIFS($D$3:$D$200,$A$3:$A$200,A65,$F$3:$F$200,"<>"),"OK","ERROR") -> OK
A66: =IFERROR(__xludf.DUMMYFUNCTION("""COMPUTED_VALUE"""),"VVV-2024-054") -> VVV-2024-054 | B66: 45436 | C66: Employee payroll settlement | D66: =IFERROR(__xludf.DUMMYFUNCTION("""COMPUTED_VALUE"""),11240.0) -> 11240 | E66: =IFERROR(__xludf.DUMMYFUNCTION("""COMPUTED_VALUE"""),"Wages Expense") -> Wages Expense | F66: =IFERROR(__xludf.DUMMYFUNCTION("""COMPUTED_VALUE"""),"Cash") -> Cash | G66: includes E04's $200 travel claim | H66: =IF(SUMIFS($D$3:$D$200,$A$3:$A$200,A66,$E$3:$E$200,"<>")=SUMIFS($D$3:$D$200,$A$3:$A$200,A66,$F$3:$F$200,"<>"),"OK","ERROR") -> OK
A67: =IFERROR(__xludf.DUMMYFUNCTION("""COMPUTED_VALUE"""),"VVV-2024-055") -> VVV-2024-055 | B67: 45437 | C67: Purchased retail inventory on account | D67: =IFERROR(__xludf.DUMMYFUNCTION("""COMPUTED_VALUE"""),9000.0) -> 9000 | E67: =IFERROR(__xludf.DUMMYFUNCTION("""COMPUTED_VALUE"""),"Inventory") -> Inventory | F67: =IFERROR(__xludf.DUMMYFUNCTION("""COMPUTED_VALUE"""),"Accounts Payable") -> Accounts Payable | G67: blank, inventory on credit | H67: =IF(SUMIFS($D$3:$D$200,$A$3:$A$200,A67,$E$3:$E$200,"<>")=SUMIFS($D$3:$D$200,$A$3:$A$200,A67,$F$3:$F$200,"<>"),"OK","ERROR") -> OK
A68: =IFERROR(__xludf.DUMMYFUNCTION("""COMPUTED_VALUE"""),"VVV-2024-056") -> VVV-2024-056 | B68: 45443 | C68: Monthly utility settlement | D68: =IFERROR(__xludf.DUMMYFUNCTION("""COMPUTED_VALUE"""),1048.0) -> 1048 | E68: =IFERROR(__xludf.DUMMYFUNCTION("""COMPUTED_VALUE"""),"Utilities Expense") -> Utilities Expense | F68: =IFERROR(__xludf.DUMMYFUNCTION("""COMPUTED_VALUE"""),"Cash") -> Cash | H68: =IF(SUMIFS($D$3:$D$200,$A$3:$A$200,A68,$E$3:$E$200,"<>")=SUMIFS($D$3:$D$200,$A$3:$A$200,A68,$F$3:$F$200,"<>"),"OK","ERROR") -> OK
A69: =IFERROR(__xludf.DUMMYFUNCTION("""COMPUTED_VALUE"""),"VVV-2024-057") -> VVV-2024-057 | B69: 45443 | C69: Facility equipment purchase | D69: =IFERROR(__xludf.DUMMYFUNCTION("""COMPUTED_VALUE"""),2200.0) -> 2200 | E69: =IFERROR(__xludf.DUMMYFUNCTION("""COMPUTED_VALUE"""),"Equipment") -> Equipment | F69: =IFERROR(__xludf.DUMMYFUNCTION("""COMPUTED_VALUE"""),"Cash") -> Cash | G69: paddles/racks last >1 yr so equipment | H69: =IF(SUMIFS($D$3:$D$200,$A$3:$A$200,A69,$E$3:$E$200,"<>")=SUMIFS($D$3:$D$200,$A$3:$A$200,A69,$F$3:$F$200,"<>"),"OK","ERROR") -> OK
A70: =IFERROR(__xludf.DUMMYFUNCTION("""COMPUTED_VALUE"""),"VVV-2024-058") -> VVV-2024-058 | B70: 45444 | C70: Monthly facility rent | D70: =IFERROR(__xludf.DUMMYFUNCTION("""COMPUTED_VALUE"""),5400.0) -> 5400 | E70: =IFERROR(__xludf.DUMMYFUNCTION("""COMPUTED_VALUE"""),"Rent Expense") -> Rent Expense | F70: =IFERROR(__xludf.DUMMYFUNCTION("""COMPUTED_VALUE"""),"Cash") -> Cash | H70: =IF(SUMIFS($D$3:$D$200,$A$3:$A$200,A70,$E$3:$E$200,"<>")=SUMIFS($D$3:$D$200,$A$3:$A$200,A70,$F$3:$F$200,"<>"),"OK","ERROR") -> OK
A71: =IFERROR(__xludf.DUMMYFUNCTION("""COMPUTED_VALUE"""),"VVV-2024-059") -> VVV-2024-059 | B71: 45448 | C71: Collected part of May corporate tour receivable | D71: =IFERROR(__xludf.DUMMYFUNCTION("""COMPUTED_VALUE"""),3000.0) -> 3000 | E71: =IFERROR(__xludf.DUMMYFUNCTION("""COMPUTED_VALUE"""),"Cash") -> Cash | F71: =IFERROR(__xludf.DUMMYFUNCTION("""COMPUTED_VALUE"""),"Accounts Receivable") -> Accounts Receivable | H71: =IF(SUMIFS($D$3:$D$200,$A$3:$A$200,A71,$E$3:$E$200,"<>")=SUMIFS($D$3:$D$200,$A$3:$A$200,A71,$F$3:$F$200,"<>"),"OK","ERROR") -> OK
A72: =IFERROR(__xludf.DUMMYFUNCTION("""COMPUTED_VALUE"""),"VVV-2024-060") -> VVV-2024-060 | B72: 45449 | C72: Monthly business insurance premium | D72: =IFERROR(__xludf.DUMMYFUNCTION("""COMPUTED_VALUE"""),600.0) -> 600 | E72: =IFERROR(__xludf.DUMMYFUNCTION("""COMPUTED_VALUE"""),"Insurance Expense") -> Insurance Expense | F72: =IFERROR(__xludf.DUMMYFUNCTION("""COMPUTED_VALUE"""),"Cash") -> Cash | H72: =IF(SUMIFS($D$3:$D$200,$A$3:$A$200,A72,$E$3:$E$200,"<>")=SUMIFS($D$3:$D$200,$A$3:$A$200,A72,$F$3:$F$200,"<>"),"OK","ERROR") -> OK
A73: =IFERROR(__xludf.DUMMYFUNCTION("""COMPUTED_VALUE"""),"VVV-2024-061") -> VVV-2024-061 | B73: 45449 | C73: Partial payment to inventory supplier | D73: =IFERROR(__xludf.DUMMYFUNCTION("""COMPUTED_VALUE"""),3000.0) -> 3000 | E73: =IFERROR(__xludf.DUMMYFUNCTION("""COMPUTED_VALUE"""),"Accounts Payable") -> Accounts Payable | F73: =IFERROR(__xludf.DUMMYFUNCTION("""COMPUTED_VALUE"""),"Cash") -> Cash | H73: =IF(SUMIFS($D$3:$D$200,$A$3:$A$200,A73,$E$3:$E$200,"<>")=SUMIFS($D$3:$D$200,$A$3:$A$200,A73,$F$3:$F$200,"<>"),"OK","ERROR") -> OK
A74: =IFERROR(__xludf.DUMMYFUNCTION("""COMPUTED_VALUE"""),"VVV-2024-062") -> VVV-2024-062 | B74: 45455 | C74: Equipment rental receipts batch | D74: =IFERROR(__xludf.DUMMYFUNCTION("""COMPUTED_VALUE"""),16000.0) -> 16000 | E74: =IFERROR(__xludf.DUMMYFUNCTION("""COMPUTED_VALUE"""),"Cash") -> Cash | F74: =IFERROR(__xludf.DUMMYFUNCTION("""COMPUTED_VALUE"""),"Equipment Rental Revenue") -> Equipment Rental Revenue | H74: =IF(SUMIFS($D$3:$D$200,$A$3:$A$200,A74,$E$3:$E$200,"<>")=SUMIFS($D$3:$D$200,$A$3:$A$200,A74,$F$3:$F$200,"<>"),"OK","ERROR") -> OK
A75: =IFERROR(__xludf.DUMMYFUNCTION("""COMPUTED_VALUE"""),"VVV-2024-063") -> VVV-2024-063 | B75: 45460 | C75: Fleet service and dispatch | D75: =IFERROR(__xludf.DUMMYFUNCTION("""COMPUTED_VALUE"""),3200.0) -> 3200 | E75: =IFERROR(__xludf.DUMMYFUNCTION("""COMPUTED_VALUE"""),"Repairs and Maintenance Expense") -> Repairs and Maintenance Expense | F75: =IFERROR(__xludf.DUMMYFUNCTION("""COMPUTED_VALUE"""),"Cash") -> Cash | G75: same as march, school shuttle split out | H75: =IF(SUMIFS($D$3:$D$200,$A$3:$A$200,A75,$E$3:$E$200,"<>")=SUMIFS($D$3:$D$200,$A$3:$A$200,A75,$F$3:$F$200,"<>"),"OK","ERROR") -> OK
A76: =IFERROR(__xludf.DUMMYFUNCTION("""COMPUTED_VALUE"""),"VVV-2024-063") -> VVV-2024-063 | B76: 45460 | C76: Fleet service and dispatch | D76: =IFERROR(__xludf.DUMMYFUNCTION("""COMPUTED_VALUE"""),720.0) -> 720 | E76: =IFERROR(__xludf.DUMMYFUNCTION("""COMPUTED_VALUE"""),"School Group Expense") -> School Group Expense | F76: =IFERROR(__xludf.DUMMYFUNCTION("""COMPUTED_VALUE"""),"Cash") -> Cash | H76: =IF(SUMIFS($D$3:$D$200,$A$3:$A$200,A76,$E$3:$E$200,"<>")=SUMIFS($D$3:$D$200,$A$3:$A$200,A76,$F$3:$F$200,"<>"),"OK","ERROR") -> OK
A77: =IFERROR(__xludf.DUMMYFUNCTION("""COMPUTED_VALUE"""),"VVV-2024-064") -> VVV-2024-064 | B77: 45460 | C77: Fleet service and dispatch | D77: =IFERROR(__xludf.DUMMYFUNCTION("""COMPUTED_VALUE"""),2200.0) -> 2200 | E77: =IFERROR(__xludf.DUMMYFUNCTION("""COMPUTED_VALUE"""),"Repairs and Maintenance Expense") -> Repairs and Maintenance Expense | F77: =IFERROR(__xludf.DUMMYFUNCTION("""COMPUTED_VALUE"""),"Cash") -> Cash | G77: same split as 033 | H77: =IF(SUMIFS($D$3:$D$200,$A$3:$A$200,A77,$E$3:$E$200,"<>")=SUMIFS($D$3:$D$200,$A$3:$A$200,A77,$F$3:$F$200,"<>"),"OK","ERROR") -> OK
A78: =IFERROR(__xludf.DUMMYFUNCTION("""COMPUTED_VALUE"""),"VVV-2024-064") -> VVV-2024-064 | B78: 45460 | C78: Fleet service and dispatch | D78: =IFERROR(__xludf.DUMMYFUNCTION("""COMPUTED_VALUE"""),680.0) -> 680 | E78: =IFERROR(__xludf.DUMMYFUNCTION("""COMPUTED_VALUE"""),"School Group Expense") -> School Group Expense | F78: =IFERROR(__xludf.DUMMYFUNCTION("""COMPUTED_VALUE"""),"Cash") -> Cash | H78: =IF(SUMIFS($D$3:$D$200,$A$3:$A$200,A78,$E$3:$E$200,"<>")=SUMIFS($D$3:$D$200,$A$3:$A$200,A78,$F$3:$F$200,"<>"),"OK","ERROR") -> OK
A79: =IFERROR(__xludf.DUMMYFUNCTION("""COMPUTED_VALUE"""),"VVV-2024-065") -> VVV-2024-065 | B79: 45461 | C79: Retail camping-supply sales | D79: =IFERROR(__xludf.DUMMYFUNCTION("""COMPUTED_VALUE"""),9000.0) -> 9000 | E79: =IFERROR(__xludf.DUMMYFUNCTION("""COMPUTED_VALUE"""),"Cash") -> Cash | F79: =IFERROR(__xludf.DUMMYFUNCTION("""COMPUTED_VALUE"""),"Retail Sales Revenue") -> Retail Sales Revenue | H79: =IF(SUMIFS($D$3:$D$200,$A$3:$A$200,A79,$E$3:$E$200,"<>")=SUMIFS($D$3:$D$200,$A$3:$A$200,A79,$F$3:$F$200,"<>"),"OK","ERROR") -> OK
A80: =IFERROR(__xludf.DUMMYFUNCTION("""COMPUTED_VALUE"""),"VVV-2024-065") -> VVV-2024-065 | B80: 45461 | C80: Retail camping-supply sales | D80: =IFERROR(__xludf.DUMMYFUNCTION("""COMPUTED_VALUE"""),5400.0) -> 5400 | E80: =IFERROR(__xludf.DUMMYFUNCTION("""COMPUTED_VALUE"""),"Cost of Goods Sold") -> Cost of Goods Sold | F80: =IFERROR(__xludf.DUMMYFUNCTION("""COMPUTED_VALUE"""),"Inventory") -> Inventory | H80: =IF(SUMIFS($D$3:$D$200,$A$3:$A$200,A80,$E$3:$E$200,"<>")=SUMIFS($D$3:$D$200,$A$3:$A$200,A80,$F$3:$F$200,"<>"),"OK","ERROR") -> OK
A81: =IFERROR(__xludf.DUMMYFUNCTION("""COMPUTED_VALUE"""),"VVV-2024-066") -> VVV-2024-066 | B81: 45463 | C81: Guided tour revenue | D81: =IFERROR(__xludf.DUMMYFUNCTION("""COMPUTED_VALUE"""),12000.0) -> 12000 | E81: =IFERROR(__xludf.DUMMYFUNCTION("""COMPUTED_VALUE"""),"Cash") -> Cash | F81: =IFERROR(__xludf.DUMMYFUNCTION("""COMPUTED_VALUE"""),"Tour Revenue") -> Tour Revenue | H81: =IF(SUMIFS($D$3:$D$200,$A$3:$A$200,A81,$E$3:$E$200,"<>")=SUMIFS($D$3:$D$200,$A$3:$A$200,A81,$F$3:$F$200,"<>"),"OK","ERROR") -> OK
A82: =IFERROR(__xludf.DUMMYFUNCTION("""COMPUTED_VALUE"""),"VVV-2024-067") -> VVV-2024-067 | B82: 45465 | C82: Summer solstice event completed; deposit applied | D82: =IFERROR(__xludf.DUMMYFUNCTION("""COMPUTED_VALUE"""),3000.0) -> 3000 | E82: =IFERROR(__xludf.DUMMYFUNCTION("""COMPUTED_VALUE"""),"Unearned Revenue") -> Unearned Revenue | F82: =IFERROR(__xludf.DUMMYFUNCTION("""COMPUTED_VALUE"""),"Event Revenue") -> Event Revenue | G82: april deposit now earned + 4500 new cash | H82: =IF(SUMIFS($D$3:$D$200,$A$3:$A$200,A82,$E$3:$E$200,"<>")=SUMIFS($D$3:$D$200,$A$3:$A$200,A82,$F$3:$F$200,"<>"),"OK","ERROR") -> OK
A83: =IFERROR(__xludf.DUMMYFUNCTION("""COMPUTED_VALUE"""),"VVV-2024-067") -> VVV-2024-067 | B83: 45465 | C83: Summer solstice event completed; deposit applied | D83: =IFERROR(__xludf.DUMMYFUNCTION("""COMPUTED_VALUE"""),4500.0) -> 4500 | E83: =IFERROR(__xludf.DUMMYFUNCTION("""COMPUTED_VALUE"""),"Cash") -> Cash | F83: =IFERROR(__xludf.DUMMYFUNCTION("""COMPUTED_VALUE"""),"Event Revenue") -> Event Revenue | H83: =IF(SUMIFS($D$3:$D$200,$A$3:$A$200,A83,$E$3:$E$200,"<>")=SUMIFS($D$3:$D$200,$A$3:$A$200,A83,$F$3:$F$200,"<>"),"OK","ERROR") -> OK
A84: =IFERROR(__xludf.DUMMYFUNCTION("""COMPUTED_VALUE"""),"VVV-2024-068") -> VVV-2024-068 | B84: 45467 | C84: Employee payroll settlement | D84: =IFERROR(__xludf.DUMMYFUNCTION("""COMPUTED_VALUE"""),12160.0) -> 12160 | E84: =IFERROR(__xludf.DUMMYFUNCTION("""COMPUTED_VALUE"""),"Wages Expense") -> Wages Expense | F84: =IFERROR(__xludf.DUMMYFUNCTION("""COMPUTED_VALUE"""),"Cash") -> Cash | G84: includes E04's $200 travel claim | H84: =IF(SUMIFS($D$3:$D$200,$A$3:$A$200,A84,$E$3:$E$200,"<>")=SUMIFS($D$3:$D$200,$A$3:$A$200,A84,$F$3:$F$200,"<>"),"OK","ERROR") -> OK
A85: =IFERROR(__xludf.DUMMYFUNCTION("""COMPUTED_VALUE"""),"VVV-2024-069") -> VVV-2024-069 | B85: 45468 | C85: Facility equipment installation | D85: =IFERROR(__xludf.DUMMYFUNCTION("""COMPUTED_VALUE"""),3600.0) -> 3600 | E85: =IFERROR(__xludf.DUMMYFUNCTION("""COMPUTED_VALUE"""),"Equipment") -> Equipment | F85: =IFERROR(__xludf.DUMMYFUNCTION("""COMPUTED_VALUE"""),"Cash") -> Cash | G85: blank. handrails are ours and last years -> equipment | H85: =IF(SUMIFS($D$3:$D$200,$A$3:$A$200,A85,$E$3:$E$200,"<>")=SUMIFS($D$3:$D$200,$A$3:$A$200,A85,$F$3:$F$200,"<>"),"OK","ERROR") -> OK
A86: =IFERROR(__xludf.DUMMYFUNCTION("""COMPUTED_VALUE"""),"VVV-2024-070") -> VVV-2024-070 | B86: 45473 | C86: Monthly utility settlement | D86: =IFERROR(__xludf.DUMMYFUNCTION("""COMPUTED_VALUE"""),1173.0) -> 1173 | E86: =IFERROR(__xludf.DUMMYFUNCTION("""COMPUTED_VALUE"""),"Utilities Expense") -> Utilities Expense | F86: =IFERROR(__xludf.DUMMYFUNCTION("""COMPUTED_VALUE"""),"Cash") -> Cash | G86: blank, utilities | H86: =IF(SUMIFS($D$3:$D$200,$A$3:$A$200,A86,$E$3:$E$200,"<>")=SUMIFS($D$3:$D$200,$A$3:$A$200,A86,$F$3:$F$200,"<>"),"OK","ERROR") -> OK
A87: =IFERROR(__xludf.DUMMYFUNCTION("""COMPUTED_VALUE"""),"VVV-2024-071") -> VVV-2024-071 | B87: 45474 | C87: Monthly facility rent | D87: =IFERROR(__xludf.DUMMYFUNCTION("""COMPUTED_VALUE"""),5400.0) -> 5400 | E87: =IFERROR(__xludf.DUMMYFUNCTION("""COMPUTED_VALUE"""),"Rent Expense") -> Rent Expense | F87: =IFERROR(__xludf.DUMMYFUNCTION("""COMPUTED_VALUE"""),"Cash") -> Cash | H87: =IF(SUMIFS($D$3:$D$200,$A$3:$A$200,A87,$E$3:$E$200,"<>")=SUMIFS($D$3:$D$200,$A$3:$A$200,A87,$F$3:$F$200,"<>"),"OK","ERROR") -> OK
A88: =IFERROR(__xludf.DUMMYFUNCTION("""COMPUTED_VALUE"""),"VVV-2024-072") -> VVV-2024-072 | B88: 45478 | C88: Fleet service work order | D88: =IFERROR(__xludf.DUMMYFUNCTION("""COMPUTED_VALUE"""),1800.0) -> 1800 | E88: =IFERROR(__xludf.DUMMYFUNCTION("""COMPUTED_VALUE"""),"Repairs and Maintenance Expense") -> Repairs and Maintenance Expense | F88: =IFERROR(__xludf.DUMMYFUNCTION("""COMPUTED_VALUE"""),"Cash") -> Cash | H88: =IF(SUMIFS($D$3:$D$200,$A$3:$A$200,A88,$E$3:$E$200,"<>")=SUMIFS($D$3:$D$200,$A$3:$A$200,A88,$F$3:$F$200,"<>"),"OK","ERROR") -> OK
A89: =IFERROR(__xludf.DUMMYFUNCTION("""COMPUTED_VALUE"""),"VVV-2024-073") -> VVV-2024-073 | B89: 45479 | C89: Monthly business insurance premium | D89: =IFERROR(__xludf.DUMMYFUNCTION("""COMPUTED_VALUE"""),600.0) -> 600 | E89: =IFERROR(__xludf.DUMMYFUNCTION("""COMPUTED_VALUE"""),"Insurance Expense") -> Insurance Expense | F89: =IFERROR(__xludf.DUMMYFUNCTION("""COMPUTED_VALUE"""),"Cash") -> Cash | H89: =IF(SUMIFS($D$3:$D$200,$A$3:$A$200,A89,$E$3:$E$200,"<>")=SUMIFS($D$3:$D$200,$A$3:$A$200,A89,$F$3:$F$200,"<>"),"OK","ERROR") -> OK
A90: =IFERROR(__xludf.DUMMYFUNCTION("""COMPUTED_VALUE"""),"VVV-2024-074") -> VVV-2024-074 | B90: 45485 | C90: Equipment rental receipts batch | D90: =IFERROR(__xludf.DUMMYFUNCTION("""COMPUTED_VALUE"""),18000.0) -> 18000 | E90: =IFERROR(__xludf.DUMMYFUNCTION("""COMPUTED_VALUE"""),"Cash") -> Cash | F90: =IFERROR(__xludf.DUMMYFUNCTION("""COMPUTED_VALUE"""),"Equipment Rental Revenue") -> Equipment Rental Revenue | H90: =IF(SUMIFS($D$3:$D$200,$A$3:$A$200,A90,$E$3:$E$200,"<>")=SUMIFS($D$3:$D$200,$A$3:$A$200,A90,$F$3:$F$200,"<>"),"OK","ERROR") -> OK
A91: =IFERROR(__xludf.DUMMYFUNCTION("""COMPUTED_VALUE"""),"VVV-2024-075") -> VVV-2024-075 | B91: 45491 | C91: Retail camping-supply sales | D91: =IFERROR(__xludf.DUMMYFUNCTION("""COMPUTED_VALUE"""),10000.0) -> 10000 | E91: =IFERROR(__xludf.DUMMYFUNCTION("""COMPUTED_VALUE"""),"Cash") -> Cash | F91: =IFERROR(__xludf.DUMMYFUNCTION("""COMPUTED_VALUE"""),"Retail Sales Revenue") -> Retail Sales Revenue | H91: =IF(SUMIFS($D$3:$D$200,$A$3:$A$200,A91,$E$3:$E$200,"<>")=SUMIFS($D$3:$D$200,$A$3:$A$200,A91,$F$3:$F$200,"<>"),"OK","ERROR") -> OK
A92: =IFERROR(__xludf.DUMMYFUNCTION("""COMPUTED_VALUE"""),"VVV-2024-075") -> VVV-2024-075 | B92: 45491 | C92: Retail camping-supply sales | D92: =IFERROR(__xludf.DUMMYFUNCTION("""COMPUTED_VALUE"""),6000.0) -> 6000 | E92: =IFERROR(__xludf.DUMMYFUNCTION("""COMPUTED_VALUE"""),"Cost of Goods Sold") -> Cost of Goods Sold | F92: =IFERROR(__xludf.DUMMYFUNCTION("""COMPUTED_VALUE"""),"Inventory") -> Inventory | H92: =IF(SUMIFS($D$3:$D$200,$A$3:$A$200,A92,$E$3:$E$200,"<>")=SUMIFS($D$3:$D$200,$A$3:$A$200,A92,$F$3:$F$200,"<>"),"OK","ERROR") -> OK
A93: =IFERROR(__xludf.DUMMYFUNCTION("""COMPUTED_VALUE"""),"VVV-2024-076") -> VVV-2024-076 | B93: 45493 | C93: Guided tour revenue | D93: =IFERROR(__xludf.DUMMYFUNCTION("""COMPUTED_VALUE"""),14000.0) -> 14000 | E93: =IFERROR(__xludf.DUMMYFUNCTION("""COMPUTED_VALUE"""),"Cash") -> Cash | F93: =IFERROR(__xludf.DUMMYFUNCTION("""COMPUTED_VALUE"""),"Tour Revenue") -> Tour Revenue | H93: =IF(SUMIFS($D$3:$D$200,$A$3:$A$200,A93,$E$3:$E$200,"<>")=SUMIFS($D$3:$D$200,$A$3:$A$200,A93,$F$3:$F$200,"<>"),"OK","ERROR") -> OK
A94: =IFERROR(__xludf.DUMMYFUNCTION("""COMPUTED_VALUE"""),"VVV-2024-077") -> VVV-2024-077 | B94: 45495 | C94: Seasonal event revenue | D94: =IFERROR(__xludf.DUMMYFUNCTION("""COMPUTED_VALUE"""),9000.0) -> 9000 | E94: =IFERROR(__xludf.DUMMYFUNCTION("""COMPUTED_VALUE"""),"Cash") -> Cash | F94: =IFERROR(__xludf.DUMMYFUNCTION("""COMPUTED_VALUE"""),"Event Revenue") -> Event Revenue | H94: =IF(SUMIFS($D$3:$D$200,$A$3:$A$200,A94,$E$3:$E$200,"<>")=SUMIFS($D$3:$D$200,$A$3:$A$200,A94,$F$3:$F$200,"<>"),"OK","ERROR") -> OK
A95: =IFERROR(__xludf.DUMMYFUNCTION("""COMPUTED_VALUE"""),"VVV-2024-078") -> VVV-2024-078 | B95: 45495 | C95: Purchased additional retail inventory | D95: =IFERROR(__xludf.DUMMYFUNCTION("""COMPUTED_VALUE"""),10000.0) -> 10000 | E95: =IFERROR(__xludf.DUMMYFUNCTION("""COMPUTED_VALUE"""),"Inventory") -> Inventory | F95: =IFERROR(__xludf.DUMMYFUNCTION("""COMPUTED_VALUE"""),"Cash") -> Cash | H95: =IF(SUMIFS($D$3:$D$200,$A$3:$A$200,A95,$E$3:$E$200,"<>")=SUMIFS($D$3:$D$200,$A$3:$A$200,A95,$F$3:$F$200,"<>"),"OK","ERROR") -> OK
A96: =IFERROR(__xludf.DUMMYFUNCTION("""COMPUTED_VALUE"""),"VVV-2024-079") -> VVV-2024-079 | B96: 45497 | C96: Employee payroll settlement | D96: =IFERROR(__xludf.DUMMYFUNCTION("""COMPUTED_VALUE"""),13280.0) -> 13280 | E96: =IFERROR(__xludf.DUMMYFUNCTION("""COMPUTED_VALUE"""),"Wages Expense") -> Wages Expense | F96: =IFERROR(__xludf.DUMMYFUNCTION("""COMPUTED_VALUE"""),"Cash") -> Cash | G96: includes E04's $200 travel claim | H96: =IF(SUMIFS($D$3:$D$200,$A$3:$A$200,A96,$E$3:$E$200,"<>")=SUMIFS($D$3:$D$200,$A$3:$A$200,A96,$F$3:$F$200,"<>"),"OK","ERROR") -> OK
A97: =IFERROR(__xludf.DUMMYFUNCTION("""COMPUTED_VALUE"""),"VVV-2024-080") -> VVV-2024-080 | B97: 45498 | C97: Bank loan instalment and interest paid | D97: =IFERROR(__xludf.DUMMYFUNCTION("""COMPUTED_VALUE"""),7500.0) -> 7500 | E97: =IFERROR(__xludf.DUMMYFUNCTION("""COMPUTED_VALUE"""),"Notes Payable") -> Notes Payable | F97: =IFERROR(__xludf.DUMMYFUNCTION("""COMPUTED_VALUE"""),"Cash") -> Cash | G97: clerk put it all as interest but 7500 is paying back the loan | H97: =IF(SUMIFS($D$3:$D$200,$A$3:$A$200,A97,$E$3:$E$200,"<>")=SUMIFS($D$3:$D$200,$A$3:$A$200,A97,$F$3:$F$200,"<>"),"OK","ERROR") -> OK
A98: =IFERROR(__xludf.DUMMYFUNCTION("""COMPUTED_VALUE"""),"VVV-2024-080") -> VVV-2024-080 | B98: 45498 | C98: Bank loan instalment and interest paid | D98: =IFERROR(__xludf.DUMMYFUNCTION("""COMPUTED_VALUE"""),1500.0) -> 1500 | E98: =IFERROR(__xludf.DUMMYFUNCTION("""COMPUTED_VALUE"""),"Interest Expense") -> Interest Expense | F98: =IFERROR(__xludf.DUMMYFUNCTION("""COMPUTED_VALUE"""),"Cash") -> Cash | H98: =IF(SUMIFS($D$3:$D$200,$A$3:$A$200,A98,$E$3:$E$200,"<>")=SUMIFS($D$3:$D$200,$A$3:$A$200,A98,$F$3:$F$200,"<>"),"OK","ERROR") -> OK
A99: =IFERROR(__xludf.DUMMYFUNCTION("""COMPUTED_VALUE"""),"VVV-2024-081") -> VVV-2024-081 | B99: 45504 | C99: Monthly utility settlement | D99: =IFERROR(__xludf.DUMMYFUNCTION("""COMPUTED_VALUE"""),1354.0) -> 1354 | E99: =IFERROR(__xludf.DUMMYFUNCTION("""COMPUTED_VALUE"""),"Utilities Expense") -> Utilities Expense | F99: =IFERROR(__xludf.DUMMYFUNCTION("""COMPUTED_VALUE"""),"Cash") -> Cash | H99: =IF(SUMIFS($D$3:$D$200,$A$3:$A$200,A99,$E$3:$E$200,"<>")=SUMIFS($D$3:$D$200,$A$3:$A$200,A99,$F$3:$F$200,"<>"),"OK","ERROR") -> OK
A100: =IFERROR(__xludf.DUMMYFUNCTION("""COMPUTED_VALUE"""),"VVV-2024-082") -> VVV-2024-082 | B100: 45505 | C100: Monthly facility rent | D100: =IFERROR(__xludf.DUMMYFUNCTION("""COMPUTED_VALUE"""),5400.0) -> 5400 | E100: =IFERROR(__xludf.DUMMYFUNCTION("""COMPUTED_VALUE"""),"Rent Expense") -> Rent Expense | F100: =IFERROR(__xludf.DUMMYFUNCTION("""COMPUTED_VALUE"""),"Cash") -> Cash | H100: =IF(SUMIFS($D$3:$D$200,$A$3:$A$200,A100,$E$3:$E$200,"<>")=SUMIFS($D$3:$D$200,$A$3:$A$200,A100,$F$3:$F$200,"<>"),"OK","ERROR") -> OK
...

Sheet Rules
A1: Keyword | B1: Debit_1 | C1: Credit_1 | D1: Amount_1 | E1: Debit_2 | F1: Credit_2 | G1: Amount_2 | H1: Debit_3 | I1: Credit_3 | J1: Amount_3 | K1: Why
A2: financed by seller | B2: Equipment | C2: Cash | D2: CASHPART | E2: Equipment | F2: Notes Payable | G2: FINANCED | K2: bikes last years -> equipment. part cash, rest owed to the seller (notes payable)
A3: business card; due | B3: Equipment | C3: Accounts Payable | D3: AMT | K3: POS lasts >1 yr -> equipment. paid by card so we owe it (AP)
A4: card balance | B4: Accounts Payable | C4: Cash | D4: AMT | K4: paying off the card, not a new expense
A5: fleet service and dispatch | B5: Repairs and Maintenance Expense | C5: Cash | D5: LABOUR | E5: School Group Expense | F5: Cash | G5: GROUP | K5: only workshop labour is repairs, shuttle/materials go to school group
A6: fleet service work order | B6: Repairs and Maintenance Expense | C6: Cash | D6: AMT | K6: fleet repairs
A7: fleet | B7: Equipment | C7: Cash | D7: AMT | K7: kayaks last years -> equipment
A8: facility equipment | B8: Equipment | C8: Cash | D8: AMT | K8: ours and lasts >1 yr -> equipment, not repairs
A9: payment to inventory supplier | B9: Accounts Payable | C9: Cash | D9: AMT | K9: paying the supplier back, reduces AP
A10: inventory on account | B10: Inventory | C10: Accounts Payable | D10: AMT | K10: stuff to resell, bought on credit
A11: inventory | B11: Inventory | C11: Cash | D11: AMT | K11: stuff to resell, paid cash
A12: fee withheld | B12: Cash | C12: Retail Sales Revenue | D12: NET | E12: Office and Admin Expense | F12: Retail Sales Revenue | G12: FEE | H12: Cost of Goods Sold | I12: Inventory | J12: COGS | K12: full 8000 is revenue, processor kept 240 (fee expense), goods leave inventory
A13: camping-supply sales | B13: Cash | C13: Retail Sales Revenue | D13: AMT | E13: Cost of Goods Sold | F13: Inventory | G13: COGS | K13: sale + cost of the goods comes out of inventory (COGS)
A14: capital contribution | B14: Cash | C14: Owner's Capital | D14: AMT | K14: owner puts money in
A15: security deposit | B15: Security Deposit | C15: Cash | D15: AMT | K15: refundable so it's an asset, not rent
A16: facility rent | B16: Rent Expense | C16: Cash | D16: AMT | K16: monthly rent
A17: license | B17: License and Permit Expense | C17: Cash | D17: AMT | K17: covers just 2024 so straight to expense
A18: loan proceeds | B18: Cash | C18: Notes Payable | D18: AMT | K18: loan not revenue, we have to pay it back
A19: loan instalment | B19: Notes Payable | C19: Cash | D19: PRINCIPAL | E19: Interest Expense | F19: Cash | G19: INTEREST | K19: principal pays back the loan, only the interest is an expense
A20: interest payment | B20: Interest Expense | C20: Cash | D20: AMT | K20: interest only, no principal
A21: insurance | B21: Insurance Expense | C21: Cash | D21: AMT | K21: monthly insurance
A22: office supplies | B22: Office and Admin Expense | C22: Cash | D22: AMT | K22: all used up in 2024
A23: advertising | B23: Marketing Expense | C23: Cash | D23: AMT | K23: ads
A24: payroll | B24: Wages Expense | C24: Cash | D24: AMT | K24: wages, includes E04's $200 travel claim
A25: utility | B25: Utilities Expense | C25: Cash | D25: AMT | K25: monthly utilities
A26: safety course | B26: Training Expense | C26: Cash | D26: AMT | K26: guide training
A27: rental receipts | B27: Cash | C27: Equipment Rental Revenue | D27: AMT | K27: rentals done and paid
A28: tour delivered; deposit applied | B28: Unearned Revenue | C28: Tour Revenue | D28: DEP | E28: Accounts Receivable | F28: Tour Revenue | G28: REST | K28: no cash today: feb deposit now earned + rest billed (AR)
A29: event completed; deposit applied | B29: Unearned Revenue | C29: Event Revenue | D29: DEP | E29: Cash | F29: Event Revenue | G29: REST | K29: april deposit now earned + rest paid now
A30: completed on account | B30: Accounts Receivable | C30: Tour Revenue | D30: AMT | K30: tour done so revenue now, cash later
A31: collected | B31: Cash | C31: Accounts Receivable | D31: AMT | K31: customer pays what they owed
A32: deposit | B32: Cash | C32: Unearned Revenue | D32: AMT | K32: paid before the service -> not earned yet (unearned)
A33: tour revenue | B33: Cash | C33: Tour Revenue | D33: AMT | K33: tours done and paid
A34: event revenue | B34: Cash | C34: Event Revenue | D34: AMT | K34: events done and paid

Sheet Entries
A1: Transaction_ID | B1: Amount | C1: Search_Text | D1: Rule_Row | E1: Matched_Keyword | F1: AMT | G1: COGS | H1: FEE | I1: NET | J1: INTEREST | K1: PRINCIPAL | L1: DEP | M1: REST | N1: CASHPART | O1: FINANCED | P1: LABOUR | Q1: GROUP | R1: Debit_1 | S1: Debit_2 | T1: Debit_3 | U1: Credit_1 | V1: Credit_2 | W1: Credit_3 | X1: Amount_1 | Y1: Amount_2 | Z1: Amount_3 | AA1: Why | AB1: Clerk_Check
A2: =Raw_Data!A2 -> VVV-2024-001 | B2: =Raw_Data!D2 -> 50000 | C2: =LOWER(Raw_Data!C2&" | "&Raw_Data!F2) -> initial owner capital contribution | owner funds received in business bank account | D2: {=MATCH(1,ISNUMBER(SEARCH(Rules!$A$2:$A$60,C2))*(Rules!$A$2:$A$60<>""),0)} -> 13 | E2: {=INDEX(Rules!$A$2:$A$60,D2)} -> capital contribution | F2: =B2 -> 50000 | G2: =IFERROR(__xludf.DUMMYFUNCTION("IFERROR(VALUE(SUBSTITUTE(REGEXEXTRACT(Raw_Data!J2,""Cost of goods sold: \$([\d,]+)""),"","","""")),0)"),0.0) -> 0 | H2: =IFERROR(__xludf.DUMMYFUNCTION("IFERROR(VALUE(SUBSTITUTE(REGEXEXTRACT(Raw_Data!J2,""withheld a \$([\d,]+) fee""),"","","""")),0)"),0.0) -> 0 | I2: =F2-H2 -> 50000 | J2: =IFERROR(__xludf.DUMMYFUNCTION("IFERROR(VALUE(SUBSTITUTE(REGEXEXTRACT(Raw_Data!J2,""(?i)interest \$([\d,]+)""),"","","""")),0)"),0.0) -> 0 | K2: =F2-J2 -> 50000 | L2: =IFERROR(__xludf.DUMMYFUNCTION("IFERROR(VALUE(SUBSTITUTE(REGEXEXTRACT(Raw_Data!F2,""\$([\d,]+) prior deposit applied""),"","","""")),0)"),0.0) -> 0 | M2: =F2-L2 -> 50000 | N2: =IFERROR(__xludf.DUMMYFUNCTION("IFERROR(VALUE(SUBSTITUTE(REGEXEXTRACT(Raw_Data!F2,""^\$([\d,]+) cash""),"","","""")),0)"),0.0) -> 0 | O2: =F2-N2 -> 50000 | P2: =IFERROR(__xludf.DUMMYFUNCTION("IFERROR(VALUE(SUBSTITUTE(REGEXEXTRACT(Raw_Data!J2,""labour \d+ h at \$\d+/h: \$([\d,]+)""),"","","""")),0)"),0.0) -> 0 | Q2: =F2-P2 -> 50000 | R2: {=IF(INDEX(Rules!$B$2:$B$60,$D2)="","",INDEX(Rules!$B$2:$B$60,$D2))} -> Cash | S2: {=IF(INDEX(Rules!$E$2:$E$60,$D2)="","",INDEX(Rules!$E$2:$E$60,$D2))} | T2: {=IF(INDEX(Rules!$H$2:$H$60,$D2)="","",INDEX(Rules!$H$2:$H$60,$D2))} | U2: {=IF(INDEX(Rules!$C$2:$C$60,$D2)="","",INDEX(Rules!$C$2:$C$60,$D2))} -> Owner's Capital | V2: {=IF(INDEX(Rules!$F$2:$F$60,$D2)="","",INDEX(Rules!$F$2:$F$60,$D2))} | W2: {=IF(INDEX(Rules!$I$2:$I$60,$D2)="","",INDEX(Rules!$I$2:$I$60,$D2))} | X2: {=IF(R2="","",INDEX($F2:$Q2,MATCH(INDEX(Rules!$D$2:$D$60,$D2),$F$1:$Q$1,0)))} -> 50000 | Y2: {=IF(S2="","",INDEX($F2:$Q2,MATCH(INDEX(Rules!$G$2:$G$60,$D2),$F$1:$Q$1,0)))} | Z2: {=IF(T2="","",INDEX($F2:$Q2,MATCH(INDEX(Rules!$J$2:$J$60,$D2),$F$1:$Q$1,0)))} | AA2: {=IF(INDEX(Rules!$K$2:$K$60,$D2)="","",INDEX(Rules!$K$2:$K$60,$D2))} -> owner puts money in | AB2: =IF(SUMPRODUCT((R2:W2<>"")*(ISNUMBER(SEARCH(Raw_Data!E2,R2:W2))+ISNUMBER(SEARCH(R2:W2,Raw_Data!E2))))>0,"OK","CHECK") -> OK
A3: =Raw_Data!A3 -> VVV-2024-002 | B3: =Raw_Data!D3 -> 5400 | C3: =LOWER(Raw_Data!C3&" | "&Raw_Data!F3) -> monthly facility rent | automatic bank transfer; settled | D3: {=MATCH(1,ISNUMBER(SEARCH(Rules!$A$2:$A$60,C3))*(Rules!$A$2:$A$60<>""),0)} -> 15 | E3: {=INDEX(Rules!$A$2:$A$60,D3)} -> facility rent | F3: =B3 -> 5400 | G3: =IFERROR(__xludf.DUMMYFUNCTION("IFERROR(VALUE(SUBSTITUTE(REGEXEXTRACT(Raw_Data!J3,""Cost of goods sold: \$([\d,]+)""),"","","""")),0)"),0.0) -> 0 | H3: =IFERROR(__xludf.DUMMYFUNCTION("IFERROR(VALUE(SUBSTITUTE(REGEXEXTRACT(Raw_Data!J3,""withheld a \$([\d,]+) fee""),"","","""")),0)"),0.0) -> 0 | I3: =F3-H3 -> 5400 | J3: =IFERROR(__xludf.DUMMYFUNCTION("IFERROR(VALUE(SUBSTITUTE(REGEXEXTRACT(Raw_Data!J3,""(?i)interest \$([\d,]+)""),"","","""")),0)"),0.0) -> 0 | K3: =F3-J3 -> 5400 | L3: =IFERROR(__xludf.DUMMYFUNCTION("IFERROR(VALUE(SUBSTITUTE(REGEXEXTRACT(Raw_Data!F3,""\$([\d,]+) prior deposit applied""),"","","""")),0)"),0.0) -> 0 | M3: =F3-L3 -> 5400 | N3: =IFERROR(__xludf.DUMMYFUNCTION("IFERROR(VALUE(SUBSTITUTE(REGEXEXTRACT(Raw_Data!F3,""^\$([\d,]+) cash""),"","","""")),0)"),0.0) -> 0 | O3: =F3-N3 -> 5400 | P3: =IFERROR(__xludf.DUMMYFUNCTION("IFERROR(VALUE(SUBSTITUTE(REGEXEXTRACT(Raw_Data!J3,""labour \d+ h at \$\d+/h: \$([\d,]+)""),"","","""")),0)"),0.0) -> 0 | Q3: =F3-P3 -> 5400 | R3: {=IF(INDEX(Rules!$B$2:$B$60,$D3)="","",INDEX(Rules!$B$2:$B$60,$D3))} -> Rent Expense | S3: {=IF(INDEX(Rules!$E$2:$E$60,$D3)="","",INDEX(Rules!$E$2:$E$60,$D3))} | T3: {=IF(INDEX(Rules!$H$2:$H$60,$D3)="","",INDEX(Rules!$H$2:$H$60,$D3))} | U3: {=IF(INDEX(Rules!$C$2:$C$60,$D3)="","",INDEX(Rules!$C$2:$C$60,$D3))} -> Cash | V3: {=IF(INDEX(Rules!$F$2:$F$60,$D3)="","",INDEX(Rules!$F$2:$F$60,$D3))} | W3: {=IF(INDEX(Rules!$I$2:$I$60,$D3)="","",INDEX(Rules!$I$2:$I$60,$D3))} | X3: {=IF(R3="","",INDEX($F3:$Q3,MATCH(INDEX(Rules!$D$2:$D$60,$D3),$F$1:$Q$1,0)))} -> 5400 | Y3: {=IF(S3="","",INDEX($F3:$Q3,MATCH(INDEX(Rules!$G$2:$G$60,$D3),$F$1:$Q$1,0)))} | Z3: {=IF(T3="","",INDEX($F3:$Q3,MATCH(INDEX(Rules!$J$2:$J$60,$D3),$F$1:$Q$1,0)))} | AA3: {=IF(INDEX(Rules!$K$2:$K$60,$D3)="","",INDEX(Rules!$K$2:$K$60,$D3))} -> monthly rent | AB3: =IF(SUMPRODUCT((R3:W3<>"")*(ISNUMBER(SEARCH(Raw_Data!E3,R3:W3))+ISNUMBER(SEARCH(R3:W3,Raw_Data!E3))))>0,"OK","CHECK") -> OK
A4: =Raw_Data!A4 -> VVV-2024-003 | B4: =Raw_Data!D4 -> 1500 | C4: =LOWER(Raw_Data!C4&" | "&Raw_Data!F4) -> annual business license and operating permits | business debit card; settled | D4: {=MATCH(1,ISNUMBER(SEARCH(Rules!$A$2:$A$60,C4))*(Rules!$A$2:$A$60<>""),0)} -> 16 | E4: {=INDEX(Rules!$A$2:$A$60,D4)} -> license | F4: =B4 -> 1500 | G4: =IFERROR(__xludf.DUMMYFUNCTION("IFERROR(VALUE(SUBSTITUTE(REGEXEXTRACT(Raw_Data!J4,""Cost of goods sold: \$([\d,]+)""),"","","""")),0)"),0.0) -> 0 | H4: =IFERROR(__xludf.DUMMYFUNCTION("IFERROR(VALUE(SUBSTITUTE(REGEXEXTRACT(Raw_Data!J4,""withheld a \$([\d,]+) fee""),"","","""")),0)"),0.0) -> 0 | I4: =F4-H4 -> 1500 | J4: =IFERROR(__xludf.DUMMYFUNCTION("IFERROR(VALUE(SUBSTITUTE(REGEXEXTRACT(Raw_Data!J4,""(?i)interest \$([\d,]+)""),"","","""")),0)"),0.0) -> 0 | K4: =F4-J4 -> 1500 | L4: =IFERROR(__xludf.DUMMYFUNCTION("IFERROR(VALUE(SUBSTITUTE(REGEXEXTRACT(Raw_Data!F4,""\$([\d,]+) prior deposit applied""),"","","""")),0)"),0.0) -> 0 | M4: =F4-L4 -> 1500 | N4: =IFERROR(__xludf.DUMMYFUNCTION("IFERROR(VALUE(SUBSTITUTE(REGEXEXTRACT(Raw_Data!F4,""^\$([\d,]+) cash""),"","","""")),0)"),0.0) -> 0 | O4: =F4-N4 -> 1500 | P4: =IFERROR(__xludf.DUMMYFUNCTION("IFERROR(VALUE(SUBSTITUTE(REGEXEXTRACT(Raw_Data!J4,""labour \d+ h at \$\d+/h: \$([\d,]+)""),"","","""")),0)"),0.0) -> 0 | Q4: =F4-P4 -> 1500 | R4: {=IF(INDEX(Rules!$B$2:$B$60,$D4)="","",INDEX(Rules!$B$2:$B$60,$D4))} -> License and Permit Expense | S4: {=IF(INDEX(Rules!$E$2:$E$60,$D4)="","",INDEX(Rules!$E$2:$E$60,$D4))} | T4: {=IF(INDEX(Rules!$H$2:$H$60,$D4)="","",INDEX(Rules!$H$2:$H$60,$D4))} | U4: {=IF(INDEX(Rules!$C$2:$C$60,$D4)="","",INDEX(Rules!$C$2:$C$60,$D4))} -> Cash | V4: {=IF(INDEX(Rules!$F$2:$F$60,$D4)="","",INDEX(Rules!$F$2:$F$60,$D4))} | W4: {=IF(INDEX(Rules!$I$2:$I$60,$D4)="","",INDEX(Rules!$I$2:$I$60,$D4))} | X4: {=IF(R4="","",INDEX($F4:$Q4,MATCH(INDEX(Rules!$D$2:$D$60,$D4),$F$1:$Q$1,0)))} -> 1500 | Y4: {=IF(S4="","",INDEX($F4:$Q4,MATCH(INDEX(Rules!$G$2:$G$60,$D4),$F$1:$Q$1,0)))} | Z4: {=IF(T4="","",INDEX($F4:$Q4,MATCH(INDEX(Rules!$J$2:$J$60,$D4),$F$1:$Q$1,0)))} | AA4: {=IF(INDEX(Rules!$K$2:$K$60,$D4)="","",INDEX(Rules!$K$2:$K$60,$D4))} -> covers just 2024 so straight to expense | AB4: =IF(SUMPRODUCT((R4:W4<>"")*(ISNUMBER(SEARCH(Raw_Data!E4,R4:W4))+ISNUMBER(SEARCH(R4:W4,Raw_Data!E4))))>0,"OK","CHECK") -> OK
A5: =Raw_Data!A5 -> VVV-2024-004 | B5: =Raw_Data!D5 -> 6000 | C5: =LOWER(Raw_Data!C5&" | "&Raw_Data!F5) -> refundable facility security deposit | bank transfer; refundable at lease end | D5: {=MATCH(1,ISNUMBER(SEARCH(Rules!$A$2:$A$60,C5))*(Rules!$A$2:$A$60<>""),0)} -> 14 | E5: {=INDEX(Rules!$A$2:$A$60,D5)} -> security deposit | F5: =B5 -> 6000 | G5: =IFERROR(__xludf.DUMMYFUNCTION("IFERROR(VALUE(SUBSTITUTE(REGEXEXTRACT(Raw_Data!J5,""Cost of goods sold: \$([\d,]+)""),"","","""")),0)"),0.0) -> 0 | H5: =IFERROR(__xludf.DUMMYFUNCTION("IFERROR(VALUE(SUBSTITUTE(REGEXEXTRACT(Raw_Data!J5,""withheld a \$([\d,]+) fee""),"","","""")),0)"),0.0) -> 0 | I5: =F5-H5 -> 6000 | J5: =IFERROR(__xludf.DUMMYFUNCTION("IFERROR(VALUE(SUBSTITUTE(REGEXEXTRACT(Raw_Data!J5,""(?i)interest \$([\d,]+)""),"","","""")),0)"),0.0) -> 0 | K5: =F5-J5 -> 6000 | L5: =IFERROR(__xludf.DUMMYFUNCTION("IFERROR(VALUE(SUBSTITUTE(REGEXEXTRACT(Raw_Data!F5,""\$([\d,]+) prior deposit applied""),"","","""")),0)"),0.0) -> 0 | M5: =F5-L5 -> 6000 | N5: =IFERROR(__xludf.DUMMYFUNCTION("IFERROR(VALUE(SUBSTITUTE(REGEXEXTRACT(Raw_Data!F5,""^\$([\d,]+) cash""),"","","""")),0)"),0.0) -> 0 | O5: =F5-N5 -> 6000 | P5: =IFERROR(__xludf.DUMMYFUNCTION("IFERROR(VALUE(SUBSTITUTE(REGEXEXTRACT(Raw_Data!J5,""labour \d+ h at \$\d+/h: \$([\d,]+)""),"","","""")),0)"),0.0) -> 0 | Q5: =F5-P5 -> 6000 | R5: {=IF(INDEX(Rules!$B$2:$B$60,$D5)="","",INDEX(Rules!$B$2:$B$60,$D5))} -> Security Deposit | S5: {=IF(INDEX(Rules!$E$2:$E$60,$D5)="","",INDEX(Rules!$E$2:$E$60,$D5))} | T5: {=IF(INDEX(Rules!$H$2:$H$60,$D5)="","",INDEX(Rules!$H$2:$H$60,$D5))} | U5: {=IF(INDEX(Rules!$C$2:$C$60,$D5)="","",INDEX(Rules!$C$2:$C$60,$D5))} -> Cash | V5: {=IF(INDEX(Rules!$F$2:$F$60,$D5)="","",INDEX(Rules!$F$2:$F$60,$D5))} | W5: {=IF(INDEX(Rules!$I$2:$I$60,$D5)="","",INDEX(Rules!$I$2:$I$60,$D5))} | X5: {=IF(R5="","",INDEX($F5:$Q5,MATCH(INDEX(Rules!$D$2:$D$60,$D5),$F$1:$Q$1,0)))} -> 6000 | Y5: {=IF(S5="","",INDEX($F5:$Q5,MATCH(INDEX(Rules!$G$2:$G$60,$D5),$F$1:$Q$1,0)))} | Z5: {=IF(T5="","",INDEX($F5:$Q5,MATCH(INDEX(Rules!$J$2:$J$60,$D5),$F$1:$Q$1,0)))} | AA5: {=IF(INDEX(Rules!$K$2:$K$60,$D5)="","",INDEX(Rules!$K$2:$K$60,$D5))} -> refundable so it's an asset, not rent | AB5: =IF(SUMPRODUCT((R5:W5<>"")*(ISNUMBER(SEARCH(Raw_Data!E5,R5:W5))+ISNUMBER(SEARCH(R5:W5,Raw_Data!E5))))>0,"OK","CHECK") -> CHECK
A6: =Raw_Data!A6 -> VVV-2024-005 | B6: =Raw_Data!D6 -> 50000 | C6: =LOWER(Raw_Data!C6&" | "&Raw_Data!F6) -> bank loan proceeds received | five-year note; cash received | D6: {=MATCH(1,ISNUMBER(SEARCH(Rules!$A$2:$A$60,C6))*(Rules!$A$2:$A$60<>""),0)} -> 17 | E6: {=INDEX(Rules!$A$2:$A$60,D6)} -> loan proceeds | F6: =B6 -> 50000 | G6: =IFERROR(__xludf.DUMMYFUNCTION("IFERROR(VALUE(SUBSTITUTE(REGEXEXTRACT(Raw_Data!J6,""Cost of goods sold: \$([\d,]+)""),"","","""")),0)"),0.0) -> 0 | H6: =IFERROR(__xludf.DUMMYFUNCTION("IFERROR(VALUE(SUBSTITUTE(REGEXEXTRACT(Raw_Data!J6,""withheld a \$([\d,]+) fee""),"","","""")),0)"),0.0) -> 0 | I6: =F6-H6 -> 50000 | J6: =IFERROR(__xludf.DUMMYFUNCTION("IFERROR(VALUE(SUBSTITUTE(REGEXEXTRACT(Raw_Data!J6,""(?i)interest \$([\d,]+)""),"","","""")),0)"),0.0) -> 0 | K6: =F6-J6 -> 50000 | L6: =IFERROR(__xludf.DUMMYFUNCTION("IFERROR(VALUE(SUBSTITUTE(REGEXEXTRACT(Raw_Data!F6,""\$([\d,]+) prior deposit applied""),"","","""")),0)"),0.0) -> 0 | M6: =F6-L6 -> 50000 | N6: =IFERROR(__xludf.DUMMYFUNCTION("IFERROR(VALUE(SUBSTITUTE(REGEXEXTRACT(Raw_Data!F6,""^\$([\d,]+) cash""),"","","""")),0)"),0.0) -> 0 | O6: =F6-N6 -> 50000 | P6: =IFERROR(__xludf.DUMMYFUNCTION("IFERROR(VALUE(SUBSTITUTE(REGEXEXTRACT(Raw_Data!J6,""labour \d+ h at \$\d+/h: \$([\d,]+)""),"","","""")),0)"),0.0) -> 0 | Q6: =F6-P6 -> 50000 | R6: {=IF(INDEX(Rules!$B$2:$B$60,$D6)="","",INDEX(Rules!$B$2:$B$60,$D6))} -> Cash | S6: {=IF(INDEX(Rules!$E$2:$E$60,$D6)="","",INDEX(Rules!$E$2:$E$60,$D6))} | T6: {=IF(INDEX(Rules!$H$2:$H$60,$D6)="","",INDEX(Rules!$H$2:$H$60,$D6))} | U6: {=IF(INDEX(Rules!$C$2:$C$60,$D6)="","",INDEX(Rules!$C$2:$C$60,$D6))} -> Notes Payable | V6: {=IF(INDEX(Rules!$F$2:$F$60,$D6)="","",INDEX(Rules!$F$2:$F$60,$D6))} | W6: {=IF(INDEX(Rules!$I$2:$I$60,$D6)="","",INDEX(Rules!$I$2:$I$60,$D6))} | X6: {=IF(R6="","",INDEX($F6:$Q6,MATCH(INDEX(Rules!$D$2:$D$60,$D6),$F$1:$Q$1,0)))} -> 50000 | Y6: {=IF(S6="","",INDEX($F6:$Q6,MATCH(INDEX(Rules!$G$2:$G$60,$D6),$F$1:$Q$1,0)))} | Z6: {=IF(T6="","",INDEX($F6:$Q6,MATCH(INDEX(Rules!$J$2:$J$60,$D6),$F$1:$Q$1,0)))} | AA6: {=IF(INDEX(Rules!$K$2:$K$60,$D6)="","",INDEX(Rules!$K$2:$K$60,$D6))} -> loan not revenue, we have to pay it back | AB6: =IF(SUMPRODUCT((R6:W6<>"")*(ISNUMBER(SEARCH(Raw_Data!E6,R6:W6))+ISNUMBER(SEARCH(R6:W6,Raw_Data!E6))))>0,"OK","CHECK") -> CHECK
A7: =Raw_Data!A7 -> VVV-2024-006 | B7: =Raw_Data!D7 -> 600 | C7: =LOWER(Raw_Data!C7&" | "&Raw_Data!F7) -> monthly business insurance premium | automatic bank transfer; settled | D7: {=MATCH(1,ISNUMBER(SEARCH(Rules!$A$2:$A$60,C7))*(Rules!$A$2:$A$60<>""),0)} -> 20 | E7: {=INDEX(Rules!$A$2:$A$60,D7)} -> insurance | F7: =B7 -> 600 | G7: =IFERROR(__xludf.DUMMYFUNCTION("IFERROR(VALUE(SUBSTITUTE(REGEXEXTRACT(Raw_Data!J7,""Cost of goods sold: \$([\d,]+)""),"","","""")),0)"),0.0) -> 0 | H7: =IFERROR(__xludf.DUMMYFUNCTION("IFERROR(VALUE(SUBSTITUTE(REGEXEXTRACT(Raw_Data!J7,""withheld a \$([\d,]+) fee""),"","","""")),0)"),0.0) -> 0 | I7: =F7-H7 -> 600 | J7: =IFERROR(__xludf.DUMMYFUNCTION("IFERROR(VALUE(SUBSTITUTE(REGEXEXTRACT(Raw_Data!J7,""(?i)interest \$([\d,]+)""),"","","""")),0)"),0.0) -> 0 | K7: =F7-J7 -> 600 | L7: =IFERROR(__xludf.DUMMYFUNCTION("IFERROR(VALUE(SUBSTITUTE(REGEXEXTRACT(Raw_Data!F7,""\$([\d,]+) prior deposit applied""),"","","""")),0)"),0.0) -> 0 | M7: =F7-L7 -> 600 | N7: =IFERROR(__xludf.DUMMYFUNCTION("IFERROR(VALUE(SUBSTITUTE(REGEXEXTRACT(Raw_Data!F7,""^\$([\d,]+) cash""),"","","""")),0)"),0.0) -> 0 | O7: =F7-N7 -> 600 | P7: =IFERROR(__xludf.DUMMYFUNCTION("IFERROR(VALUE(SUBSTITUTE(REGEXEXTRACT(Raw_Data!J7,""labour \d+ h at \$\d+/h: \$([\d,]+)""),"","","""")),0)"),0.0) -> 0 | Q7: =F7-P7 -> 600 | R7: {=IF(INDEX(Rules!$B$2:$B$60,$D7)="","",INDEX(Rules!$B$2:$B$60,$D7))} -> Insurance Expense | S7: {=IF(INDEX(Rules!$E$2:$E$60,$D7)="","",INDEX(Rules!$E$2:$E$60,$D7))} | T7: {=IF(INDEX(Rules!$H$2:$H$60,$D7)="","",INDEX(Rules!$H$2:$H$60,$D7))} | U7: {=IF(INDEX(Rules!$C$2:$C$60,$D7)="","",INDEX(Rules!$C$2:$C$60,$D7))} -> Cash | V7: {=IF(INDEX(Rules!$F$2:$F$60,$D7)="","",INDEX(Rules!$F$2:$F$60,$D7))} | W7: {=IF(INDEX(Rules!$I$2:$I$60,$D7)="","",INDEX(Rules!$I$2:$I$60,$D7))} | X7: {=IF(R7="","",INDEX($F7:$Q7,MATCH(INDEX(Rules!$D$2:$D$60,$D7),$F$1:$Q$1,0)))} -> 600 | Y7: {=IF(S7="","",INDEX($F7:$Q7,MATCH(INDEX(Rules!$G$2:$G$60,$D7),$F$1:$Q$1,0)))} | Z7: {=IF(T7="","",INDEX($F7:$Q7,MATCH(INDEX(Rules!$J$2:$J$60,$D7),$F$1:$Q$1,0)))} | AA7: {=IF(INDEX(Rules!$K$2:$K$60,$D7)="","",INDEX(Rules!$K$2:$K$60,$D7))} -> monthly insurance | AB7: =IF(SUMPRODUCT((R7:W7<>"")*(ISNUMBER(SEARCH(Raw_Data!E7,R7:W7))+ISNUMBER(SEARCH(R7:W7,Raw_Data!E7))))>0,"OK","CHECK") -> OK
A8: =Raw_Data!A8 -> VVV-2024-007 | B8: =Raw_Data!D8 -> 30000 | C8: =LOWER(Raw_Data!C8&" | "&Raw_Data!F8) -> purchased mountain-bike fleet | $10,000 cash; $20,000 financed by seller | D8: {=MATCH(1,ISNUMBER(SEARCH(Rules!$A$2:$A$60,C8))*(Rules!$A$2:$A$60<>""),0)} -> 1 | E8: {=INDEX(Rules!$A$2:$A$60,D8)} -> financed by seller | F8: =B8 -> 30000 | G8: =IFERROR(__xludf.DUMMYFUNCTION("IFERROR(VALUE(SUBSTITUTE(REGEXEXTRACT(Raw_Data!J8,""Cost of goods sold: \$([\d,]+)""),"","","""")),0)"),0.0) -> 0 | H8: =IFERROR(__xludf.DUMMYFUNCTION("IFERROR(VALUE(SUBSTITUTE(REGEXEXTRACT(Raw_Data!J8,""withheld a \$([\d,]+) fee""),"","","""")),0)"),0.0) -> 0 | I8: =F8-H8 -> 30000 | J8: =IFERROR(__xludf.DUMMYFUNCTION("IFERROR(VALUE(SUBSTITUTE(REGEXEXTRACT(Raw_Data!J8,""(?i)interest \$([\d,]+)""),"","","""")),0)"),0.0) -> 0 | K8: =F8-J8 -> 30000 | L8: =IFERROR(__xludf.DUMMYFUNCTION("IFERROR(VALUE(SUBSTITUTE(REGEXEXTRACT(Raw_Data!F8,""\$([\d,]+) prior deposit applied""),"","","""")),0)"),0.0) -> 0 | M8: =F8-L8 -> 30000 | N8: =IFERROR(__xludf.DUMMYFUNCTION("IFERROR(VALUE(SUBSTITUTE(REGEXEXTRACT(Raw_Data!F8,""^\$([\d,]+) cash""),"","","""")),0)"),10000.0) -> 10000 | O8: =F8-N8 -> 20000 | P8: =IFERROR(__xludf.DUMMYFUNCTION("IFERROR(VALUE(SUBSTITUTE(REGEXEXTRACT(Raw_Data!J8,""labour \d+ h at \$\d+/h: \$([\d,]+)""),"","","""")),0)"),0.0) -> 0 | Q8: =F8-P8 -> 30000 | R8: {=IF(INDEX(Rules!$B$2:$B$60,$D8)="","",INDEX(Rules!$B$2:$B$60,$D8))} -> Equipment | S8: {=IF(INDEX(Rules!$E$2:$E$60,$D8)="","",INDEX(Rules!$E$2:$E$60,$D8))} -> Equipment | T8: {=IF(INDEX(Rules!$H$2:$H$60,$D8)="","",INDEX(Rules!$H$2:$H$60,$D8))} | U8: {=IF(INDEX(Rules!$C$2:$C$60,$D8)="","",INDEX(Rules!$C$2:$C$60,$D8))} -> Cash | V8: {=IF(INDEX(Rules!$F$2:$F$60,$D8)="","",INDEX(Rules!$F$2:$F$60,$D8))} -> Notes Payable | W8: {=IF(INDEX(Rules!$I$2:$I$60,$D8)="","",INDEX(Rules!$I$2:$I$60,$D8))} | X8: {=IF(R8="","",INDEX($F8:$Q8,MATCH(INDEX(Rules!$D$2:$D$60,$D8),$F$1:$Q$1,0)))} -> 10000 | Y8: {=IF(S8="","",INDEX($F8:$Q8,MATCH(INDEX(Rules!$G$2:$G$60,$D8),$F$1:$Q$1,0)))} -> 20000 | Z8: {=IF(T8="","",INDEX($F8:$Q8,MATCH(INDEX(Rules!$J$2:$J$60,$D8),$F$1:$Q$1,0)))} | AA8: {=IF(INDEX(Rules!$K$2:$K$60,$D8)="","",INDEX(Rules!$K$2:$K$60,$D8))} -> bikes last years -> equipment. part cash, rest owed to the seller (notes payable) | AB8: =IF(SUMPRODUCT((R8:W8<>"")*(ISNUMBER(SEARCH(Raw_Data!E8,R8:W8))+ISNUMBER(SEARCH(R8:W8,Raw_Data!E8))))>0,"OK","CHECK") -> CHECK
A9: =Raw_Data!A9 -> VVV-2024-008 | B9: =Raw_Data!D9 -> 18000 | C9: =LOWER(Raw_Data!C9&" | "&Raw_Data!F9) -> purchased kayak fleet | bank transfer; settled | D9: {=MATCH(1,ISNUMBER(SEARCH(Rules!$A$2:$A$60,C9))*(Rules!$A$2:$A$60<>""),0)} -> 6 | E9: {=INDEX(Rules!$A$2:$A$60,D9)} -> fleet | F9: =B9 -> 18000 | G9: =IFERROR(__xludf.DUMMYFUNCTION("IFERROR(VALUE(SUBSTITUTE(REGEXEXTRACT(Raw_Data!J9,""Cost of goods sold: \$([\d,]+)""),"","","""")),0)"),0.0) -> 0 | H9: =IFERROR(__xludf.DUMMYFUNCTION("IFERROR(VALUE(SUBSTITUTE(REGEXEXTRACT(Raw_Data!J9,""withheld a \$([\d,]+) fee""),"","","""")),0)"),0.0) -> 0 | I9: =F9-H9 -> 18000 | J9: =IFERROR(__xludf.DUMMYFUNCTION("IFERROR(VALUE(SUBSTITUTE(REGEXEXTRACT(Raw_Data!J9,""(?i)interest \$([\d,]+)""),"","","""")),0)"),0.0) -> 0 | K9: =F9-J9 -> 18000 | L9: =IFERROR(__xludf.DUMMYFUNCTION("IFERROR(VALUE(SUBSTITUTE(REGEXEXTRACT(Raw_Data!F9,""\$([\d,]+) prior deposit applied""),"","","""")),0)"),0.0) -> 0 | M9: =F9-L9 -> 18000 | N9: =IFERROR(__xludf.DUMMYFUNCTION("IFERROR(VALUE(SUBSTITUTE(REGEXEXTRACT(Raw_Data!F9,""^\$([\d,]+) cash""),"","","""")),0)"),0.0) -> 0 | O9: =F9-N9 -> 18000 | P9: =IFERROR(__xludf.DUMMYFUNCTION("IFERROR(VALUE(SUBSTITUTE(REGEXEXTRACT(Raw_Data!J9,""labour \d+ h at \$\d+/h: \$([\d,]+)""),"","","""")),0)"),0.0) -> 0 | Q9: =F9-P9 -> 18000 | R9: {=IF(INDEX(Rules!$B$2:$B$60,$D9)="","",INDEX(Rules!$B$2:$B$60,$D9))} -> Equipment | S9: {=IF(INDEX(Rules!$E$2:$E$60,$D9)="","",INDEX(Rules!$E$2:$E$60,$D9))} | T9: {=IF(INDEX(Rules!$H$2:$H$60,$D9)="","",INDEX(Rules!$H$2:$H$60,$D9))} | U9: {=IF(INDEX(Rules!$C$2:$C$60,$D9)="","",INDEX(Rules!$C$2:$C$60,$D9))} -> Cash | V9: {=IF(INDEX(Rules!$F$2:$F$60,$D9)="","",INDEX(Rules!$F$2:$F$60,$D9))} | W9: {=IF(INDEX(Rules!$I$2:$I$60,$D9)="","",INDEX(Rules!$I$2:$I$60,$D9))} | X9: {=IF(R9="","",INDEX($F9:$Q9,MATCH(INDEX(Rules!$D$2:$D$60,$D9),$F$1:$Q$1,0)))} -> 18000 | Y9: {=IF(S9="","",INDEX($F9:$Q9,MATCH(INDEX(Rules!$G$2:$G$60,$D9),$F$1:$Q$1,0)))} | Z9: {=IF(T9="","",INDEX($F9:$Q9,MATCH(INDEX(Rules!$J$2:$J$60,$D9),$F$1:$Q$1,0)))} | AA9: {=IF(INDEX(Rules!$K$2:$K$60,$D9)="","",INDEX(Rules!$K$2:$K$60,$D9))} -> kayaks last years -> equipment | AB9: =IF(SUMPRODUCT((R9:W9<>"")*(ISNUMBER(SEARCH(Raw_Data!E9,R9:W9))+ISNUMBER(SEARCH(R9:W9,Raw_Data!E9))))>0,"OK","CHECK") -> OK
A10: =Raw_Data!A10 -> VVV-2024-009 | B10: =Raw_Data!D10 -> 5000 | C10: =LOWER(Raw_Data!C10&" | "&Raw_Data!F10) -> purchased computer and point-of-sale system | business card; due next month | D10: {=MATCH(1,ISNUMBER(SEARCH(Rules!$A$2:$A$60,C10))*(Rules!$A$2:$A$60<>""),0)} -> 2 | E10: {=INDEX(Rules!$A$2:$A$60,D10)} -> business card; due | F10: =B10 -> 5000 | G10: =IFERROR(__xludf.DUMMYFUNCTION("IFERROR(VALUE(SUBSTITUTE(REGEXEXTRACT(Raw_Data!J10,""Cost of goods sold: \$([\d,]+)""),"","","""")),0)"),0.0) -> 0 | H10: =IFERROR(__xludf.DUMMYFUNCTION("IFERROR(VALUE(SUBSTITUTE(REGEXEXTRACT(Raw_Data!J10,""withheld a \$([\d,]+) fee""),"","","""")),0)"),0.0) -> 0 | I10: =F10-H10 -> 5000 | J10: =IFERROR(__xludf.DUMMYFUNCTION("IFERROR(VALUE(SUBSTITUTE(REGEXEXTRACT(Raw_Data!J10,""(?i)interest \$([\d,]+)""),"","","""")),0)"),0.0) -> 0 | K10: =F10-J10 -> 5000 | L10: =IFERROR(__xludf.DUMMYFUNCTION("IFERROR(VALUE(SUBSTITUTE(REGEXEXTRACT(Raw_Data!F10,""\$([\d,]+) prior deposit applied""),"","","""")),0)"),0.0) -> 0 | M10: =F10-L10 -> 5000 | N10: =IFERROR(__xludf.DUMMYFUNCTION("IFERROR(VALUE(SUBSTITUTE(REGEXEXTRACT(Raw_Data!F10,""^\$([\d,]+) cash""),"","","""")),0)"),0.0) -> 0 | O10: =F10-N10 -> 5000 | P10: =IFERROR(__xludf.DUMMYFUNCTION("IFERROR(VALUE(SUBSTITUTE(REGEXEXTRACT(Raw_Data!J10,""labour \d+ h at \$\d+/h: \$([\d,]+)""),"","","""")),0)"),0.0) -> 0 | Q10: =F10-P10 -> 5000 | R10: {=IF(INDEX(Rules!$B$2:$B$60,$D10)="","",INDEX(Rules!$B$2:$B$60,$D10))} -> Equipment | S10: {=IF(INDEX(Rules!$E$2:$E$60,$D10)="","",INDEX(Rules!$E$2:$E$60,$D10))} | T10: {=IF(INDEX(Rules!$H$2:$H$60,$D10)="","",INDEX(Rules!$H$2:$H$60,$D10))} | U10: {=IF(INDEX(Rules!$C$2:$C$60,$D10)="","",INDEX(Rules!$C$2:$C$60,$D10))} -> Accounts Payable | V10: {=IF(INDEX(Rules!$F$2:$F$60,$D10)="","",INDEX(Rules!$F$2:$F$60,$D10))} | W10: {=IF(INDEX(Rules!$I$2:$I$60,$D10)="","",INDEX(Rules!$I$2:$I$60,$D10))} | X10: {=IF(R10="","",INDEX($F10:$Q10,MATCH(INDEX(Rules!$D$2:$D$60,$D10),$F$1:$Q$1,0)))} -> 5000 | Y10: {=IF(S10="","",INDEX($F10:$Q10,MATCH(INDEX(Rules!$G$2:$G$60,$D10),$F$1:$Q$1,0)))} | Z10: {=IF(T10="","",INDEX($F10:$Q10,MATCH(INDEX(Rules!$J$2:$J$60,$D10),$F$1:$Q$1,0)))} | AA10: {=IF(INDEX(Rules!$K$2:$K$60,$D10)="","",INDEX(Rules!$K$2:$K$60,$D10))} -> POS lasts >1 yr -> equipment. paid by card so we owe it (AP) | AB10: =IF(SUMPRODUCT((R10:W10<>"")*(ISNUMBER(SEARCH(Raw_Data!E10,R10:W10))+ISNUMBER(SEARCH(R10:W10,Raw_Data!E10))))>0,"OK","CHECK") -> CHECK
A11: =Raw_Data!A11 -> VVV-2024-010 | B11: =Raw_Data!D11 -> 4500 | C11: =LOWER(Raw_Data!C11&" | "&Raw_Data!F11) -> equipment rental receipts batch | cash and card receipts; settled | D11: {=MATCH(1,ISNUMBER(SEARCH(Rules!$A$2:$A$60,C11))*(Rules!$A$2:$A$60<>""),0)} -> 26 | E11: {=INDEX(Rules!$A$2:$A$60,D11)} -> rental receipts | F11: =B11 -> 4500 | G11: =IFERROR(__xludf.DUMMYFUNCTION("IFERROR(VALUE(SUBSTITUTE(REGEXEXTRACT(Raw_Data!J11,""Cost of goods sold: \$([\d,]+)""),"","","""")),0)"),0.0) -> 0 | H11: =IFERROR(__xludf.DUMMYFUNCTION("IFERROR(VALUE(SUBSTITUTE(REGEXEXTRACT(Raw_Data!J11,""withheld a \$([\d,]+) fee""),"","","""")),0)"),0.0) -> 0 | I11: =F11-H11 -> 4500 | J11: =IFERROR(__xludf.DUMMYFUNCTION("IFERROR(VALUE(SUBSTITUTE(REGEXEXTRACT(Raw_Data!J11,""(?i)interest \$([\d,]+)""),"","","""")),0)"),0.0) -> 0 | K11: =F11-J11 -> 4500 | L11: =IFERROR(__xludf.DUMMYFUNCTION("IFERROR(VALUE(SUBSTITUTE(REGEXEXTRACT(Raw_Data!F11,""\$([\d,]+) prior deposit applied""),"","","""")),0)"),0.0) -> 0 | M11: =F11-L11 -> 4500 | N11: =IFERROR(__xludf.DUMMYFUNCTION("IFERROR(VALUE(SUBSTITUTE(REGEXEXTRACT(Raw_Data!F11,""^\$([\d,]+) cash""),"","","""")),0)"),0.0) -> 0 | O11: =F11-N11 -> 4500 | P11: =IFERROR(__xludf.DUMMYFUNCTION("IFERROR(VALUE(SUBSTITUTE(REGEXEXTRACT(Raw_Data!J11,""labour \d+ h at \$\d+/h: \$([\d,]+)""),"","","""")),0)"),0.0) -> 0 | Q11: =F11-P11 -> 4500 | R11: {=IF(INDEX(Rules!$B$2:$B$60,$D11)="","",INDEX(Rules!$B$2:$B$60,$D11))} -> Cash | S11: {=IF(INDEX(Rules!$E$2:$E$60,$D11)="","",INDEX(Rules!$E$2:$E$60,$D11))} | T11: {=IF(INDEX(Rules!$H$2:$H$60,$D11)="","",INDEX(Rules!$H$2:$H$60,$D11))} | U11: {=IF(INDEX(Rules!$C$2:$C$60,$D11)="","",INDEX(Rules!$C$2:$C$60,$D11))} -> Equipment Rental Revenue | V11: {=IF(INDEX(Rules!$F$2:$F$60,$D11)="","",INDEX(Rules!$F$2:$F$60,$D11))} | W11: {=IF(INDEX(Rules!$I$2:$I$60,$D11)="","",INDEX(Rules!$I$2:$I$60,$D11))} | X11: {=IF(R11="","",INDEX($F11:$Q11,MATCH(INDEX(Rules!$D$2:$D$60,$D11),$F$1:$Q$1,0)))} -> 4500 | Y11: {=IF(S11="","",INDEX($F11:$Q11,MATCH(INDEX(Rules!$G$2:$G$60,$D11),$F$1:$Q$1,0)))} | Z11: {=IF(T11="","",INDEX($F11:$Q11,MATCH(INDEX(Rules!$J$2:$J$60,$D11),$F$1:$Q$1,0)))} | AA11: {=IF(INDEX(Rules!$K$2:$K$60,$D11)="","",INDEX(Rules!$K$2:$K$60,$D11))} -> rentals done and paid | AB11: =IF(SUMPRODUCT((R11:W11<>"")*(ISNUMBER(SEARCH(Raw_Data!E11,R11:W11))+ISNUMBER(SEARCH(R11:W11,Raw_Data!E11))))>0,"OK","CHECK") -> OK
A12: =Raw_Data!A12 -> VVV-2024-011 | B12: =Raw_Data!D12 -> 1800 | C12: =LOWER(Raw_Data!C12&" | "&Raw_Data!F12) -> purchased office supplies | business debit card; settled | D12: {=MATCH(1,ISNUMBER(SEARCH(Rules!$A$2:$A$60,C12))*(Rules!$A$2:$A$60<>""),0)} -> 21 | E12: {=INDEX(Rules!$A$2:$A$60,D12)} -> office supplies | F12: =B12 -> 1800 | G12: =IFERROR(__xludf.DUMMYFUNCTION("IFERROR(VALUE(SUBSTITUTE(REGEXEXTRACT(Raw_Data!J12,""Cost of goods sold: \$([\d,]+)""),"","","""")),0)"),0.0) -> 0 | H12: =IFERROR(__xludf.DUMMYFUNCTION("IFERROR(VALUE(SUBSTITUTE(REGEXEXTRACT(Raw_Data!J12,""withheld a \$([\d,]+) fee""),"","","""")),0)"),0.0) -> 0 | I12: =F12-H12 -> 1800 | J12: =IFERROR(__xludf.DUMMYFUNCTION("IFERROR(VALUE(SUBSTITUTE(REGEXEXTRACT(Raw_Data!J12,""(?i)interest \$([\d,]+)""),"","","""")),0)"),0.0) -> 0 | K12: =F12-J12 -> 1800 | L12: =IFERROR(__xludf.DUMMYFUNCTION("IFERROR(VALUE(SUBSTITUTE(REGEXEXTRACT(Raw_Data!F12,""\$([\d,]+) prior deposit applied""),"","","""")),0)"),0.0) -> 0 | M12: =F12-L12 -> 1800 | N12: =IFERROR(__xludf.DUMMYFUNCTION("IFERROR(VALUE(SUBSTITUTE(REGEXEXTRACT(Raw_Data!F12,""^\$([\d,]+) cash""),"","","""")),0)"),0.0) -> 0 | O12: =F12-N12 -> 1800 | P12: =IFERROR(__xludf.DUMMYFUNCTION("IFERROR(VALUE(SUBSTITUTE(REGEXEXTRACT(Raw_Data!J12,""labour \d+ h at \$\d+/h: \$([\d,]+)""),"","","""")),0)"),0.0) -> 0 | Q12: =F12-P12 -> 1800 | R12: {=IF(INDEX(Rules!$B$2:$B$60,$D12)="","",INDEX(Rules!$B$2:$B$60,$D12))} -> Office and Admin Expense | S12: {=IF(INDEX(Rules!$E$2:$E$60,$D12)="","",INDEX(Rules!$E$2:$E$60,$D12))} | T12: {=IF(INDEX(Rules!$H$2:$H$60,$D12)="","",INDEX(Rules!$H$2:$H$60,$D12))} | U12: {=IF(INDEX(Rules!$C$2:$C$60,$D12)="","",INDEX(Rules!$C$2:$C$60,$D12))} -> Cash | V12: {=IF(INDEX(Rules!$F$2:$F$60,$D12)="","",INDEX(Rules!$F$2:$F$60,$D12))} | W12: {=IF(INDEX(Rules!$I$2:$I$60,$D12)="","",INDEX(Rules!$I$2:$I$60,$D12))} | X12: {=IF(R12="","",INDEX($F12:$Q12,MATCH(INDEX(Rules!$D$2:$D$60,$D12),$F$1:$Q$1,0)))} -> 1800 | Y12: {=IF(S12="","",INDEX($F12:$Q12,MATCH(INDEX(Rules!$G$2:$G$60,$D12),$F$1:$Q$1,0)))} | Z12: {=IF(T12="","",INDEX($F12:$Q12,MATCH(INDEX(Rules!$J$2:$J$60,$D12),$F$1:$Q$1,0)))} | AA12: {=IF(INDEX(Rules!$K$2:$K$60,$D12)="","",INDEX(Rules!$K$2:$K$60,$D12))} -> all used up in 2024 | AB12: =IF(SUMPRODUCT((R12:W12<>"")*(ISNUMBER(SEARCH(Raw_Data!E12,R12:W12))+ISNUMBER(SEARCH(R12:W12,Raw_Data!E12))))>0,"OK","CHECK") -> CHECK
A13: =Raw_Data!A13 -> VVV-2024-012 | B13: =Raw_Data!D13 -> 12000 | C13: =LOWER(Raw_Data!C13&" | "&Raw_Data!F13) -> purchased initial retail inventory | bank transfer; settled | D13: {=MATCH(1,ISNUMBER(SEARCH(Rules!$A$2:$A$60,C13))*(Rules!$A$2:$A$60<>""),0)} -> 10 | E13: {=INDEX(Rules!$A$2:$A$60,D13)} -> inventory | F13: =B13 -> 12000 | G13: =IFERROR(__xludf.DUMMYFUNCTION("IFERROR(VALUE(SUBSTITUTE(REGEXEXTRACT(Raw_Data!J13,""Cost of goods sold: \$([\d,]+)""),"","","""")),0)"),0.0) -> 0 | H13: =IFERROR(__xludf.DUMMYFUNCTION("IFERROR(VALUE(SUBSTITUTE(REGEXEXTRACT(Raw_Data!J13,""withheld a \$([\d,]+) fee""),"","","""")),0)"),0.0) -> 0 | I13: =F13-H13 -> 12000 | J13: =IFERROR(__xludf.DUMMYFUNCTION("IFERROR(VALUE(SUBSTITUTE(REGEXEXTRACT(Raw_Data!J13,""(?i)interest \$([\d,]+)""),"","","""")),0)"),0.0) -> 0 | K13: =F13-J13 -> 12000 | L13: =IFERROR(__xludf.DUMMYFUNCTION("IFERROR(VALUE(SUBSTITUTE(REGEXEXTRACT(Raw_Data!F13,""\$([\d,]+) prior deposit applied""),"","","""")),0)"),0.0) -> 0 | M13: =F13-L13 -> 12000 | N13: =IFERROR(__xludf.DUMMYFUNCTION("IFERROR(VALUE(SUBSTITUTE(REGEXEXTRACT(Raw_Data!F13,""^\$([\d,]+) cash""),"","","""")),0)"),0.0) -> 0 | O13: =F13-N13 -> 12000 | P13: =IFERROR(__xludf.DUMMYFUNCTION("IFERROR(VALUE(SUBSTITUTE(REGEXEXTRACT(Raw_Data!J13,""labour \d+ h at \$\d+/h: \$([\d,]+)""),"","","""")),0)"),0.0) -> 0 | Q13: =F13-P13 -> 12000 | R13: {=IF(INDEX(Rules!$B$2:$B$60,$D13)="","",INDEX(Rules!$B$2:$B$60,$D13))} -> Inventory | S13: {=IF(INDEX(Rules!$E$2:$E$60,$D13)="","",INDEX(Rules!$E$2:$E$60,$D13))} | T13: {=IF(INDEX(Rules!$H$2:$H$60,$D13)="","",INDEX(Rules!$H$2:$H$60,$D13))} | U13: {=IF(INDEX(Rules!$C$2:$C$60,$D13)="","",INDEX(Rules!$C$2:$C$60,$D13))} -> Cash | V13: {=IF(INDEX(Rules!$F$2:$F$60,$D13)="","",INDEX(Rules!$F$2:$F$60,$D13))} | W13: {=IF(INDEX(Rules!$I$2:$I$60,$D13)="","",INDEX(Rules!$I$2:$I$60,$D13))} | X13: {=IF(R13="","",INDEX($F13:$Q13,MATCH(INDEX(Rules!$D$2:$D$60,$D13),$F$1:$Q$1,0)))} -> 12000 | Y13: {=IF(S13="","",INDEX($F13:$Q13,MATCH(INDEX(Rules!$G$2:$G$60,$D13),$F$1:$Q$1,0)))} | Z13: {=IF(T13="","",INDEX($F13:$Q13,MATCH(INDEX(Rules!$J$2:$J$60,$D13),$F$1:$Q$1,0)))} | AA13: {=IF(INDEX(Rules!$K$2:$K$60,$D13)="","",INDEX(Rules!$K$2:$K$60,$D13))} -> stuff to resell, paid cash | AB13: =IF(SUMPRODUCT((R13:W13<>"")*(ISNUMBER(SEARCH(Raw_Data!E13,R13:W13))+ISNUMBER(SEARCH(R13:W13,Raw_Data!E13))))>0,"OK","CHECK") -> OK
A14: =Raw_Data!A14 -> VVV-2024-013 | B14: =Raw_Data!D14 -> 2200 | C14: =LOWER(Raw_Data!C14&" | "&Raw_Data!F14) -> opening advertising campaign | business debit card; settled | D14: {=MATCH(1,ISNUMBER(SEARCH(Rules!$A$2:$A$60,C14))*(Rules!$A$2:$A$60<>""),0)} -> 22 | E14: {=INDEX(Rules!$A$2:$A$60,D14)} -> advertising | F14: =B14 -> 2200 | G14: =IFERROR(__xludf.DUMMYFUNCTION("IFERROR(VALUE(SUBSTITUTE(REGEXEXTRACT(Raw_Data!J14,""Cost of goods sold: \$([\d,]+)""),"","","""")),0)"),0.0) -> 0 | H14: =IFERROR(__xludf.DUMMYFUNCTION("IFERROR(VALUE(SUBSTITUTE(REGEXEXTRACT(Raw_Data!J14,""withheld a \$([\d,]+) fee""),"","","""")),0)"),0.0) -> 0 | I14: =F14-H14 -> 2200 | J14: =IFERROR(__xludf.DUMMYFUNCTION("IFERROR(VALUE(SUBSTITUTE(REGEXEXTRACT(Raw_Data!J14,""(?i)interest \$([\d,]+)""),"","","""")),0)"),0.0) -> 0 | K14: =F14-J14 -> 2200 | L14: =IFERROR(__xludf.DUMMYFUNCTION("IFERROR(VALUE(SUBSTITUTE(REGEXEXTRACT(Raw_Data!F14,""\$([\d,]+) prior deposit applied""),"","","""")),0)"),0.0) -> 0 | M14: =F14-L14 -> 2200 | N14: =IFERROR(__xludf.DUMMYFUNCTION("IFERROR(VALUE(SUBSTITUTE(REGEXEXTRACT(Raw_Data!F14,""^\$([\d,]+) cash""),"","","""")),0)"),0.0) -> 0 | O14: =F14-N14 -> 2200 | P14: =IFERROR(__xludf.DUMMYFUNCTION("IFERROR(VALUE(SUBSTITUTE(REGEXEXTRACT(Raw_Data!J14,""labour \d+ h at \$\d+/h: \$([\d,]+)""),"","","""")),0)"),0.0) -> 0 | Q14: =F14-P14 -> 2200 | R14: {=IF(INDEX(Rules!$B$2:$B$60,$D14)="","",INDEX(Rules!$B$2:$B$60,$D14))} -> Marketing Expense | S14: {=IF(INDEX(Rules!$E$2:$E$60,$D14)="","",INDEX(Rules!$E$2:$E$60,$D14))} | T14: {=IF(INDEX(Rules!$H$2:$H$60,$D14)="","",INDEX(Rules!$H$2:$H$60,$D14))} | U14: {=IF(INDEX(Rules!$C$2:$C$60,$D14)="","",INDEX(Rules!$C$2:$C$60,$D14))} -> Cash | V14: {=IF(INDEX(Rules!$F$2:$F$60,$D14)="","",INDEX(Rules!$F$2:$F$60,$D14))} | W14: {=IF(INDEX(Rules!$I$2:$I$60,$D14)="","",INDEX(Rules!$I$2:$I$60,$D14))} | X14: {=IF(R14="","",INDEX($F14:$Q14,MATCH(INDEX(Rules!$D$2:$D$60,$D14),$F$1:$Q$1,0)))} -> 2200 | Y14: {=IF(S14="","",INDEX($F14:$Q14,MATCH(INDEX(Rules!$G$2:$G$60,$D14),$F$1:$Q$1,0)))} | Z14: {=IF(T14="","",INDEX($F14:$Q14,MATCH(INDEX(Rules!$J$2:$J$60,$D14),$F$1:$Q$1,0)))} | AA14: {=IF(INDEX(Rules!$K$2:$K$60,$D14)="","",INDEX(Rules!$K$2:$K$60,$D14))} -> ads | AB14: =IF(SUMPRODUCT((R14:W14<>"")*(ISNUMBER(SEARCH(Raw_Data!E14,R14:W14))+ISNUMBER(SEARCH(R14:W14,Raw_Data!E14))))>0,"OK","CHECK") -> OK
A15: =Raw_Data!A15 -> VVV-2024-014 | B15: =Raw_Data!D15 -> 3000 | C15: =LOWER(Raw_Data!C15&" | "&Raw_Data!F15) -> retail camping-supply sales | cash and card receipts; settled | D15: {=MATCH(1,ISNUMBER(SEARCH(Rules!$A$2:$A$60,C15))*(Rules!$A$2:$A$60<>""),0)} -> 12 | E15: {=INDEX(Rules!$A$2:$A$60,D15)} -> camping-supply sales | F15: =B15 -> 3000 | G15: =IFERROR(__xludf.DUMMYFUNCTION("IFERROR(VALUE(SUBSTITUTE(REGEXEXTRACT(Raw_Data!J15,""Cost of goods sold: \$([\d,]+)""),"","","""")),0)"),1800.0) -> 1800 | H15: =IFERROR(__xludf.DUMMYFUNCTION("IFERROR(VALUE(SUBSTITUTE(REGEXEXTRACT(Raw_Data!J15,""withheld a \$([\d,]+) fee""),"","","""")),0)"),0.0) -> 0 | I15: =F15-H15 -> 3000 | J15: =IFERROR(__xludf.DUMMYFUNCTION("IFERROR(VALUE(SUBSTITUTE(REGEXEXTRACT(Raw_Data!J15,""(?i)interest \$([\d,]+)""),"","","""")),0)"),0.0) -> 0 | K15: =F15-J15 -> 3000 | L15: =IFERROR(__xludf.DUMMYFUNCTION("IFERROR(VALUE(SUBSTITUTE(REGEXEXTRACT(Raw_Data!F15,""\$([\d,]+) prior deposit applied""),"","","""")),0)"),0.0) -> 0 | M15: =F15-L15 -> 3000 | N15: =IFERROR(__xludf.DUMMYFUNCTION("IFERROR(VALUE(SUBSTITUTE(REGEXEXTRACT(Raw_Data!F15,""^\$([\d,]+) cash""),"","","""")),0)"),0.0) -> 0 | O15: =F15-N15 -> 3000 | P15: =IFERROR(__xludf.DUMMYFUNCTION("IFERROR(VALUE(SUBSTITUTE(REGEXEXTRACT(Raw_Data!J15,""labour \d+ h at \$\d+/h: \$([\d,]+)""),"","","""")),0)"),0.0) -> 0 | Q15: =F15-P15 -> 3000 | R15: {=IF(INDEX(Rules!$B$2:$B$60,$D15)="","",INDEX(Rules!$B$2:$B$60,$D15))} -> Cash | S15: {=IF(INDEX(Rules!$E$2:$E$60,$D15)="","",INDEX(Rules!$E$2:$E$60,$D15))} -> Cost of Goods Sold | T15: {=IF(INDEX(Rules!$H$2:$H$60,$D15)="","",INDEX(Rules!$H$2:$H$60,$D15))} | U15: {=IF(INDEX(Rules!$C$2:$C$60,$D15)="","",INDEX(Rules!$C$2:$C$60,$D15))} -> Retail Sales Revenue | V15: {=IF(INDEX(Rules!$F$2:$F$60,$D15)="","",INDEX(Rules!$F$2:$F$60,$D15))} -> Inventory | W15: {=IF(INDEX(Rules!$I$2:$I$60,$D15)="","",INDEX(Rules!$I$2:$I$60,$D15))} | X15: {=IF(R15="","",INDEX($F15:$Q15,MATCH(INDEX(Rules!$D$2:$D$60,$D15),$F$1:$Q$1,0)))} -> 3000 | Y15: {=IF(S15="","",INDEX($F15:$Q15,MATCH(INDEX(Rules!$G$2:$G$60,$D15),$F$1:$Q$1,0)))} -> 1800 | Z15: {=IF(T15="","",INDEX($F15:$Q15,MATCH(INDEX(Rules!$J$2:$J$60,$D15),$F$1:$Q$1,0)))} | AA15: {=IF(INDEX(Rules!$K$2:$K$60,$D15)="","",INDEX(Rules!$K$2:$K$60,$D15))} -> sale + cost of the goods comes out of inventory (COGS) | AB15: =IF(SUMPRODUCT((R15:W15<>"")*(ISNUMBER(SEARCH(Raw_Data!E15,R15:W15))+ISNUMBER(SEARCH(R15:W15,Raw_Data!E15))))>0,"OK","CHECK") -> OK
A16: =Raw_Data!A16 -> VVV-2024-015 | B16: =Raw_Data!D16 -> 7200 | C16: =LOWER(Raw_Data!C16&" | "&Raw_Data!F16) -> employee payroll settlement | payroll and claims paid from business bank account | D16: {=MATCH(1,ISNUMBER(SEARCH(Rules!$A$2:$A$60,C16))*(Rules!$A$2:$A$60<>""),0)} -> 23 | E16: {=INDEX(Rules!$A$2:$A$60,D16)} -> payroll | F16: =B16 -> 7200 | G16: =IFERROR(__xludf.DUMMYFUNCTION("IFERROR(VALUE(SUBSTITUTE(REGEXEXTRACT(Raw_Data!J16,""Cost of goods sold: \$([\d,]+)""),"","","""")),0)"),0.0) -> 0 | H16: =IFERROR(__xludf.DUMMYFUNCTION("IFERROR(VALUE(SUBSTITUTE(REGEXEXTRACT(Raw_Data!J16,""withheld a \$([\d,]+) fee""),"","","""")),0)"),0.0) -> 0 | I16: =F16-H16 -> 7200 | J16: =IFERROR(__xludf.DUMMYFUNCTION("IFERROR(VALUE(SUBSTITUTE(REGEXEXTRACT(Raw_Data!J16,""(?i)interest \$([\d,]+)""),"","","""")),0)"),0.0) -> 0 | K16: =F16-J16 -> 7200 | L16: =IFERROR(__xludf.DUMMYFUNCTION("IFERROR(VALUE(SUBSTITUTE(REGEXEXTRACT(Raw_Data!F16,""\$([\d,]+) prior deposit applied""),"","","""")),0)"),0.0) -> 0 | M16: =F16-L16 -> 7200 | N16: =IFERROR(__xludf.DUMMYFUNCTION("IFERROR(VALUE(SUBSTITUTE(REGEXEXTRACT(Raw_Data!F16,""^\$([\d,]+) cash""),"","","""")),0)"),0.0) -> 0 | O16: =F16-N16 -> 7200 | P16: =IFERROR(__xludf.DUMMYFUNCTION("IFERROR(VALUE(SUBSTITUTE(REGEXEXTRACT(Raw_Data!J16,""labour \d+ h at \$\d+/h: \$([\d,]+)""),"","","""")),0)"),0.0) -> 0 | Q16: =F16-P16 -> 7200 | R16: {=IF(INDEX(Rules!$B$2:$B$60,$D16)="","",INDEX(Rules!$B$2:$B$60,$D16))} -> Wages Expense | S16: {=IF(INDEX(Rules!$E$2:$E$60,$D16)="","",INDEX(Rules!$E$2:$E$60,$D16))} | T16: {=IF(INDEX(Rules!$H$2:$H$60,$D16)="","",INDEX(Rules!$H$2:$H$60,$D16))} | U16: {=IF(INDEX(Rules!$C$2:$C$60,$D16)="","",INDEX(Rules!$C$2:$C$60,$D16))} -> Cash | V16: {=IF(INDEX(Rules!$F$2:$F$60,$D16)="","",INDEX(Rules!$F$2:$F$60,$D16))} | W16: {=IF(INDEX(Rules!$I$2:$I$60,$D16)="","",INDEX(Rules!$I$2:$I$60,$D16))} | X16: {=IF(R16="","",INDEX($F16:$Q16,MATCH(INDEX(Rules!$D$2:$D$60,$D16),$F$1:$Q$1,0)))} -> 7200 | Y16: {=IF(S16="","",INDEX($F16:$Q16,MATCH(INDEX(Rules!$G$2:$G$60,$D16),$F$1:$Q$1,0)))} | Z16: {=IF(T16="","",INDEX($F16:$Q16,MATCH(INDEX(Rules!$J$2:$J$60,$D16),$F$1:$Q$1,0)))} | AA16: {=IF(INDEX(Rules!$K$2:$K$60,$D16)="","",INDEX(Rules!$K$2:$K$60,$D16))} -> wages, includes E04's $200 travel claim | AB16: =IF(SUMPRODUCT((R16:W16<>"")*(ISNUMBER(SEARCH(Raw_Data!E16,R16:W16))+ISNUMBER(SEARCH(R16:W16,Raw_Data!E16))))>0,"OK","CHECK") -> OK
A17: =Raw_Data!A17 -> VVV-2024-016 | B17: =Raw_Data!D17 -> 694 | C17: =LOWER(Raw_Data!C17&" | "&Raw_Data!F17) -> monthly utility settlement | paid from business bank account | D17: {=MATCH(1,ISNUMBER(SEARCH(Rules!$A$2:$A$60,C17))*(Rules!$A$2:$A$60<>""),0)} -> 24 | E17: {=INDEX(Rules!$A$2:$A$60,D17)} -> utility | F17: =B17 -> 694 | G17: =IFERROR(__xludf.DUMMYFUNCTION("IFERROR(VALUE(SUBSTITUTE(REGEXEXTRACT(Raw_Data!J17,""Cost of goods sold: \$([\d,]+)""),"","","""")),0)"),0.0) -> 0 | H17: =IFERROR(__xludf.DUMMYFUNCTION("IFERROR(VALUE(SUBSTITUTE(REGEXEXTRACT(Raw_Data!J17,""withheld a \$([\d,]+) fee""),"","","""")),0)"),0.0) -> 0 | I17: =F17-H17 -> 694 | J17: =IFERROR(__xludf.DUMMYFUNCTION("IFERROR(VALUE(SUBSTITUTE(REGEXEXTRACT(Raw_Data!J17,""(?i)interest \$([\d,]+)""),"","","""")),0)"),0.0) -> 0 | K17: =F17-J17 -> 694 | L17: =IFERROR(__xludf.DUMMYFUNCTION("IFERROR(VALUE(SUBSTITUTE(REGEXEXTRACT(Raw_Data!F17,""\$([\d,]+) prior deposit applied""),"","","""")),0)"),0.0) -> 0 | M17: =F17-L17 -> 694 | N17: =IFERROR(__xludf.DUMMYFUNCTION("IFERROR(VALUE(SUBSTITUTE(REGEXEXTRACT(Raw_Data!F17,""^\$([\d,]+) cash""),"","","""")),0)"),0.0) -> 0 | O17: =F17-N17 -> 694 | P17: =IFERROR(__xludf.DUMMYFUNCTION("IFERROR(VALUE(SUBSTITUTE(REGEXEXTRACT(Raw_Data!J17,""labour \d+ h at \$\d+/h: \$([\d,]+)""),"","","""")),0)"),0.0) -> 0 | Q17: =F17-P17 -> 694 | R17: {=IF(INDEX(Rules!$B$2:$B$60,$D17)="","",INDEX(Rules!$B$2:$B$60,$D17))} -> Utilities Expense | S17: {=IF(INDEX(Rules!$E$2:$E$60,$D17)="","",INDEX(Rules!$E$2:$E$60,$D17))} | T17: {=IF(INDEX(Rules!$H$2:$H$60,$D17)="","",INDEX(Rules!$H$2:$H$60,$D17))} | U17: {=IF(INDEX(Rules!$C$2:$C$60,$D17)="","",INDEX(Rules!$C$2:$C$60,$D17))} -> Cash | V17: {=IF(INDEX(Rules!$F$2:$F$60,$D17)="","",INDEX(Rules!$F$2:$F$60,$D17))} | W17: {=IF(INDEX(Rules!$I$2:$I$60,$D17)="","",INDEX(Rules!$I$2:$I$60,$D17))} | X17: {=IF(R17="","",INDEX($F17:$Q17,MATCH(INDEX(Rules!$D$2:$D$60,$D17),$F$1:$Q$1,0)))} -> 694 | Y17: {=IF(S17="","",INDEX($F17:$Q17,MATCH(INDEX(Rules!$G$2:$G$60,$D17),$F$1:$Q$1,0)))} | Z17: {=IF(T17="","",INDEX($F17:$Q17,MATCH(INDEX(Rules!$J$2:$J$60,$D17),$F$1:$Q$1,0)))} | AA17: {=IF(INDEX(Rules!$K$2:$K$60,$D17)="","",INDEX(Rules!$K$2:$K$60,$D17))} -> monthly utilities | AB17: =IF(SUMPRODUCT((R17:W17<>"")*(ISNUMBER(SEARCH(Raw_Data!E17,R17:W17))+ISNUMBER(SEARCH(R17:W17,Raw_Data!E17))))>0,"OK","CHECK") -> OK
A18: =Raw_Data!A18 -> VVV-2024-017 | B18: =Raw_Data!D18 -> 5400 | C18: =LOWER(Raw_Data!C18&" | "&Raw_Data!F18) -> monthly facility rent | automatic bank transfer; settled | D18: {=MATCH(1,ISNUMBER(SEARCH(Rules!$A$2:$A$60,C18))*(Rules!$A$2:$A$60<>""),0)} -> 15 | E18: {=INDEX(Rules!$A$2:$A$60,D18)} -> facility rent | F18: =B18 -> 5400 | G18: =IFERROR(__xludf.DUMMYFUNCTION("IFERROR(VALUE(SUBSTITUTE(REGEXEXTRACT(Raw_Data!J18,""Cost of goods sold: \$([\d,]+)""),"","","""")),0)"),0.0) -> 0 | H18: =IFERROR(__xludf.DUMMYFUNCTION("IFERROR(VALUE(SUBSTITUTE(REGEXEXTRACT(Raw_Data!J18,""withheld a \$([\d,]+) fee""),"","","""")),0)"),0.0) -> 0 | I18: =F18-H18 -> 5400 | J18: =IFERROR(__xludf.DUMMYFUNCTION("IFERROR(VALUE(SUBSTITUTE(REGEXEXTRACT(Raw_Data!J18,""(?i)interest \$([\d,]+)""),"","","""")),0)"),0.0) -> 0 | K18: =F18-J18 -> 5400 | L18: =IFERROR(__xludf.DUMMYFUNCTION("IFERROR(VALUE(SUBSTITUTE(REGEXEXTRACT(Raw_Data!F18,""\$([\d,]+) prior deposit applied""),"","","""")),0)"),0.0) -> 0 | M18: =F18-L18 -> 5400 | N18: =IFERROR(__xludf.DUMMYFUNCTION("IFERROR(VALUE(SUBSTITUTE(REGEXEXTRACT(Raw_Data!F18,""^\$([\d,]+) cash""),"","","""")),0)"),0.0) -> 0 | O18: =F18-N18 -> 5400 | P18: =IFERROR(__xludf.DUMMYFUNCTION("IFERROR(VALUE(SUBSTITUTE(REGEXEXTRACT(Raw_Data!J18,""labour \d+ h at \$\d+/h: \$([\d,]+)""),"","","""")),0)"),0.0) -> 0 | Q18: =F18-P18 -> 5400 | R18: {=IF(INDEX(Rules!$B$2:$B$60,$D18)="","",INDEX(Rules!$B$2:$B$60,$D18))} -> Rent Expense | S18: {=IF(INDEX(Rules!$E$2:$E$60,$D18)="","",INDEX(Rules!$E$2:$E$60,$D18))} | T18: {=IF(INDEX(Rules!$H$2:$H$60,$D18)="","",INDEX(Rules!$H$2:$H$60,$D18))} | U18: {=IF(INDEX(Rules!$C$2:$C$60,$D18)="","",INDEX(Rules!$C$2:$C$60,$D18))} -> Cash | V18: {=IF(INDEX(Rules!$F$2:$F$60,$D18)="","",INDEX(Rules!$F$2:$F$60,$D18))} | W18: {=IF(INDEX(Rules!$I$2:$I$60,$D18)="","",INDEX(Rules!$I$2:$I$60,$D18))} | X18: {=IF(R18="","",INDEX($F18:$Q18,MATCH(INDEX(Rules!$D$2:$D$60,$D18),$F$1:$Q$1,0)))} -> 5400 | Y18: {=IF(S18="","",INDEX($F18:$Q18,MATCH(INDEX(Rules!$G$2:$G$60,$D18),$F$1:$Q$1,0)))} | Z18: {=IF(T18="","",INDEX($F18:$Q18,MATCH(INDEX(Rules!$J$2:$J$60,$D18),$F$1:$Q$1,0)))} | AA18: {=IF(INDEX(Rules!$K$2:$K$60,$D18)="","",INDEX(Rules!$K$2:$K$60,$D18))} -> monthly rent | AB18: =IF(SUMPRODUCT((R18:W18<>"")*(ISNUMBER(SEARCH(Raw_Data!E18,R18:W18))+ISNUMBER(SEARCH(R18:W18,Raw_Data!E18))))>0,"OK","CHECK") -> OK
A19: =Raw_Data!A19 -> VVV-2024-018 | B19: =Raw_Data!D19 -> 5000 | C19: =LOWER(Raw_Data!C19&" | "&Raw_Data!F19) -> paid business card balance for computer/pos purchase | online payment; settled | D19: {=MATCH(1,ISNUMBER(SEARCH(Rules!$A$2:$A$60,C19))*(Rules!$A$2:$A$60<>""),0)} -> 3 | E19: {=INDEX(Rules!$A$2:$A$60,D19)} -> card balance | F19: =B19 -> 5000 | G19: =IFERROR(__xludf.DUMMYFUNCTION("IFERROR(VALUE(SUBSTITUTE(REGEXEXTRACT(Raw_Data!J19,""Cost of goods sold: \$([\d,]+)""),"","","""")),0)"),0.0) -> 0 | H19: =IFERROR(__xludf.DUMMYFUNCTION("IFERROR(VALUE(SUBSTITUTE(REGEXEXTRACT(Raw_Data!J19,""withheld a \$([\d,]+) fee""),"","","""")),0)"),0.0) -> 0 | I19: =F19-H19 -> 5000 | J19: =IFERROR(__xludf.DUMMYFUNCTION("IFERROR(VALUE(SUBSTITUTE(REGEXEXTRACT(Raw_Data!J19,""(?i)interest \$([\d,]+)""),"","","""")),0)"),0.0) -> 0 | K19: =F19-J19 -> 5000 | L19: =IFERROR(__xludf.DUMMYFUNCTION("IFERROR(VALUE(SUBSTITUTE(REGEXEXTRACT(Raw_Data!F19,""\$([\d,]+) prior deposit applied""),"","","""")),0)"),0.0) -> 0 | M19: =F19-L19 -> 5000 | N19: =IFERROR(__xludf.DUMMYFUNCTION("IFERROR(VALUE(SUBSTITUTE(REGEXEXTRACT(Raw_Data!F19,""^\$([\d,]+) cash""),"","","""")),0)"),0.0) -> 0 | O19: =F19-N19 -> 5000 | P19: =IFERROR(__xludf.DUMMYFUNCTION("IFERROR(VALUE(SUBSTITUTE(REGEXEXTRACT(Raw_Data!J19,""labour \d+ h at \$\d+/h: \$([\d,]+)""),"","","""")),0)"),0.0) -> 0 | Q19: =F19-P19 -> 5000 | R19: {=IF(INDEX(Rules!$B$2:$B$60,$D19)="","",INDEX(Rules!$B$2:$B$60,$D19))} -> Accounts Payable | S19: {=IF(INDEX(Rules!$E$2:$E$60,$D19)="","",INDEX(Rules!$E$2:$E$60,$D19))} | T19: {=IF(INDEX(Rules!$H$2:$H$60,$D19)="","",INDEX(Rules!$H$2:$H$60,$D19))} | U19: {=IF(INDEX(Rules!$C$2:$C$60,$D19)="","",INDEX(Rules!$C$2:$C$60,$D19))} -> Cash | V19: {=IF(INDEX(Rules!$F$2:$F$60,$D19)="","",INDEX(Rules!$F$2:$F$60,$D19))} | W19: {=IF(INDEX(Rules!$I$2:$I$60,$D19)="","",INDEX(Rules!$I$2:$I$60,$D19))} | X19: {=IF(R19="","",INDEX($F19:$Q19,MATCH(INDEX(Rules!$D$2:$D$60,$D19),$F$1:$Q$1,0)))} -> 5000 | Y19: {=IF(S19="","",INDEX($F19:$Q19,MATCH(INDEX(Rules!$G$2:$G$60,$D19),$F$1:$Q$1,0)))} | Z19: {=IF(T19="","",INDEX($F19:$Q19,MATCH(INDEX(Rules!$J$2:$J$60,$D19),$F$1:$Q$1,0)))} | AA19: {=IF(INDEX(Rules!$K$2:$K$60,$D19)="","",INDEX(Rules!$K$2:$K$60,$D19))} -> paying off the card, not a new expense | AB19: =IF(SUMPRODUCT((R19:W19<>"")*(ISNUMBER(SEARCH(Raw_Data!E19,R19:W19))+ISNUMBER(SEARCH(R19:W19,Raw_Data!E19))))>0,"OK","CHECK") -> CHECK
A20: =Raw_Data!A20 -> VVV-2024-019 | B20: =Raw_Data!D20 -> 600 | C20: =LOWER(Raw_Data!C20&" | "&Raw_Data!F20) -> monthly business insurance premium | automatic bank transfer; settled | D20: {=MATCH(1,ISNUMBER(SEARCH(Rules!$A$2:$A$60,C20))*(Rules!$A$2:$A$60<>""),0)} -> 20 | E20: {=INDEX(Rules!$A$2:$A$60,D20)} -> insurance | F20: =B20 -> 600 | G20: =IFERROR(__xludf.DUMMYFUNCTION("IFERROR(VALUE(SUBSTITUTE(REGEXEXTRACT(Raw_Data!J20,""Cost of goods sold: \$([\d,]+)""),"","","""")),0)"),0.0) -> 0 | H20: =IFERROR(__xludf.DUMMYFUNCTION("IFERROR(VALUE(SUBSTITUTE(REGEXEXTRACT(Raw_Data!J20,""withheld a \$([\d,]+) fee""),"","","""")),0)"),0.0) -> 0 | I20: =F20-H20 -> 600 | J20: =IFERROR(__xludf.DUMMYFUNCTION("IFERROR(VALUE(SUBSTITUTE(REGEXEXTRACT(Raw_Data!J20,""(?i)interest \$([\d,]+)""),"","","""")),0)"),0.0) -> 0 | K20: =F20-J20 -> 600 | L20: =IFERROR(__xludf.DUMMYFUNCTION("IFERROR(VALUE(SUBSTITUTE(REGEXEXTRACT(Raw_Data!F20,""\$([\d,]+) prior deposit applied""),"","","""")),0)"),0.0) -> 0 | M20: =F20-L20 -> 600 | N20: =IFERROR(__xludf.DUMMYFUNCTION("IFERROR(VALUE(SUBSTITUTE(REGEXEXTRACT(Raw_Data!F20,""^\$([\d,]+) cash""),"","","""")),0)"),0.0) -> 0 | O20: =F20-N20 -> 600 | P20: =IFERROR(__xludf.DUMMYFUNCTION("IFERROR(VALUE(SUBSTITUTE(REGEXEXTRACT(Raw_Data!J20,""labour \d+ h at \$\d+/h: \$([\d,]+)""),"","","""")),0)"),0.0) -> 0 | Q20: =F20-P20 -> 600 | R20: {=IF(INDEX(Rules!$B$2:$B$60,$D20)="","",INDEX(Rules!$B$2:$B$60,$D20))} -> Insurance Expense | S20: {=IF(INDEX(Rules!$E$2:$E$60,$D20)="","",INDEX(Rules!$E$2:$E$60,$D20))} | T20: {=IF(INDEX(Rules!$H$2:$H$60,$D20)="","",INDEX(Rules!$H$2:$H$60,$D20))} | U20: {=IF(INDEX(Rules!$C$2:$C$60,$D20)="","",INDEX(Rules!$C$2:$C$60,$D20))} -> Cash | V20: {=IF(INDEX(Rules!$F$2:$F$60,$D20)="","",INDEX(Rules!$F$2:$F$60,$D20))} | W20: {=IF(INDEX(Rules!$I$2:$I$60,$D20)="","",INDEX(Rules!$I$2:$I$60,$D20))} | X20: {=IF(R20="","",INDEX($F20:$Q20,MATCH(INDEX(Rules!$D$2:$D$60,$D20),$F$1:$Q$1,0)))} -> 600 | Y20: {=IF(S20="","",INDEX($F20:$Q20,MATCH(INDEX(Rules!$G$2:$G$60,$D20),$F$1:$Q$1,0)))} | Z20: {=IF(T20="","",INDEX($F20:$Q20,MATCH(INDEX(Rules!$J$2:$J$60,$D20),$F$1:$Q$1,0)))} | AA20: {=IF(INDEX(Rules!$K$2:$K$60,$D20)="","",INDEX(Rules!$K$2:$K$60,$D20))} -> monthly insurance | AB20: =IF(SUMPRODUCT((R20:W20<>"")*(ISNUMBER(SEARCH(Raw_Data!E20,R20:W20))+ISNUMBER(SEARCH(R20:W20,Raw_Data!E20))))>0,"OK","CHECK") -> OK
A21: =Raw_Data!A21 -> VVV-2024-020 | B21: =Raw_Data!D21 -> 5500 | C21: =LOWER(Raw_Data!C21&" | "&Raw_Data!F21) -> equipment rental receipts batch | cash and card receipts; settled | D21: {=MATCH(1,ISNUMBER(SEARCH(Rules!$A$2:$A$60,C21))*(Rules!$A$2:$A$60<>""),0)} -> 26 | E21: {=INDEX(Rules!$A$2:$A$60,D21)} -> rental receipts | F21: =B21 -> 5500 | G21: =IFERROR(__xludf.DUMMYFUNCTION("IFERROR(VALUE(SUBSTITUTE(REGEXEXTRACT(Raw_Data!J21,""Cost of goods sold: \$([\d,]+)""),"","","""")),0)"),0.0) -> 0 | H21: =IFERROR(__xludf.DUMMYFUNCTION("IFERROR(VALUE(SUBSTITUTE(REGEXEXTRACT(Raw_Data!J21,""withheld a \$([\d,]+) fee""),"","","""")),0)"),0.0) -> 0 | I21: =F21-H21 -> 5500 | J21: =IFERROR(__xludf.DUMMYFUNCTION("IFERROR(VALUE(SUBSTITUTE(REGEXEXTRACT(Raw_Data!J21,""(?i)interest \$([\d,]+)""),"","","""")),0)"),0.0) -> 0 | K21: =F21-J21 -> 5500 | L21: =IFERROR(__xludf.DUMMYFUNCTION("IFERROR(VALUE(SUBSTITUTE(REGEXEXTRACT(Raw_Data!F21,""\$([\d,]+) prior deposit applied""),"","","""")),0)"),0.0) -> 0 | M21: =F21-L21 -> 5500 | N21: =IFERROR(__xludf.DUMMYFUNCTION("IFERROR(VALUE(SUBSTITUTE(REGEXEXTRACT(Raw_Data!F21,""^\$([\d,]+) cash""),"","","""")),0)"),0.0) -> 0 | O21: =F21-N21 -> 5500 | P21: =IFERROR(__xludf.DUMMYFUNCTION("IFERROR(VALUE(SUBSTITUTE(REGEXEXTRACT(Raw_Data!J21,""labour \d+ h at \$\d+/h: \$([\d,]+)""),"","","""")),0)"),0.0) -> 0 | Q21: =F21-P21 -> 5500 | R21: {=IF(INDEX(Rules!$B$2:$B$60,$D21)="","",INDEX(Rules!$B$2:$B$60,$D21))} -> Cash | S21: {=IF(INDEX(Rules!$E$2:$E$60,$D21)="","",INDEX(Rules!$E$2:$E$60,$D21))} | T21: {=IF(INDEX(Rules!$H$2:$H$60,$D21)="","",INDEX(Rules!$H$2:$H$60,$D21))} | U21: {=IF(INDEX(Rules!$C$2:$C$60,$D21)="","",INDEX(Rules!$C$2:$C$60,$D21))} -> Equipment Rental Revenue | V21: {=IF(INDEX(Rules!$F$2:$F$60,$D21)="","",INDEX(Rules!$F$2:$F$60,$D21))} | W21: {=IF(INDEX(Rules!$I$2:$I$60,$D21)="","",INDEX(Rules!$I$2:$I$60,$D21))} | X21: {=IF(R21="","",INDEX($F21:$Q21,MATCH(INDEX(Rules!$D$2:$D$60,$D21),$F$1:$Q$1,0)))} -> 5500 | Y21: {=IF(S21="","",INDEX($F21:$Q21,MATCH(INDEX(Rules!$G$2:$G$60,$D21),$F$1:$Q$1,0)))} | Z21: {=IF(T21="","",INDEX($F21:$Q21,MATCH(INDEX(Rules!$J$2:$J$60,$D21),$F$1:$Q$1,0)))} | AA21: {=IF(INDEX(Rules!$K$2:$K$60,$D21)="","",INDEX(Rules!$K$2:$K$60,$D21))} -> rentals done and paid | AB21: =IF(SUMPRODUCT((R21:W21<>"")*(ISNUMBER(SEARCH(Raw_Data!E21,R21:W21))+ISNUMBER(SEARCH(R21:W21,Raw_Data!E21))))>0,"OK","CHECK") -> OK
A22: =Raw_Data!A22 -> VVV-2024-021 | B22: =Raw_Data!D22 -> 4000 | C22: =LOWER(Raw_Data!C22&" | "&Raw_Data!F22) -> customer deposit for may corporate tour | bank transfer received; tour scheduled for may | D22: {=MATCH(1,ISNUMBER(SEARCH(Rules!$A$2:$A$60,C22))*(Rules!$A$2:$A$60<>""),0)} -> 31 | E22: {=INDEX(Rules!$A$2:$A$60,D22)} -> deposit | F22: =B22 -> 4000 | G22: =IFERROR(__xludf.DUMMYFUNCTION("IFERROR(VALUE(SUBSTITUTE(REGEXEXTRACT(Raw_Data!J22,""Cost of goods sold: \$([\d,]+)""),"","","""")),0)"),0.0) -> 0 | H22: =IFERROR(__xludf.DUMMYFUNCTION("IFERROR(VALUE(SUBSTITUTE(REGEXEXTRACT(Raw_Data!J22,""withheld a \$([\d,]+) fee""),"","","""")),0)"),0.0) -> 0 | I22: =F22-H22 -> 4000 | J22: =IFERROR(__xludf.DUMMYFUNCTION("IFERROR(VALUE(SUBSTITUTE(REGEXEXTRACT(Raw_Data!J22,""(?i)interest \$([\d,]+)""),"","","""")),0)"),0.0) -> 0 | K22: =F22-J22 -> 4000 | L22: =IFERROR(__xludf.DUMMYFUNCTION("IFERROR(VALUE(SUBSTITUTE(REGEXEXTRACT(Raw_Data!F22,""\$([\d,]+) prior deposit applied""),"","","""")),0)"),0.0) -> 0 | M22: =F22-L22 -> 4000 | N22: =IFERROR(__xludf.DUMMYFUNCTION("IFERROR(VALUE(SUBSTITUTE(REGEXEXTRACT(Raw_Data!F22,""^\$([\d,]+) cash""),"","","""")),0)"),0.0) -> 0 | O22: =F22-N22 -> 4000 | P22: =IFERROR(__xludf.DUMMYFUNCTION("IFERROR(VALUE(SUBSTITUTE(REGEXEXTRACT(Raw_Data!J22,""labour \d+ h at \$\d+/h: \$([\d,]+)""),"","","""")),0)"),0.0) -> 0 | Q22: =F22-P22 -> 4000 | R22: {=IF(INDEX(Rules!$B$2:$B$60,$D22)="","",INDEX(Rules!$B$2:$B$60,$D22))} -> Cash | S22: {=IF(INDEX(Rules!$E$2:$E$60,$D22)="","",INDEX(Rules!$E$2:$E$60,$D22))} | T22: {=IF(INDEX(Rules!$H$2:$H$60,$D22)="","",INDEX(Rules!$H$2:$H$60,$D22))} | U22: {=IF(INDEX(Rules!$C$2:$C$60,$D22)="","",INDEX(Rules!$C$2:$C$60,$D22))} -> Unearned Revenue | V22: {=IF(INDEX(Rules!$F$2:$F$60,$D22)="","",INDEX(Rules!$F$2:$F$60,$D22))} | W22: {=IF(INDEX(Rules!$I$2:$I$60,$D22)="","",INDEX(Rules!$I$2:$I$60,$D22))} | X22: {=IF(R22="","",INDEX($F22:$Q22,MATCH(INDEX(Rules!$D$2:$D$60,$D22),$F$1:$Q$1,0)))} -> 4000 | Y22: {=IF(S22="","",INDEX($F22:$Q22,MATCH(INDEX(Rules!$G$2:$G$60,$D22),$F$1:$Q$1,0)))} | Z22: {=IF(T22="","",INDEX($F22:$Q22,MATCH(INDEX(Rules!$J$2:$J$60,$D22),$F$1:$Q$1,0)))} | AA22: {=IF(INDEX(Rules!$K$2:$K$60,$D22)="","",INDEX(Rules!$K$2:$K$60,$D22))} -> paid before the service -> not earned yet (unearned) | AB22: =IF(SUMPRODUCT((R22:W22<>"")*(ISNUMBER(SEARCH(Raw_Data!E22,R22:W22))+ISNUMBER(SEARCH(R22:W22,Raw_Data!E22))))>0,"OK","CHECK") -> CHECK
A23: =Raw_Data!A23 -> VVV-2024-022 | B23: =Raw_Data!D23 -> 6000 | C23: =LOWER(Raw_Data!C23&" | "&Raw_Data!F23) -> purchased retail inventory on account | supplier invoice; payment by agreed instalments | D23: {=MATCH(1,ISNUMBER(SEARCH(Rules!$A$2:$A$60,C23))*(Rules!$A$2:$A$60<>""),0)} -> 9 | E23: {=INDEX(Rules!$A$2:$A$60,D23)} -> inventory on account | F23: =B23 -> 6000 | G23: =IFERROR(__xludf.DUMMYFUNCTION("IFERROR(VALUE(SUBSTITUTE(REGEXEXTRACT(Raw_Data!J23,""Cost of goods sold: \$([\d,]+)""),"","","""")),0)"),0.0) -> 0 | H23: =IFERROR(__xludf.DUMMYFUNCTION("IFERROR(VALUE(SUBSTITUTE(REGEXEXTRACT(Raw_Data!J23,""withheld a \$([\d,]+) fee""),"","","""")),0)"),0.0) -> 0 | I23: =F23-H23 -> 6000 | J23: =IFERROR(__xludf.DUMMYFUNCTION("IFERROR(VALUE(SUBSTITUTE(REGEXEXTRACT(Raw_Data!J23,""(?i)interest \$([\d,]+)""),"","","""")),0)"),0.0) -> 0 | K23: =F23-J23 -> 6000 | L23: =IFERROR(__xludf.DUMMYFUNCTION("IFERROR(VALUE(SUBSTITUTE(REGEXEXTRACT(Raw_Data!F23,""\$([\d,]+) prior deposit applied""),"","","""")),0)"),0.0) -> 0 | M23: =F23-L23 -> 6000 | N23: =IFERROR(__xludf.DUMMYFUNCTION("IFERROR(VALUE(SUBSTITUTE(REGEXEXTRACT(Raw_Data!F23,""^\$([\d,]+) cash""),"","","""")),0)"),0.0) -> 0 | O23: =F23-N23 -> 6000 | P23: =IFERROR(__xludf.DUMMYFUNCTION("IFERROR(VALUE(SUBSTITUTE(REGEXEXTRACT(Raw_Data!J23,""labour \d+ h at \$\d+/h: \$([\d,]+)""),"","","""")),0)"),0.0) -> 0 | Q23: =F23-P23 -> 6000 | R23: {=IF(INDEX(Rules!$B$2:$B$60,$D23)="","",INDEX(Rules!$B$2:$B$60,$D23))} -> Inventory | S23: {=IF(INDEX(Rules!$E$2:$E$60,$D23)="","",INDEX(Rules!$E$2:$E$60,$D23))} | T23: {=IF(INDEX(Rules!$H$2:$H$60,$D23)="","",INDEX(Rules!$H$2:$H$60,$D23))} | U23: {=IF(INDEX(Rules!$C$2:$C$60,$D23)="","",INDEX(Rules!$C$2:$C$60,$D23))} -> Accounts Payable | V23: {=IF(INDEX(Rules!$F$2:$F$60,$D23)="","",INDEX(Rules!$F$2:$F$60,$D23))} | W23: {=IF(INDEX(Rules!$I$2:$I$60,$D23)="","",INDEX(Rules!$I$2:$I$60,$D23))} | X23: {=IF(R23="","",INDEX($F23:$Q23,MATCH(INDEX(Rules!$D$2:$D$60,$D23),$F$1:$Q$1,0)))} -> 6000 | Y23: {=IF(S23="","",INDEX($F23:$Q23,MATCH(INDEX(Rules!$G$2:$G$60,$D23),$F$1:$Q$1,0)))} | Z23: {=IF(T23="","",INDEX($F23:$Q23,MATCH(INDEX(Rules!$J$2:$J$60,$D23),$F$1:$Q$1,0)))} | AA23: {=IF(INDEX(Rules!$K$2:$K$60,$D23)="","",INDEX(Rules!$K$2:$K$60,$D23))} -> stuff to resell, bought on credit | AB23: =IF(SUMPRODUCT((R23:W23<>"")*(ISNUMBER(SEARCH(Raw_Data!E23,R23:W23))+ISNUMBER(SEARCH(R23:W23,Raw_Data!E23))))>0,"OK","CHECK") -> CHECK
A24: =Raw_Data!A24 -> VVV-2024-023 | B24: =Raw_Data!D24 -> 4000 | C24: =LOWER(Raw_Data!C24&" | "&Raw_Data!F24) -> retail camping-supply sales | cash and card receipts; settled | D24: {=MATCH(1,ISNUMBER(SEARCH(Rules!$A$2:$A$60,C24))*(Rules!$A$2:$A$60<>""),0)} -> 12 | E24: {=INDEX(Rules!$A$2:$A$60,D24)} -> camping-supply sales | F24: =B24 -> 4000 | G24: =IFERROR(__xludf.DUMMYFUNCTION("IFERROR(VALUE(SUBSTITUTE(REGEXEXTRACT(Raw_Data!J24,""Cost of goods sold: \$([\d,]+)""),"","","""")),0)"),2400.0) -> 2400 | H24: =IFERROR(__xludf.DUMMYFUNCTION("IFERROR(VALUE(SUBSTITUTE(REGEXEXTRACT(Raw_Data!J24,""withheld a \$([\d,]+) fee""),"","","""")),0)"),0.0) -> 0 | I24: =F24-H24 -> 4000 | J24: =IFERROR(__xludf.DUMMYFUNCTION("IFERROR(VALUE(SUBSTITUTE(REGEXEXTRACT(Raw_Data!J24,""(?i)interest \$([\d,]+)""),"","","""")),0)"),0.0) -> 0 | K24: =F24-J24 -> 4000 | L24: =IFERROR(__xludf.DUMMYFUNCTION("IFERROR(VALUE(SUBSTITUTE(REGEXEXTRACT(Raw_Data!F24,""\$([\d,]+) prior deposit applied""),"","","""")),0)"),0.0) -> 0 | M24: =F24-L24 -> 4000 | N24: =IFERROR(__xludf.DUMMYFUNCTION("IFERROR(VALUE(SUBSTITUTE(REGEXEXTRACT(Raw_Data!F24,""^\$([\d,]+) cash""),"","","""")),0)"),0.0) -> 0 | O24: =F24-N24 -> 4000 | P24: =IFERROR(__xludf.DUMMYFUNCTION("IFERROR(VALUE(SUBSTITUTE(REGEXEXTRACT(Raw_Data!J24,""labour \d+ h at \$\d+/h: \$([\d,]+)""),"","","""")),0)"),0.0) -> 0 | Q24: =F24-P24 -> 4000 | R24: {=IF(INDEX(Rules!$B$2:$B$60,$D24)="","",INDEX(Rules!$B$2:$B$60,$D24))} -> Cash | S24: {=IF(INDEX(Rules!$E$2:$E$60,$D24)="","",INDEX(Rules!$E$2:$E$60,$D24))} -> Cost of Goods Sold | T24: {=IF(INDEX(Rules!$H$2:$H$60,$D24)="","",INDEX(Rules!$H$2:$H$60,$D24))} | U24: {=IF(INDEX(Rules!$C$2:$C$60,$D24)="","",INDEX(Rules!$C$2:$C$60,$D24))} -> Retail Sales Revenue | V24: {=IF(INDEX(Rules!$F$2:$F$60,$D24)="","",INDEX(Rules!$F$2:$F$60,$D24))} -> Inventory | W24: {=IF(INDEX(Rules!$I$2:$I$60,$D24)="","",INDEX(Rules!$I$2:$I$60,$D24))} | X24: {=IF(R24="","",INDEX($F24:$Q24,MATCH(INDEX(Rules!$D$2:$D$60,$D24),$F$1:$Q$1,0)))} -> 4000 | Y24: {=IF(S24="","",INDEX($F24:$Q24,MATCH(INDEX(Rules!$G$2:$G$60,$D24),$F$1:$Q$1,0)))} -> 2400 | Z24: {=IF(T24="","",INDEX($F24:$Q24,MATCH(INDEX(Rules!$J$2:$J$60,$D24),$F$1:$Q$1,0)))} | AA24: {=IF(INDEX(Rules!$K$2:$K$60,$D24)="","",INDEX(Rules!$K$2:$K$60,$D24))} -> sale + cost of the goods comes out of inventory (COGS) | AB24: =IF(SUMPRODUCT((R24:W24<>"")*(ISNUMBER(SEARCH(Raw_Data!E24,R24:W24))+ISNUMBER(SEARCH(R24:W24,Raw_Data!E24))))>0,"OK","CHECK") -> OK
A25: =Raw_Data!A25 -> VVV-2024-024 | B25: =Raw_Data!D25 -> 3500 | C25: =LOWER(Raw_Data!C25&" | "&Raw_Data!F25) -> guided tour revenue | cash and card receipts; settled | D25: {=MATCH(1,ISNUMBER(SEARCH(Rules!$A$2:$A$60,C25))*(Rules!$A$2:$A$60<>""),0)} -> 32 | E25: {=INDEX(Rules!$A$2:$A$60,D25)} -> tour revenue | F25: =B25 -> 3500 | G25: =IFERROR(__xludf.DUMMYFUNCTION("IFERROR(VALUE(SUBSTITUTE(REGEXEXTRACT(Raw_Data!J25,""Cost of goods sold: \$([\d,]+)""),"","","""")),0)"),0.0) -> 0 | H25: =IFERROR(__xludf.DUMMYFUNCTION("IFERROR(VALUE(SUBSTITUTE(REGEXEXTRACT(Raw_Data!J25,""withheld a \$([\d,]+) fee""),"","","""")),0)"),0.0) -> 0 | I25: =F25-H25 -> 3500 | J25: =IFERROR(__xludf.DUMMYFUNCTION("IFERROR(VALUE(SUBSTITUTE(REGEXEXTRACT(Raw_Data!J25,""(?i)interest \$([\d,]+)""),"","","""")),0)"),0.0) -> 0 | K25: =F25-J25 -> 3500 | L25: =IFERROR(__xludf.DUMMYFUNCTION("IFERROR(VALUE(SUBSTITUTE(REGEXEXTRACT(Raw_Data!F25,""\$([\d,]+) prior deposit applied""),"","","""")),0)"),0.0) -> 0 | M25: =F25-L25 -> 3500 | N25: =IFERROR(__xludf.DUMMYFUNCTION("IFERROR(VALUE(SUBSTITUTE(REGEXEXTRACT(Raw_Data!F25,""^\$([\d,]+) cash""),"","","""")),0)"),0.0) -> 0 | O25: =F25-N25 -> 3500 | P25: =IFERROR(__xludf.DUMMYFUNCTION("IFERROR(VALUE(SUBSTITUTE(REGEXEXTRACT(Raw_Data!J25,""labour \d+ h at \$\d+/h: \$([\d,]+)""),"","","""")),0)"),0.0) -> 0 | Q25: =F25-P25 -> 3500 | R25: {=IF(INDEX(Rules!$B$2:$B$60,$D25)="","",INDEX(Rules!$B$2:$B$60,$D25))} -> Cash | S25: {=IF(INDEX(Rules!$E$2:$E$60,$D25)="","",INDEX(Rules!$E$2:$E$60,$D25))} | T25: {=IF(INDEX(Rules!$H$2:$H$60,$D25)="","",INDEX(Rules!$H$2:$H$60,$D25))} | U25: {=IF(INDEX(Rules!$C$2:$C$60,$D25)="","",INDEX(Rules!$C$2:$C$60,$D25))} -> Tour Revenue | V25: {=IF(INDEX(Rules!$F$2:$F$60,$D25)="","",INDEX(Rules!$F$2:$F$60,$D25))} | W25: {=IF(INDEX(Rules!$I$2:$I$60,$D25)="","",INDEX(Rules!$I$2:$I$60,$D25))} | X25: {=IF(R25="","",INDEX($F25:$Q25,MATCH(INDEX(Rules!$D$2:$D$60,$D25),$F$1:$Q$1,0)))} -> 3500 | Y25: {=IF(S25="","",INDEX($F25:$Q25,MATCH(INDEX(Rules!$G$2:$G$60,$D25),$F$1:$Q$1,0)))} | Z25: {=IF(T25="","",INDEX($F25:$Q25,MATCH(INDEX(Rules!$J$2:$J$60,$D25),$F$1:$Q$1,0)))} | AA25: {=IF(INDEX(Rules!$K$2:$K$60,$D25)="","",INDEX(Rules!$K$2:$K$60,$D25))} -> tours done and paid | AB25: =IF(SUMPRODUCT((R25:W25<>"")*(ISNUMBER(SEARCH(Raw_Data!E25,R25:W25))+ISNUMBER(SEARCH(R25:W25,Raw_Data!E25))))>0,"OK","CHECK") -> OK
A26: =Raw_Data!A26 -> VVV-2024-025 | B26: =Raw_Data!D26 -> 8200 | C26: =LOWER(Raw_Data!C26&" | "&Raw_Data!F26) -> employee payroll settlement | payroll and claims paid from business bank account | D26: {=MATCH(1,ISNUMBER(SEARCH(Rules!$A$2:$A$60,C26))*(Rules!$A$2:$A$60<>""),0)} -> 23 | E26: {=INDEX(Rules!$A$2:$A$60,D26)} -> payroll | F26: =B26 -> 8200 | G26: =IFERROR(__xludf.DUMMYFUNCTION("IFERROR(VALUE(SUBSTITUTE(REGEXEXTRACT(Raw_Data!J26,""Cost of goods sold: \$([\d,]+)""),"","","""")),0)"),0.0) -> 0 | H26: =IFERROR(__xludf.DUMMYFUNCTION("IFERROR(VALUE(SUBSTITUTE(REGEXEXTRACT(Raw_Data!J26,""withheld a \$([\d,]+) fee""),"","","""")),0)"),0.0) -> 0 | I26: =F26-H26 -> 8200 | J26: =IFERROR(__xludf.DUMMYFUNCTION("IFERROR(VALUE(SUBSTITUTE(REGEXEXTRACT(Raw_Data!J26,""(?i)interest \$([\d,]+)""),"","","""")),0)"),0.0) -> 0 | K26: =F26-J26 -> 8200 | L26: =IFERROR(__xludf.DUMMYFUNCTION("IFERROR(VALUE(SUBSTITUTE(REGEXEXTRACT(Raw_Data!F26,""\$([\d,]+) prior deposit applied""),"","","""")),0)"),0.0) -> 0 | M26: =F26-L26 -> 8200 | N26: =IFERROR(__xludf.DUMMYFUNCTION("IFERROR(VALUE(SUBSTITUTE(REGEXEXTRACT(Raw_Data!F26,""^\$([\d,]+) cash""),"","","""")),0)"),0.0) -> 0 | O26: =F26-N26 -> 8200 | P26: =IFERROR(__xludf.DUMMYFUNCTION("IFERROR(VALUE(SUBSTITUTE(REGEXEXTRACT(Raw_Data!J26,""labour \d+ h at \$\d+/h: \$([\d,]+)""),"","","""")),0)"),0.0) -> 0 | Q26: =F26-P26 -> 8200 | R26: {=IF(INDEX(Rules!$B$2:$B$60,$D26)="","",INDEX(Rules!$B$2:$B$60,$D26))} -> Wages Expense | S26: {=IF(INDEX(Rules!$E$2:$E$60,$D26)="","",INDEX(Rules!$E$2:$E$60,$D26))} | T26: {=IF(INDEX(Rules!$H$2:$H$60,$D26)="","",INDEX(Rules!$H$2:$H$60,$D26))} | U26: {=IF(INDEX(Rules!$C$2:$C$60,$D26)="","",INDEX(Rules!$C$2:$C$60,$D26))} -> Cash | V26: {=IF(INDEX(Rules!$F$2:$F$60,$D26)="","",INDEX(Rules!$F$2:$F$60,$D26))} | W26: {=IF(INDEX(Rules!$I$2:$I$60,$D26)="","",INDEX(Rules!$I$2:$I$60,$D26))} | X26: {=IF(R26="","",INDEX($F26:$Q26,MATCH(INDEX(Rules!$D$2:$D$60,$D26),$F$1:$Q$1,0)))} -> 8200 | Y26: {=IF(S26="","",INDEX($F26:$Q26,MATCH(INDEX(Rules!$G$2:$G$60,$D26),$F$1:$Q$1,0)))} | Z26: {=IF(T26="","",INDEX($F26:$Q26,MATCH(INDEX(Rules!$J$2:$J$60,$D26),$F$1:$Q$1,0)))} | AA26: {=IF(INDEX(Rules!$K$2:$K$60,$D26)="","",INDEX(Rules!$K$2:$K$60,$D26))} -> wages, includes E04's $200 travel claim | AB26: =IF(SUMPRODUCT((R26:W26<>"")*(ISNUMBER(SEARCH(Raw_Data!E26,R26:W26))+ISNUMBER(SEARCH(R26:W26,Raw_Data!E26))))>0,"OK","CHECK") -> OK
A27: =Raw_Data!A27 -> VVV-2024-026 | B27: =Raw_Data!D27 -> 754 | C27: =LOWER(Raw_Data!C27&" | "&Raw_Data!F27) -> monthly utility settlement | paid from business bank account | D27: {=MATCH(1,ISNUMBER(SEARCH(Rules!$A$2:$A$60,C27))*(Rules!$A$2:$A$60<>""),0)} -> 24 | E27: {=INDEX(Rules!$A$2:$A$60,D27)} -> utility | F27: =B27 -> 754 | G27: =IFERROR(__xludf.DUMMYFUNCTION("IFERROR(VALUE(SUBSTITUTE(REGEXEXTRACT(Raw_Data!J27,""Cost of goods sold: \$([\d,]+)""),"","","""")),0)"),0.0) -> 0 | H27: =IFERROR(__xludf.DUMMYFUNCTION("IFERROR(VALUE(SUBSTITUTE(REGEXEXTRACT(Raw_Data!J27,""withheld a \$([\d,]+) fee""),"","","""")),0)"),0.0) -> 0 | I27: =F27-H27 -> 754 | J27: =IFERROR(__xludf.DUMMYFUNCTION("IFERROR(VALUE(SUBSTITUTE(REGEXEXTRACT(Raw_Data!J27,""(?i)interest \$([\d,]+)""),"","","""")),0)"),0.0) -> 0 | K27: =F27-J27 -> 754 | L27: =IFERROR(__xludf.DUMMYFUNCTION("IFERROR(VALUE(SUBSTITUTE(REGEXEXTRACT(Raw_Data!F27,""\$([\d,]+) prior deposit applied""),"","","""")),0)"),0.0) -> 0 | M27: =F27-L27 -> 754 | N27: =IFERROR(__xludf.DUMMYFUNCTION("IFERROR(VALUE(SUBSTITUTE(REGEXEXTRACT(Raw_Data!F27,""^\$([\d,]+) cash""),"","","""")),0)"),0.0) -> 0 | O27: =F27-N27 -> 754 | P27: =IFERROR(__xludf.DUMMYFUNCTION("IFERROR(VALUE(SUBSTITUTE(REGEXEXTRACT(Raw_Data!J27,""labour \d+ h at \$\d+/h: \$([\d,]+)""),"","","""")),0)"),0.0) -> 0 | Q27: =F27-P27 -> 754 | R27: {=IF(INDEX(Rules!$B$2:$B$60,$D27)="","",INDEX(Rules!$B$2:$B$60,$D27))} -> Utilities Expense | S27: {=IF(INDEX(Rules!$E$2:$E$60,$D27)="","",INDEX(Rules!$E$2:$E$60,$D27))} | T27: {=IF(INDEX(Rules!$H$2:$H$60,$D27)="","",INDEX(Rules!$H$2:$H$60,$D27))} | U27: {=IF(INDEX(Rules!$C$2:$C$60,$D27)="","",INDEX(Rules!$C$2:$C$60,$D27))} -> Cash | V27: {=IF(INDEX(Rules!$F$2:$F$60,$D27)="","",INDEX(Rules!$F$2:$F$60,$D27))} | W27: {=IF(INDEX(Rules!$I$2:$I$60,$D27)="","",INDEX(Rules!$I$2:$I$60,$D27))} | X27: {=IF(R27="","",INDEX($F27:$Q27,MATCH(INDEX(Rules!$D$2:$D$60,$D27),$F$1:$Q$1,0)))} -> 754 | Y27: {=IF(S27="","",INDEX($F27:$Q27,MATCH(INDEX(Rules!$G$2:$G$60,$D27),$F$1:$Q$1,0)))} | Z27: {=IF(T27="","",INDEX($F27:$Q27,MATCH(INDEX(Rules!$J$2:$J$60,$D27),$F$1:$Q$1,0)))} | AA27: {=IF(INDEX(Rules!$K$2:$K$60,$D27)="","",INDEX(Rules!$K$2:$K$60,$D27))} -> monthly utilities | AB27: =IF(SUMPRODUCT((R27:W27<>"")*(ISNUMBER(SEARCH(Raw_Data!E27,R27:W27))+ISNUMBER(SEARCH(R27:W27,Raw_Data!E27))))>0,"OK","CHECK") -> OK
A28: =Raw_Data!A28 -> VVV-2024-027 | B28: =Raw_Data!D28 -> 5400 | C28: =LOWER(Raw_Data!C28&" | "&Raw_Data!F28) -> monthly facility rent | automatic bank transfer; settled | D28: {=MATCH(1,ISNUMBER(SEARCH(Rules!$A$2:$A$60,C28))*(Rules!$A$2:$A$60<>""),0)} -> 15 | E28: {=INDEX(Rules!$A$2:$A$60,D28)} -> facility rent | F28: =B28 -> 5400 | G28: =IFERROR(__xludf.DUMMYFUNCTION("IFERROR(VALUE(SUBSTITUTE(REGEXEXTRACT(Raw_Data!J28,""Cost of goods sold: \$([\d,]+)""),"","","""")),0)"),0.0) -> 0 | H28: =IFERROR(__xludf.DUMMYFUNCTION("IFERROR(VALUE(SUBSTITUTE(REGEXEXTRACT(Raw_Data!J28,""withheld a \$([\d,]+) fee""),"","","""")),0)"),0.0) -> 0 | I28: =F28-H28 -> 5400 | J28: =IFERROR(__xludf.DUMMYFUNCTION("IFERROR(VALUE(SUBSTITUTE(REGEXEXTRACT(Raw_Data!J28,""(?i)interest \$([\d,]+)""),"","","""")),0)"),0.0) -> 0 | K28: =F28-J28 -> 5400 | L28: =IFERROR(__xludf.DUMMYFUNCTION("IFERROR(VALUE(SUBSTITUTE(REGEXEXTRACT(Raw_Data!F28,""\$([\d,]+) prior deposit applied""),"","","""")),0)"),0.0) -> 0 | M28: =F28-L28 -> 5400 | N28: =IFERROR(__xludf.DUMMYFUNCTION("IFERROR(VALUE(SUBSTITUTE(REGEXEXTRACT(Raw_Data!F28,""^\$([\d,]+) cash""),"","","""")),0)"),0.0) -> 0 | O28: =F28-N28 -> 5400 | P28: =IFERROR(__xludf.DUMMYFUNCTION("IFERROR(VALUE(SUBSTITUTE(REGEXEXTRACT(Raw_Data!J28,""labour \d+ h at \$\d+/h: \$([\d,]+)""),"","","""")),0)"),0.0) -> 0 | Q28: =F28-P28 -> 5400 | R28: {=IF(INDEX(Rules!$B$2:$B$60,$D28)="","",INDEX(Rules!$B$2:$B$60,$D28))} -> Rent Expense | S28: {=IF(INDEX(Rules!$E$2:$E$60,$D28)="","",INDEX(Rules!$E$2:$E$60,$D28))} | T28: {=IF(INDEX(Rules!$H$2:$H$60,$D28)="","",INDEX(Rules!$H$2:$H$60,$D28))} | U28: {=IF(INDEX(Rules!$C$2:$C$60,$D28)="","",INDEX(Rules!$C$2:$C$60,$D28))} -> Cash | V28: {=IF(INDEX(Rules!$F$2:$F$60,$D28)="","",INDEX(Rules!$F$2:$F$60,$D28))} | W28: {=IF(INDEX(Rules!$I$2:$I$60,$D28)="","",INDEX(Rules!$I$2:$I$60,$D28))} | X28: {=IF(R28="","",INDEX($F28:$Q28,MATCH(INDEX(Rules!$D$2:$D$60,$D28),$F$1:$Q$1,0)))} -> 5400 | Y28: {=IF(S28="","",INDEX($F28:$Q28,MATCH(INDEX(Rules!$G$2:$G$60,$D28),$F$1:$Q$1,0)))} | Z28: {=IF(T28="","",INDEX($F28:$Q28,MATCH(INDEX(Rules!$J$2:$J$60,$D28),$F$1:$Q$1,0)))} | AA28: {=IF(INDEX(Rules!$K$2:$K$60,$D28)="","",INDEX(Rules!$K$2:$K$60,$D28))} -> monthly rent | AB28: =IF(SUMPRODUCT((R28:W28<>"")*(ISNUMBER(SEARCH(Raw_Data!E28,R28:W28))+ISNUMBER(SEARCH(R28:W28,Raw_Data!E28))))>0,"OK","CHECK") -> OK
A29: =Raw_Data!A29 -> VVV-2024-028 | B29: =Raw_Data!D29 -> 600 | C29: =LOWER(Raw_Data!C29&" | "&Raw_Data!F29) -> monthly business insurance premium | automatic bank transfer; settled | D29: {=MATCH(1,ISNUMBER(SEARCH(Rules!$A$2:$A$60,C29))*(Rules!$A$2:$A$60<>""),0)} -> 20 | E29: {=INDEX(Rules!$A$2:$A$60,D29)} -> insurance | F29: =B29 -> 600 | G29: =IFERROR(__xludf.DUMMYFUNCTION("IFERROR(VALUE(SUBSTITUTE(REGEXEXTRACT(Raw_Data!J29,""Cost of goods sold: \$([\d,]+)""),"","","""")),0)"),0.0) -> 0 | H29: =IFERROR(__xludf.DUMMYFUNCTION("IFERROR(VALUE(SUBSTITUTE(REGEXEXTRACT(Raw_Data!J29,""withheld a \$([\d,]+) fee""),"","","""")),0)"),0.0) -> 0 | I29: =F29-H29 -> 600 | J29: =IFERROR(__xludf.DUMMYFUNCTION("IFERROR(VALUE(SUBSTITUTE(REGEXEXTRACT(Raw_Data!J29,""(?i)interest \$([\d,]+)""),"","","""")),0)"),0.0) -> 0 | K29: =F29-J29 -> 600 | L29: =IFERROR(__xludf.DUMMYFUNCTION("IFERROR(VALUE(SUBSTITUTE(REGEXEXTRACT(Raw_Data!F29,""\$([\d,]+) prior deposit applied""),"","","""")),0)"),0.0) -> 0 | M29: =F29-L29 -> 600 | N29: =IFERROR(__xludf.DUMMYFUNCTION("IFERROR(VALUE(SUBSTITUTE(REGEXEXTRACT(Raw_Data!F29,""^\$([\d,]+) cash""),"","","""")),0)"),0.0) -> 0 | O29: =F29-N29 -> 600 | P29: =IFERROR(__xludf.DUMMYFUNCTION("IFERROR(VALUE(SUBSTITUTE(REGEXEXTRACT(Raw_Data!J29,""labour \d+ h at \$\d+/h: \$([\d,]+)""),"","","""")),0)"),0.0) -> 0 | Q29: =F29-P29 -> 600 | R29: {=IF(INDEX(Rules!$B$2:$B$60,$D29)="","",INDEX(Rules!$B$2:$B$60,$D29))} -> Insurance Expense | S29: {=IF(INDEX(Rules!$E$2:$E$60,$D29)="","",INDEX(Rules!$E$2:$E$60,$D29))} | T29: {=IF(INDEX(Rules!$H$2:$H$60,$D29)="","",INDEX(Rules!$H$2:$H$60,$D29))} | U29: {=IF(INDEX(Rules!$C$2:$C$60,$D29)="","",INDEX(Rules!$C$2:$C$60,$D29))} -> Cash | V29: {=IF(INDEX(Rules!$F$2:$F$60,$D29)="","",INDEX(Rules!$F$2:$F$60,$D29))} | W29: {=IF(INDEX(Rules!$I$2:$I$60,$D29)="","",INDEX(Rules!$I$2:$I$60,$D29))} | X29: {=IF(R29="","",INDEX($F29:$Q29,MATCH(INDEX(Rules!$D$2:$D$60,$D29),$F$1:$Q$1,0)))} -> 600 | Y29: {=IF(S29="","",INDEX($F29:$Q29,MATCH(INDEX(Rules!$G$2:$G$60,$D29),$F$1:$Q$1,0)))} | Z29: {=IF(T29="","",INDEX($F29:$Q29,MATCH(INDEX(Rules!$J$2:$J$60,$D29),$F$1:$Q$1,0)))} | AA29: {=IF(INDEX(Rules!$K$2:$K$60,$D29)="","",INDEX(Rules!$K$2:$K$60,$D29))} -> monthly insurance | AB29: =IF(SUMPRODUCT((R29:W29<>"")*(ISNUMBER(SEARCH(Raw_Data!E29,R29:W29))+ISNUMBER(SEARCH(R29:W29,Raw_Data!E29))))>0,"OK","CHECK") -> OK
A30: =Raw_Data!A30 -> VVV-2024-029 | B30: =Raw_Data!D30 -> 4000 | C30: =LOWER(Raw_Data!C30&" | "&Raw_Data!F30) -> partial payment to inventory supplier | bank transfer; settled | D30: {=MATCH(1,ISNUMBER(SEARCH(Rules!$A$2:$A$60,C30))*(Rules!$A$2:$A$60<>""),0)} -> 8 | E30: {=INDEX(Rules!$A$2:$A$60,D30)} -> payment to inventory supplier | F30: =B30 -> 4000 | G30: =IFERROR(__xludf.DUMMYFUNCTION("IFERROR(VALUE(SUBSTITUTE(REGEXEXTRACT(Raw_Data!J30,""Cost of goods sold: \$([\d,]+)""),"","","""")),0)"),0.0) -> 0 | H30: =IFERROR(__xludf.DUMMYFUNCTION("IFERROR(VALUE(SUBSTITUTE(REGEXEXTRACT(Raw_Data!J30,""withheld a \$([\d,]+) fee""),"","","""")),0)"),0.0) -> 0 | I30: =F30-H30 -> 4000 | J30: =IFERROR(__xludf.DUMMYFUNCTION("IFERROR(VALUE(SUBSTITUTE(REGEXEXTRACT(Raw_Data!J30,""(?i)interest \$([\d,]+)""),"","","""")),0)"),0.0) -> 0 | K30: =F30-J30 -> 4000 | L30: =IFERROR(__xludf.DUMMYFUNCTION("IFERROR(VALUE(SUBSTITUTE(REGEXEXTRACT(Raw_Data!F30,""\$([\d,]+) prior deposit applied""),"","","""")),0)"),0.0) -> 0 | M30: =F30-L30 -> 4000 | N30: =IFERROR(__xludf.DUMMYFUNCTION("IFERROR(VALUE(SUBSTITUTE(REGEXEXTRACT(Raw_Data!F30,""^\$([\d,]+) cash""),"","","""")),0)"),0.0) -> 0 | O30: =F30-N30 -> 4000 | P30: =IFERROR(__xludf.DUMMYFUNCTION("IFERROR(VALUE(SUBSTITUTE(REGEXEXTRACT(Raw_Data!J30,""labour \d+ h at \$\d+/h: \$([\d,]+)""),"","","""")),0)"),0.0) -> 0 | Q30: =F30-P30 -> 4000 | R30: {=IF(INDEX(Rules!$B$2:$B$60,$D30)="","",INDEX(Rules!$B$2:$B$60,$D30))} -> Accounts Payable | S30: {=IF(INDEX(Rules!$E$2:$E$60,$D30)="","",INDEX(Rules!$E$2:$E$60,$D30))} | T30: {=IF(INDEX(Rules!$H$2:$H$60,$D30)="","",INDEX(Rules!$H$2:$H$60,$D30))} | U30: {=IF(INDEX(Rules!$C$2:$C$60,$D30)="","",INDEX(Rules!$C$2:$C$60,$D30))} -> Cash | V30: {=IF(INDEX(Rules!$F$2:$F$60,$D30)="","",INDEX(Rules!$F$2:$F$60,$D30))} | W30: {=IF(INDEX(Rules!$I$2:$I$60,$D30)="","",INDEX(Rules!$I$2:$I$60,$D30))} | X30: {=IF(R30="","",INDEX($F30:$Q30,MATCH(INDEX(Rules!$D$2:$D$60,$D30),$F$1:$Q$1,0)))} -> 4000 | Y30: {=IF(S30="","",INDEX($F30:$Q30,MATCH(INDEX(Rules!$G$2:$G$60,$D30),$F$1:$Q$1,0)))} | Z30: {=IF(T30="","",INDEX($F30:$Q30,MATCH(INDEX(Rules!$J$2:$J$60,$D30),$F$1:$Q$1,0)))} | AA30: {=IF(INDEX(Rules!$K$2:$K$60,$D30)="","",INDEX(Rules!$K$2:$K$60,$D30))} -> paying the supplier back, reduces AP | AB30: =IF(SUMPRODUCT((R30:W30<>"")*(ISNUMBER(SEARCH(Raw_Data!E30,R30:W30))+ISNUMBER(SEARCH(R30:W30,Raw_Data!E30))))>0,"OK","CHECK") -> OK
A31: =Raw_Data!A31 -> VVV-2024-030 | B31: =Raw_Data!D31 -> 7500 | C31: =LOWER(Raw_Data!C31&" | "&Raw_Data!F31) -> equipment rental receipts batch | cash and card receipts; settled | D31: {=MATCH(1,ISNUMBER(SEARCH(Rules!$A$2:$A$60,C31))*(Rules!$A$2:$A$60<>""),0)} -> 26 | E31: {=INDEX(Rules!$A$2:$A$60,D31)} -> rental receipts | F31: =B31 -> 7500 | G31: =IFERROR(__xludf.DUMMYFUNCTION("IFERROR(VALUE(SUBSTITUTE(REGEXEXTRACT(Raw_Data!J31,""Cost of goods sold: \$([\d,]+)""),"","","""")),0)"),0.0) -> 0 | H31: =IFERROR(__xludf.DUMMYFUNCTION("IFERROR(VALUE(SUBSTITUTE(REGEXEXTRACT(Raw_Data!J31,""withheld a \$([\d,]+) fee""),"","","""")),0)"),0.0) -> 0 | I31: =F31-H31 -> 7500 | J31: =IFERROR(__xludf.DUMMYFUNCTION("IFERROR(VALUE(SUBSTITUTE(REGEXEXTRACT(Raw_Data!J31,""(?i)interest \$([\d,]+)""),"","","""")),0)"),0.0) -> 0 | K31: =F31-J31 -> 7500 | L31: =IFERROR(__xludf.DUMMYFUNCTION("IFERROR(VALUE(SUBSTITUTE(REGEXEXTRACT(Raw_Data!F31,""\$([\d,]+) prior deposit applied""),"","","""")),0)"),0.0) -> 0 | M31: =F31-L31 -> 7500 | N31: =IFERROR(__xludf.DUMMYFUNCTION("IFERROR(VALUE(SUBSTITUTE(REGEXEXTRACT(Raw_Data!F31,""^\$([\d,]+) cash""),"","","""")),0)"),0.0) -> 0 | O31: =F31-N31 -> 7500 | P31: =IFERROR(__xludf.DUMMYFUNCTION("IFERROR(VALUE(SUBSTITUTE(REGEXEXTRACT(Raw_Data!J31,""labour \d+ h at \$\d+/h: \$([\d,]+)""),"","","""")),0)"),0.0) -> 0 | Q31: =F31-P31 -> 7500 | R31: {=IF(INDEX(Rules!$B$2:$B$60,$D31)="","",INDEX(Rules!$B$2:$B$60,$D31))} -> Cash | S31: {=IF(INDEX(Rules!$E$2:$E$60,$D31)="","",INDEX(Rules!$E$2:$E$60,$D31))} | T31: {=IF(INDEX(Rules!$H$2:$H$60,$D31)="","",INDEX(Rules!$H$2:$H$60,$D31))} | U31: {=IF(INDEX(Rules!$C$2:$C$60,$D31)="","",INDEX(Rules!$C$2:$C$60,$D31))} -> Equipment Rental Revenue | V31: {=IF(INDEX(Rules!$F$2:$F$60,$D31)="","",INDEX(Rules!$F$2:$F$60,$D31))} | W31: {=IF(INDEX(Rules!$I$2:$I$60,$D31)="","",INDEX(Rules!$I$2:$I$60,$D31))} | X31: {=IF(R31="","",INDEX($F31:$Q31,MATCH(INDEX(Rules!$D$2:$D$60,$D31),$F$1:$Q$1,0)))} -> 7500 | Y31: {=IF(S31="","",INDEX($F31:$Q31,MATCH(INDEX(Rules!$G$2:$G$60,$D31),$F$1:$Q$1,0)))} | Z31: {=IF(T31="","",INDEX($F31:$Q31,MATCH(INDEX(Rules!$J$2:$J$60,$D31),$F$1:$Q$1,0)))} | AA31: {=IF(INDEX(Rules!$K$2:$K$60,$D31)="","",INDEX(Rules!$K$2:$K$60,$D31))} -> rentals done and paid | AB31: =IF(SUMPRODUCT((R31:W31<>"")*(ISNUMBER(SEARCH(Raw_Data!E31,R31:W31))+ISNUMBER(SEARCH(R31:W31,Raw_Data!E31))))>0,"OK","CHECK") -> OK
A32: =Raw_Data!A32 -> VVV-2024-031 | B32: =Raw_Data!D32 -> 5000 | C32: =LOWER(Raw_Data!C32&" | "&Raw_Data!F32) -> retail camping-supply sales | cash and card receipts; settled | D32: {=MATCH(1,ISNUMBER(SEARCH(Rules!$A$2:$A$60,C32))*(Rules!$A$2:$A$60<>""),0)} -> 12 | E32: {=INDEX(Rules!$A$2:$A$60,D32)} -> camping-supply sales | F32: =B32 -> 5000 | G32: =IFERROR(__xludf.DUMMYFUNCTION("IFERROR(VALUE(SUBSTITUTE(REGEXEXTRACT(Raw_Data!J32,""Cost of goods sold: \$([\d,]+)""),"","","""")),0)"),3000.0) -> 3000 | H32: =IFERROR(__xludf.DUMMYFUNCTION("IFERROR(VALUE(SUBSTITUTE(REGEXEXTRACT(Raw_Data!J32,""withheld a \$([\d,]+) fee""),"","","""")),0)"),0.0) -> 0 | I32: =F32-H32 -> 5000 | J32: =IFERROR(__xludf.DUMMYFUNCTION("IFERROR(VALUE(SUBSTITUTE(REGEXEXTRACT(Raw_Data!J32,""(?i)interest \$([\d,]+)""),"","","""")),0)"),0.0) -> 0 | K32: =F32-J32 -> 5000 | L32: =IFERROR(__xludf.DUMMYFUNCTION("IFERROR(VALUE(SUBSTITUTE(REGEXEXTRACT(Raw_Data!F32,""\$([\d,]+) prior deposit applied""),"","","""")),0)"),0.0) -> 0 | M32: =F32-L32 -> 5000 | N32: =IFERROR(__xludf.DUMMYFUNCTION("IFERROR(VALUE(SUBSTITUTE(REGEXEXTRACT(Raw_Data!F32,""^\$([\d,]+) cash""),"","","""")),0)"),0.0) -> 0 | O32: =F32-N32 -> 5000 | P32: =IFERROR(__xludf.DUMMYFUNCTION("IFERROR(VALUE(SUBSTITUTE(REGEXEXTRACT(Raw_Data!J32,""labour \d+ h at \$\d+/h: \$([\d,]+)""),"","","""")),0)"),0.0) -> 0 | Q32: =F32-P32 -> 5000 | R32: {=IF(INDEX(Rules!$B$2:$B$60,$D32)="","",INDEX(Rules!$B$2:$B$60,$D32))} -> Cash | S32: {=IF(INDEX(Rules!$E$2:$E$60,$D32)="","",INDEX(Rules!$E$2:$E$60,$D32))} -> Cost of Goods Sold | T32: {=IF(INDEX(Rules!$H$2:$H$60,$D32)="","",INDEX(Rules!$H$2:$H$60,$D32))} | U32: {=IF(INDEX(Rules!$C$2:$C$60,$D32)="","",INDEX(Rules!$C$2:$C$60,$D32))} -> Retail Sales Revenue | V32: {=IF(INDEX(Rules!$F$2:$F$60,$D32)="","",INDEX(Rules!$F$2:$F$60,$D32))} -> Inventory | W32: {=IF(INDEX(Rules!$I$2:$I$60,$D32)="","",INDEX(Rules!$I$2:$I$60,$D32))} | X32: {=IF(R32="","",INDEX($F32:$Q32,MATCH(INDEX(Rules!$D$2:$D$60,$D32),$F$1:$Q$1,0)))} -> 5000 | Y32: {=IF(S32="","",INDEX($F32:$Q32,MATCH(INDEX(Rules!$G$2:$G$60,$D32),$F$1:$Q$1,0)))} -> 3000 | Z32: {=IF(T32="","",INDEX($F32:$Q32,MATCH(INDEX(Rules!$J$2:$J$60,$D32),$F$1:$Q$1,0)))} | AA32: {=IF(INDEX(Rules!$K$2:$K$60,$D32)="","",INDEX(Rules!$K$2:$K$60,$D32))} -> sale + cost of the goods comes out of inventory (COGS) | AB32: =IF(SUMPRODUCT((R32:W32<>"")*(ISNUMBER(SEARCH(Raw_Data!E32,R32:W32))+ISNUMBER(SEARCH(R32:W32,Raw_Data!E32))))>0,"OK","CHECK") -> OK
A33: =Raw_Data!A33 -> VVV-2024-032 | B33: =Raw_Data!D33 -> 3400 | C33: =LOWER(Raw_Data!C33&" | "&Raw_Data!F33) -> fleet service and dispatch | paid from business bank account | D33: {=MATCH(1,ISNUMBER(SEARCH(Rules!$A$2:$A$60,C33))*(Rules!$A$2:$A$60<>""),0)} -> 4 | E33: {=INDEX(Rules!$A$2:$A$60,D33)} -> fleet service and dispatch | F33: =B33 -> 3400 | G33: =IFERROR(__xludf.DUMMYFUNCTION("IFERROR(VALUE(SUBSTITUTE(REGEXEXTRACT(Raw_Data!J33,""Cost of goods sold: \$([\d,]+)""),"","","""")),0)"),0.0) -> 0 | H33: =IFERROR(__xludf.DUMMYFUNCTION("IFERROR(VALUE(SUBSTITUTE(REGEXEXTRACT(Raw_Data!J33,""withheld a \$([\d,]+) fee""),"","","""")),0)"),0.0) -> 0 | I33: =F33-H33 -> 3400 | J33: =IFERROR(__xludf.DUMMYFUNCTION("IFERROR(VALUE(SUBSTITUTE(REGEXEXTRACT(Raw_Data!J33,""(?i)interest \$([\d,]+)""),"","","""")),0)"),0.0) -> 0 | K33: =F33-J33 -> 3400 | L33: =IFERROR(__xludf.DUMMYFUNCTION("IFERROR(VALUE(SUBSTITUTE(REGEXEXTRACT(Raw_Data!F33,""\$([\d,]+) prior deposit applied""),"","","""")),0)"),0.0) -> 0 | M33: =F33-L33 -> 3400 | N33: =IFERROR(__xludf.DUMMYFUNCTION("IFERROR(VALUE(SUBSTITUTE(REGEXEXTRACT(Raw_Data!F33,""^\$([\d,]+) cash""),"","","""")),0)"),0.0) -> 0 | O33: =F33-N33 -> 3400 | P33: =IFERROR(__xludf.DUMMYFUNCTION("IFERROR(VALUE(SUBSTITUTE(REGEXEXTRACT(Raw_Data!J33,""labour \d+ h at \$\d+/h: \$([\d,]+)""),"","","""")),0)"),2800.0) -> 2800 | Q33: =F33-P33 -> 600 | R33: {=IF(INDEX(Rules!$B$2:$B$60,$D33)="","",INDEX(Rules!$B$2:$B$60,$D33))} -> Repairs and Maintenance Expense | S33: {=IF(INDEX(Rules!$E$2:$E$60,$D33)="","",INDEX(Rules!$E$2:$E$60,$D33))} -> School Group Expense | T33: {=IF(INDEX(Rules!$H$2:$H$60,$D33)="","",INDEX(Rules!$H$2:$H$60,$D33))} | U33: {=IF(INDEX(Rules!$C$2:$C$60,$D33)="","",INDEX(Rules!$C$2:$C$60,$D33))} -> Cash | V33: {=IF(INDEX(Rules!$F$2:$F$60,$D33)="","",INDEX(Rules!$F$2:$F$60,$D33))} -> Cash | W33: {=IF(INDEX(Rules!$I$2:$I$60,$D33)="","",INDEX(Rules!$I$2:$I$60,$D33))} | X33: {=IF(R33="","",INDEX($F33:$Q33,MATCH(INDEX(Rules!$D$2:$D$60,$D33),$F$1:$Q$1,0)))} -> 2800 | Y33: {=IF(S33="","",INDEX($F33:$Q33,MATCH(INDEX(Rules!$G$2:$G$60,$D33),$F$1:$Q$1,0)))} -> 600 | Z33: {=IF(T33="","",INDEX($F33:$Q33,MATCH(INDEX(Rules!$J$2:$J$60,$D33),$F$1:$Q$1,0)))} | AA33: {=IF(INDEX(Rules!$K$2:$K$60,$D33)="","",INDEX(Rules!$K$2:$K$60,$D33))} -> only workshop labour is repairs, shuttle/materials go to school group | AB33: =IF(SUMPRODUCT((R33:W33<>"")*(ISNUMBER(SEARCH(Raw_Data!E33,R33:W33))+ISNUMBER(SEARCH(R33:W33,Raw_Data!E33))))>0,"OK","CHECK") -> OK
A34: =Raw_Data!A34 -> VVV-2024-033 | B34: =Raw_Data!D34 -> 2450 | C34: =LOWER(Raw_Data!C34&" | "&Raw_Data!F34) -> fleet service and dispatch | paid from business bank account | D34: {=MATCH(1,ISNUMBER(SEARCH(Rules!$A$2:$A$60,C34))*(Rules!$A$2:$A$60<>""),0)} -> 4 | E34: {=INDEX(Rules!$A$2:$A$60,D34)} -> fleet service and dispatch | F34: =B34 -> 2450 | G34: =IFERROR(__xludf.DUMMYFUNCTION("IFERROR(VALUE(SUBSTITUTE(REGEXEXTRACT(Raw_Data!J34,""Cost of goods sold: \$([\d,]+)""),"","","""")),0)"),0.0) -> 0 | H34: =IFERROR(__xludf.DUMMYFUNCTION("IFERROR(VALUE(SUBSTITUTE(REGEXEXTRACT(Raw_Data!J34,""withheld a \$([\d,]+) fee""),"","","""")),0)"),0.0) -> 0 | I34: =F34-H34 -> 2450 | J34: =IFERROR(__xludf.DUMMYFUNCTION("IFERROR(VALUE(SUBSTITUTE(REGEXEXTRACT(Raw_Data!J34,""(?i)interest \$([\d,]+)""),"","","""")),0)"),0.0) -> 0 | K34: =F34-J34 -> 2450 | L34: =IFERROR(__xludf.DUMMYFUNCTION("IFERROR(VALUE(SUBSTITUTE(REGEXEXTRACT(Raw_Data!F34,""\$([\d,]+) prior deposit applied""),"","","""")),0)"),0.0) -> 0 | M34: =F34-L34 -> 2450 | N34: =IFERROR(__xludf.DUMMYFUNCTION("IFERROR(VALUE(SUBSTITUTE(REGEXEXTRACT(Raw_Data!F34,""^\$([\d,]+) cash""),"","","""")),0)"),0.0) -> 0 | O34: =F34-N34 -> 2450 | P34: =IFERROR(__xludf.DUMMYFUNCTION("IFERROR(VALUE(SUBSTITUTE(REGEXEXTRACT(Raw_Data!J34,""labour \d+ h at \$\d+/h: \$([\d,]+)""),"","","""")),0)"),1800.0) -> 1800 | Q34: =F34-P34 -> 650 | R34: {=IF(INDEX(Rules!$B$2:$B$60,$D34)="","",INDEX(Rules!$B$2:$B$60,$D34))} -> Repairs and Maintenance Expense | S34: {=IF(INDEX(Rules!$E$2:$E$60,$D34)="","",INDEX(Rules!$E$2:$E$60,$D34))} -> School Group Expense | T34: {=IF(INDEX(Rules!$H$2:$H$60,$D34)="","",INDEX(Rules!$H$2:$H$60,$D34))} | U34: {=IF(INDEX(Rules!$C$2:$C$60,$D34)="","",INDEX(Rules!$C$2:$C$60,$D34))} -> Cash | V34: {=IF(INDEX(Rules!$F$2:$F$60,$D34)="","",INDEX(Rules!$F$2:$F$60,$D34))} -> Cash | W34: {=IF(INDEX(Rules!$I$2:$I$60,$D34)="","",INDEX(Rules!$I$2:$I$60,$D34))} | X34: {=IF(R34="","",INDEX($F34:$Q34,MATCH(INDEX(Rules!$D$2:$D$60,$D34),$F$1:$Q$1,0)))} -> 1800 | Y34: {=IF(S34="","",INDEX($F34:$Q34,MATCH(INDEX(Rules!$G$2:$G$60,$D34),$F$1:$Q$1,0)))} -> 650 | Z34: {=IF(T34="","",INDEX($F34:$Q34,MATCH(INDEX(Rules!$J$2:$J$60,$D34),$F$1:$Q$1,0)))} | AA34: {=IF(INDEX(Rules!$K$2:$K$60,$D34)="","",INDEX(Rules!$K$2:$K$60,$D34))} -> only workshop labour is repairs, shuttle/materials go to school group | AB34: =IF(SUMPRODUCT((R34:W34<>"")*(ISNUMBER(SEARCH(Raw_Data!E34,R34:W34))+ISNUMBER(SEARCH(R34:W34,Raw_Data!E34))))>0,"OK","CHECK") -> OK
A35: =Raw_Data!A35 -> VVV-2024-034 | B35: =Raw_Data!D35 -> 6000 | C35: =LOWER(Raw_Data!C35&" | "&Raw_Data!F35) -> corporate guided tour completed on account | invoice; due in 60 days | D35: {=MATCH(1,ISNUMBER(SEARCH(Rules!$A$2:$A$60,C35))*(Rules!$A$2:$A$60<>""),0)} -> 29 | E35: {=INDEX(Rules!$A$2:$A$60,D35)} -> completed on account | F35: =B35 -> 6000 | G35: =IFERROR(__xludf.DUMMYFUNCTION("IFERROR(VALUE(SUBSTITUTE(REGEXEXTRACT(Raw_Data!J35,""Cost of goods sold: \$([\d,]+)""),"","","""")),0)"),0.0) -> 0 | H35: =IFERROR(__xludf.DUMMYFUNCTION("IFERROR(VALUE(SUBSTITUTE(REGEXEXTRACT(Raw_Data!J35,""withheld a \$([\d,]+) fee""),"","","""")),0)"),0.0) -> 0 | I35: =F35-H35 -> 6000 | J35: =IFERROR(__xludf.DUMMYFUNCTION("IFERROR(VALUE(SUBSTITUTE(REGEXEXTRACT(Raw_Data!J35,""(?i)interest \$([\d,]+)""),"","","""")),0)"),0.0) -> 0 | K35: =F35-J35 -> 6000 | L35: =IFERROR(__xludf.DUMMYFUNCTION("IFERROR(VALUE(SUBSTITUTE(REGEXEXTRACT(Raw_Data!F35,""\$([\d,]+) prior deposit applied""),"","","""")),0)"),0.0) -> 0 | M35: =F35-L35 -> 6000 | N35: =IFERROR(__xludf.DUMMYFUNCTION("IFERROR(VALUE(SUBSTITUTE(REGEXEXTRACT(Raw_Data!F35,""^\$([\d,]+) cash""),"","","""")),0)"),0.0) -> 0 | O35: =F35-N35 -> 6000 | P35: =IFERROR(__xludf.DUMMYFUNCTION("IFERROR(VALUE(SUBSTITUTE(REGEXEXTRACT(Raw_Data!J35,""labour \d+ h at \$\d+/h: \$([\d,]+)""),"","","""")),0)"),0.0) -> 0 | Q35: =F35-P35 -> 6000 | R35: {=IF(INDEX(Rules!$B$2:$B$60,$D35)="","",INDEX(Rules!$B$2:$B$60,$D35))} -> Accounts Receivable | S35: {=IF(INDEX(Rules!$E$2:$E$60,$D35)="","",INDEX(Rules!$E$2:$E$60,$D35))} | T35: {=IF(INDEX(Rules!$H$2:$H$60,$D35)="","",INDEX(Rules!$H$2:$H$60,$D35))} | U35: {=IF(INDEX(Rules!$C$2:$C$60,$D35)="","",INDEX(Rules!$C$2:$C$60,$D35))} -> Tour Revenue | V35: {=IF(INDEX(Rules!$F$2:$F$60,$D35)="","",INDEX(Rules!$F$2:$F$60,$D35))} | W35: {=IF(INDEX(Rules!$I$2:$I$60,$D35)="","",INDEX(Rules!$I$2:$I$60,$D35))} | X35: {=IF(R35="","",INDEX($F35:$Q35,MATCH(INDEX(Rules!$D$2:$D$60,$D35),$F$1:$Q$1,0)))} -> 6000 | Y35: {=IF(S35="","",INDEX($F35:$Q35,MATCH(INDEX(Rules!$G$2:$G$60,$D35),$F$1:$Q$1,0)))} | Z35: {=IF(T35="","",INDEX($F35:$Q35,MATCH(INDEX(Rules!$J$2:$J$60,$D35),$F$1:$Q$1,0)))} | AA35: {=IF(INDEX(Rules!$K$2:$K$60,$D35)="","",INDEX(Rules!$K$2:$K$60,$D35))} -> tour done so revenue now, cash later | AB35: =IF(SUMPRODUCT((R35:W35<>"")*(ISNUMBER(SEARCH(Raw_Data!E35,R35:W35))+ISNUMBER(SEARCH(R35:W35,Raw_Data!E35))))>0,"OK","CHECK") -> OK
A36: =Raw_Data!A36 -> VVV-2024-035 | B36: =Raw_Data!D36 -> 9200 | C36: =LOWER(Raw_Data!C36&" | "&Raw_Data!F36) -> employee payroll settlement | payroll and claims paid from business bank account | D36: {=MATCH(1,ISNUMBER(SEARCH(Rules!$A$2:$A$60,C36))*(Rules!$A$2:$A$60<>""),0)} -> 23 | E36: {=INDEX(Rules!$A$2:$A$60,D36)} -> payroll | F36: =B36 -> 9200 | G36: =IFERROR(__xludf.DUMMYFUNCTION("IFERROR(VALUE(SUBSTITUTE(REGEXEXTRACT(Raw_Data!J36,""Cost of goods sold: \$([\d,]+)""),"","","""")),0)"),0.0) -> 0 | H36: =IFERROR(__xludf.DUMMYFUNCTION("IFERROR(VALUE(SUBSTITUTE(REGEXEXTRACT(Raw_Data!J36,""withheld a \$([\d,]+) fee""),"","","""")),0)"),0.0) -> 0 | I36: =F36-H36 -> 9200 | J36: =IFERROR(__xludf.DUMMYFUNCTION("IFERROR(VALUE(SUBSTITUTE(REGEXEXTRACT(Raw_Data!J36,""(?i)interest \$([\d,]+)""),"","","""")),0)"),0.0) -> 0 | K36: =F36-J36 -> 9200 | L36: =IFERROR(__xludf.DUMMYFUNCTION("IFERROR(VALUE(SUBSTITUTE(REGEXEXTRACT(Raw_Data!F36,""\$([\d,]+) prior deposit applied""),"","","""")),0)"),0.0) -> 0 | M36: =F36-L36 -> 9200 | N36: =IFERROR(__xludf.DUMMYFUNCTION("IFERROR(VALUE(SUBSTITUTE(REGEXEXTRACT(Raw_Data!F36,""^\$([\d,]+) cash""),"","","""")),0)"),0.0) -> 0 | O36: =F36-N36 -> 9200 | P36: =IFERROR(__xludf.DUMMYFUNCTION("IFERROR(VALUE(SUBSTITUTE(REGEXEXTRACT(Raw_Data!J36,""labour \d+ h at \$\d+/h: \$([\d,]+)""),"","","""")),0)"),0.0) -> 0 | Q36: =F36-P36 -> 9200 | R36: {=IF(INDEX(Rules!$B$2:$B$60,$D36)="","",INDEX(Rules!$B$2:$B$60,$D36))} -> Wages Expense | S36: {=IF(INDEX(Rules!$E$2:$E$60,$D36)="","",INDEX(Rules!$E$2:$E$60,$D36))} | T36: {=IF(INDEX(Rules!$H$2:$H$60,$D36)="","",INDEX(Rules!$H$2:$H$60,$D36))} | U36: {=IF(INDEX(Rules!$C$2:$C$60,$D36)="","",INDEX(Rules!$C$2:$C$60,$D36))} -> Cash | V36: {=IF(INDEX(Rules!$F$2:$F$60,$D36)="","",INDEX(Rules!$F$2:$F$60,$D36))} | W36: {=IF(INDEX(Rules!$I$2:$I$60,$D36)="","",INDEX(Rules!$I$2:$I$60,$D36))} | X36: {=IF(R36="","",INDEX($F36:$Q36,MATCH(INDEX(Rules!$D$2:$D$60,$D36),$F$1:$Q$1,0)))} -> 9200 | Y36: {=IF(S36="","",INDEX($F36:$Q36,MATCH(INDEX(Rules!$G$2:$G$60,$D36),$F$1:$Q$1,0)))} | Z36: {=IF(T36="","",INDEX($F36:$Q36,MATCH(INDEX(Rules!$J$2:$J$60,$D36),$F$1:$Q$1,0)))} | AA36: {=IF(INDEX(Rules!$K$2:$K$60,$D36)="","",INDEX(Rules!$K$2:$K$60,$D36))} -> wages, includes E04's $200 travel claim | AB36: =IF(SUMPRODUCT((R36:W36<>"")*(ISNUMBER(SEARCH(Raw_Data!E36,R36:W36))+ISNUMBER(SEARCH(R36:W36,Raw_Data!E36))))>0,"OK","CHECK") -> OK
A37: =Raw_Data!A37 -> VVV-2024-036 | B37: =Raw_Data!D37 -> 833 | C37: =LOWER(Raw_Data!C37&" | "&Raw_Data!F37) -> monthly utility settlement | paid from business bank account | D37: {=MATCH(1,ISNUMBER(SEARCH(Rules!$A$2:$A$60,C37))*(Rules!$A$2:$A$60<>""),0)} -> 24 | E37: {=INDEX(Rules!$A$2:$A$60,D37)} -> utility | F37: =B37 -> 833 | G37: =IFERROR(__xludf.DUMMYFUNCTION("IFERROR(VALUE(SUBSTITUTE(REGEXEXTRACT(Raw_Data!J37,""Cost of goods sold: \$([\d,]+)""),"","","""")),0)"),0.0) -> 0 | H37: =IFERROR(__xludf.DUMMYFUNCTION("IFERROR(VALUE(SUBSTITUTE(REGEXEXTRACT(Raw_Data!J37,""withheld a \$([\d,]+) fee""),"","","""")),0)"),0.0) -> 0 | I37: =F37-H37 -> 833 | J37: =IFERROR(__xludf.DUMMYFUNCTION("IFERROR(VALUE(SUBSTITUTE(REGEXEXTRACT(Raw_Data!J37,""(?i)interest \$([\d,]+)""),"","","""")),0)"),0.0) -> 0 | K37: =F37-J37 -> 833 | L37: =IFERROR(__xludf.DUMMYFUNCTION("IFERROR(VALUE(SUBSTITUTE(REGEXEXTRACT(Raw_Data!F37,""\$([\d,]+) prior deposit applied""),"","","""")),0)"),0.0) -> 0 | M37: =F37-L37 -> 833 | N37: =IFERROR(__xludf.DUMMYFUNCTION("IFERROR(VALUE(SUBSTITUTE(REGEXEXTRACT(Raw_Data!F37,""^\$([\d,]+) cash""),"","","""")),0)"),0.0) -> 0 | O37: =F37-N37 -> 833 | P37: =IFERROR(__xludf.DUMMYFUNCTION("IFERROR(VALUE(SUBSTITUTE(REGEXEXTRACT(Raw_Data!J37,""labour \d+ h at \$\d+/h: \$([\d,]+)""),"","","""")),0)"),0.0) -> 0 | Q37: =F37-P37 -> 833 | R37: {=IF(INDEX(Rules!$B$2:$B$60,$D37)="","",INDEX(Rules!$B$2:$B$60,$D37))} -> Utilities Expense | S37: {=IF(INDEX(Rules!$E$2:$E$60,$D37)="","",INDEX(Rules!$E$2:$E$60,$D37))} | T37: {=IF(INDEX(Rules!$H$2:$H$60,$D37)="","",INDEX(Rules!$H$2:$H$60,$D37))} | U37: {=IF(INDEX(Rules!$C$2:$C$60,$D37)="","",INDEX(Rules!$C$2:$C$60,$D37))} -> Cash | V37: {=IF(INDEX(Rules!$F$2:$F$60,$D37)="","",INDEX(Rules!$F$2:$F$60,$D37))} | W37: {=IF(INDEX(Rules!$I$2:$I$60,$D37)="","",INDEX(Rules!$I$2:$I$60,$D37))} | X37: {=IF(R37="","",INDEX($F37:$Q37,MATCH(INDEX(Rules!$D$2:$D$60,$D37),$F$1:$Q$1,0)))} -> 833 | Y37: {=IF(S37="","",INDEX($F37:$Q37,MATCH(INDEX(Rules!$G$2:$G$60,$D37),$F$1:$Q$1,0)))} | Z37: {=IF(T37="","",INDEX($F37:$Q37,MATCH(INDEX(Rules!$J$2:$J$60,$D37),$F$1:$Q$1,0)))} | AA37: {=IF(INDEX(Rules!$K$2:$K$60,$D37)="","",INDEX(Rules!$K$2:$K$60,$D37))} -> monthly utilities | AB37: =IF(SUMPRODUCT((R37:W37<>"")*(ISNUMBER(SEARCH(Raw_Data!E37,R37:W37))+ISNUMBER(SEARCH(R37:W37,Raw_Data!E37))))>0,"OK","CHECK") -> OK
A38: =Raw_Data!A38 -> VVV-2024-037 | B38: =Raw_Data!D38 -> 5400 | C38: =LOWER(Raw_Data!C38&" | "&Raw_Data!F38) -> monthly facility rent | automatic bank transfer; settled | D38: {=MATCH(1,ISNUMBER(SEARCH(Rules!$A$2:$A$60,C38))*(Rules!$A$2:$A$60<>""),0)} -> 15 | E38: {=INDEX(Rules!$A$2:$A$60,D38)} -> facility rent | F38: =B38 -> 5400 | G38: =IFERROR(__xludf.DUMMYFUNCTION("IFERROR(VALUE(SUBSTITUTE(REGEXEXTRACT(Raw_Data!J38,""Cost of goods sold: \$([\d,]+)""),"","","""")),0)"),0.0) -> 0 | H38: =IFERROR(__xludf.DUMMYFUNCTION("IFERROR(VALUE(SUBSTITUTE(REGEXEXTRACT(Raw_Data!J38,""withheld a \$([\d,]+) fee""),"","","""")),0)"),0.0) -> 0 | I38: =F38-H38 -> 5400 | J38: =IFERROR(__xludf.DUMMYFUNCTION("IFERROR(VALUE(SUBSTITUTE(REGEXEXTRACT(Raw_Data!J38,""(?i)interest \$([\d,]+)""),"","","""")),0)"),0.0) -> 0 | K38: =F38-J38 -> 5400 | L38: =IFERROR(__xludf.DUMMYFUNCTION("IFERROR(VALUE(SUBSTITUTE(REGEXEXTRACT(Raw_Data!F38,""\$([\d,]+) prior deposit applied""),"","","""")),0)"),0.0) -> 0 | M38: =F38-L38 -> 5400 | N38: =IFERROR(__xludf.DUMMYFUNCTION("IFERROR(VALUE(SUBSTITUTE(REGEXEXTRACT(Raw_Data!F38,""^\$([\d,]+) cash""),"","","""")),0)"),0.0) -> 0 | O38: =F38-N38 -> 5400 | P38: =IFERROR(__xludf.DUMMYFUNCTION("IFERROR(VALUE(SUBSTITUTE(REGEXEXTRACT(Raw_Data!J38,""labour \d+ h at \$\d+/h: \$([\d,]+)""),"","","""")),0)"),0.0) -> 0 | Q38: =F38-P38 -> 5400 | R38: {=IF(INDEX(Rules!$B$2:$B$60,$D38)="","",INDEX(Rules!$B$2:$B$60,$D38))} -> Rent Expense | S38: {=IF(INDEX(Rules!$E$2:$E$60,$D38)="","",INDEX(Rules!$E$2:$E$60,$D38))} | T38: {=IF(INDEX(Rules!$H$2:$H$60,$D38)="","",INDEX(Rules!$H$2:$H$60,$D38))} | U38: {=IF(INDEX(Rules!$C$2:$C$60,$D38)="","",INDEX(Rules!$C$2:$C$60,$D38))} -> Cash | V38: {=IF(INDEX(Rules!$F$2:$F$60,$D38)="","",INDEX(Rules!$F$2:$F$60,$D38))} | W38: {=IF(INDEX(Rules!$I$2:$I$60,$D38)="","",INDEX(Rules!$I$2:$I$60,$D38))} | X38: {=IF(R38="","",INDEX($F38:$Q38,MATCH(INDEX(Rules!$D$2:$D$60,$D38),$F$1:$Q$1,0)))} -> 5400 | Y38: {=IF(S38="","",INDEX($F38:$Q38,MATCH(INDEX(Rules!$G$2:$G$60,$D38),$F$1:$Q$1,0)))} | Z38: {=IF(T38="","",INDEX($F38:$Q38,MATCH(INDEX(Rules!$J$2:$J$60,$D38),$F$1:$Q$1,0)))} | AA38: {=IF(INDEX(Rules!$K$2:$K$60,$D38)="","",INDEX(Rules!$K$2:$K$60,$D38))} -> monthly rent | AB38: =IF(SUMPRODUCT((R38:W38<>"")*(ISNUMBER(SEARCH(Raw_Data!E38,R38:W38))+ISNUMBER(SEARCH(R38:W38,Raw_Data!E38))))>0,"OK","CHECK") -> OK
A39: =Raw_Data!A39 -> VVV-2024-038 | B39: =Raw_Data!D39 -> 2000 | C39: =LOWER(Raw_Data!C39&" | "&Raw_Data!F39) -> fleet service work order | paid from business bank account | D39: {=MATCH(1,ISNUMBER(SEARCH(Rules!$A$2:$A$60,C39))*(Rules!$A$2:$A$60<>""),0)} -> 5 | E39: {=INDEX(Rules!$A$2:$A$60,D39)} -> fleet service work order | F39: =B39 -> 2000 | G39: =IFERROR(__xludf.DUMMYFUNCTION("IFERROR(VALUE(SUBSTITUTE(REGEXEXTRACT(Raw_Data!J39,""Cost of goods sold: \$([\d,]+)""),"","","""")),0)"),0.0) -> 0 | H39: =IFERROR(__xludf.DUMMYFUNCTION("IFERROR(VALUE(SUBSTITUTE(REGEXEXTRACT(Raw_Data!J39,""withheld a \$([\d,]+) fee""),"","","""")),0)"),0.0) -> 0 | I39: =F39-H39 -> 2000 | J39: =IFERROR(__xludf.DUMMYFUNCTION("IFERROR(VALUE(SUBSTITUTE(REGEXEXTRACT(Raw_Data!J39,""(?i)interest \$([\d,]+)""),"","","""")),0)"),0.0) -> 0 | K39: =F39-J39 -> 2000 | L39: =IFERROR(__xludf.DUMMYFUNCTION("IFERROR(VALUE(SUBSTITUTE(REGEXEXTRACT(Raw_Data!F39,""\$([\d,]+) prior deposit applied""),"","","""")),0)"),0.0) -> 0 | M39: =F39-L39 -> 2000 | N39: =IFERROR(__xludf.DUMMYFUNCTION("IFERROR(VALUE(SUBSTITUTE(REGEXEXTRACT(Raw_Data!F39,""^\$([\d,]+) cash""),"","","""")),0)"),0.0) -> 0 | O39: =F39-N39 -> 2000 | P39: =IFERROR(__xludf.DUMMYFUNCTION("IFERROR(VALUE(SUBSTITUTE(REGEXEXTRACT(Raw_Data!J39,""labour \d+ h at \$\d+/h: \$([\d,]+)""),"","","""")),0)"),0.0) -> 0 | Q39: =F39-P39 -> 2000 | R39: {=IF(INDEX(Rules!$B$2:$B$60,$D39)="","",INDEX(Rules!$B$2:$B$60,$D39))} -> Repairs and Maintenance Expense | S39: {=IF(INDEX(Rules!$E$2:$E$60,$D39)="","",INDEX(Rules!$E$2:$E$60,$D39))} | T39: {=IF(INDEX(Rules!$H$2:$H$60,$D39)="","",INDEX(Rules!$H$2:$H$60,$D39))} | U39: {=IF(INDEX(Rules!$C$2:$C$60,$D39)="","",INDEX(Rules!$C$2:$C$60,$D39))} -> Cash | V39: {=IF(INDEX(Rules!$F$2:$F$60,$D39)="","",INDEX(Rules!$F$2:$F$60,$D39))} | W39: {=IF(INDEX(Rules!$I$2:$I$60,$D39)="","",INDEX(Rules!$I$2:$I$60,$D39))} | X39: {=IF(R39="","",INDEX($F39:$Q39,MATCH(INDEX(Rules!$D$2:$D$60,$D39),$F$1:$Q$1,0)))} -> 2000 | Y39: {=IF(S39="","",INDEX($F39:$Q39,MATCH(INDEX(Rules!$G$2:$G$60,$D39),$F$1:$Q$1,0)))} | Z39: {=IF(T39="","",INDEX($F39:$Q39,MATCH(INDEX(Rules!$J$2:$J$60,$D39),$F$1:$Q$1,0)))} | AA39: {=IF(INDEX(Rules!$K$2:$K$60,$D39)="","",INDEX(Rules!$K$2:$K$60,$D39))} -> fleet repairs | AB39: =IF(SUMPRODUCT((R39:W39<>"")*(ISNUMBER(SEARCH(Raw_Data!E39,R39:W39))+ISNUMBER(SEARCH(R39:W39,Raw_Data!E39))))>0,"OK","CHECK") -> OK
A40: =Raw_Data!A40 -> VVV-2024-039 | B40: =Raw_Data!D40 -> 600 | C40: =LOWER(Raw_Data!C40&" | "&Raw_Data!F40) -> monthly business insurance premium | automatic bank transfer; settled | D40: {=MATCH(1,ISNUMBER(SEARCH(Rules!$A$2:$A$60,C40))*(Rules!$A$2:$A$60<>""),0)} -> 20 | E40: {=INDEX(Rules!$A$2:$A$60,D40)} -> insurance | F40: =B40 -> 600 | G40: =IFERROR(__xludf.DUMMYFUNCTION("IFERROR(VALUE(SUBSTITUTE(REGEXEXTRACT(Raw_Data!J40,""Cost of goods sold: \$([\d,]+)""),"","","""")),0)"),0.0) -> 0 | H40: =IFERROR(__xludf.DUMMYFUNCTION("IFERROR(VALUE(SUBSTITUTE(REGEXEXTRACT(Raw_Data!J40,""withheld a \$([\d,]+) fee""),"","","""")),0)"),0.0) -> 0 | I40: =F40-H40 -> 600 | J40: =IFERROR(__xludf.DUMMYFUNCTION("IFERROR(VALUE(SUBSTITUTE(REGEXEXTRACT(Raw_Data!J40,""(?i)interest \$([\d,]+)""),"","","""")),0)"),0.0) -> 0 | K40: =F40-J40 -> 600 | L40: =IFERROR(__xludf.DUMMYFUNCTION("IFERROR(VALUE(SUBSTITUTE(REGEXEXTRACT(Raw_Data!F40,""\$([\d,]+) prior deposit applied""),"","","""")),0)"),0.0) -> 0 | M40: =F40-L40 -> 600 | N40: =IFERROR(__xludf.DUMMYFUNCTION("IFERROR(VALUE(SUBSTITUTE(REGEXEXTRACT(Raw_Data!F40,""^\$([\d,]+) cash""),"","","""")),0)"),0.0) -> 0 | O40: =F40-N40 -> 600 | P40: =IFERROR(__xludf.DUMMYFUNCTION("IFERROR(VALUE(SUBSTITUTE(REGEXEXTRACT(Raw_Data!J40,""labour \d+ h at \$\d+/h: \$([\d,]+)""),"","","""")),0)"),0.0) -> 0 | Q40: =F40-P40 -> 600 | R40: {=IF(INDEX(Rules!$B$2:$B$60,$D40)="","",INDEX(Rules!$B$2:$B$60,$D40))} -> Insurance Expense | S40: {=IF(INDEX(Rules!$E$2:$E$60,$D40)="","",INDEX(Rules!$E$2:$E$60,$D40))} | T40: {=IF(INDEX(Rules!$H$2:$H$60,$D40)="","",INDEX(Rules!$H$2:$H$60,$D40))} | U40: {=IF(INDEX(Rules!$C$2:$C$60,$D40)="","",INDEX(Rules!$C$2:$C$60,$D40))} -> Cash | V40: {=IF(INDEX(Rules!$F$2:$F$60,$D40)="","",INDEX(Rules!$F$2:$F$60,$D40))} | W40: {=IF(INDEX(Rules!$I$2:$I$60,$D40)="","",INDEX(Rules!$I$2:$I$60,$D40))} | X40: {=IF(R40="","",INDEX($F40:$Q40,MATCH(INDEX(Rules!$D$2:$D$60,$D40),$F$1:$Q$1,0)))} -> 600 | Y40: {=IF(S40="","",INDEX($F40:$Q40,MATCH(INDEX(Rules!$G$2:$G$60,$D40),$F$1:$Q$1,0)))} | Z40: {=IF(T40="","",INDEX($F40:$Q40,MATCH(INDEX(Rules!$J$2:$J$60,$D40),$F$1:$Q$1,0)))} | AA40: {=IF(INDEX(Rules!$K$2:$K$60,$D40)="","",INDEX(Rules!$K$2:$K$60,$D40))} -> monthly insurance | AB40: =IF(SUMPRODUCT((R40:W40<>"")*(ISNUMBER(SEARCH(Raw_Data!E40,R40:W40))+ISNUMBER(SEARCH(R40:W40,Raw_Data!E40))))>0,"OK","CHECK") -> OK
A41: =Raw_Data!A41 -> VVV-2024-040 | B41: =Raw_Data!D41 -> 10000 | C41: =LOWER(Raw_Data!C41&" | "&Raw_Data!F41) -> equipment rental receipts batch | cash and card receipts; settled | D41: {=MATCH(1,ISNUMBER(SEARCH(Rules!$A$2:$A$60,C41))*(Rules!$A$2:$A$60<>""),0)} -> 26 | E41: {=INDEX(Rules!$A$2:$A$60,D41)} -> rental receipts | F41: =B41 -> 10000 | G41: =IFERROR(__xludf.DUMMYFUNCTION("IFERROR(VALUE(SUBSTITUTE(REGEXEXTRACT(Raw_Data!J41,""Cost of goods sold: \$([\d,]+)""),"","","""")),0)"),0.0) -> 0 | H41: =IFERROR(__xludf.DUMMYFUNCTION("IFERROR(VALUE(SUBSTITUTE(REGEXEXTRACT(Raw_Data!J41,""withheld a \$([\d,]+) fee""),"","","""")),0)"),0.0) -> 0 | I41: =F41-H41 -> 10000 | J41: =IFERROR(__xludf.DUMMYFUNCTION("IFERROR(VALUE(SUBSTITUTE(REGEXEXTRACT(Raw_Data!J41,""(?i)interest \$([\d,]+)""),"","","""")),0)"),0.0) -> 0 | K41: =F41-J41 -> 10000 | L41: =IFERROR(__xludf.DUMMYFUNCTION("IFERROR(VALUE(SUBSTITUTE(REGEXEXTRACT(Raw_Data!F41,""\$([\d,]+) prior deposit applied""),"","","""")),0)"),0.0) -> 0 | M41: =F41-L41 -> 10000 | N41: =IFERROR(__xludf.DUMMYFUNCTION("IFERROR(VALUE(SUBSTITUTE(REGEXEXTRACT(Raw_Data!F41,""^\$([\d,]+) cash""),"","","""")),0)"),0.0) -> 0 | O41: =F41-N41 -> 10000 | P41: =IFERROR(__xludf.DUMMYFUNCTION("IFERROR(VALUE(SUBSTITUTE(REGEXEXTRACT(Raw_Data!J41,""labour \d+ h at \$\d+/h: \$([\d,]+)""),"","","""")),0)"),0.0) -> 0 | Q41: =F41-P41 -> 10000 | R41: {=IF(INDEX(Rules!$B$2:$B$60,$D41)="","",INDEX(Rules!$B$2:$B$60,$D41))} -> Cash | S41: {=IF(INDEX(Rules!$E$2:$E$60,$D41)="","",INDEX(Rules!$E$2:$E$60,$D41))} | T41: {=IF(INDEX(Rules!$H$2:$H$60,$D41)="","",INDEX(Rules!$H$2:$H$60,$D41))} | U41: {=IF(INDEX(Rules!$C$2:$C$60,$D41)="","",INDEX(Rules!$C$2:$C$60,$D41))} -> Equipment Rental Revenue | V41: {=IF(INDEX(Rules!$F$2:$F$60,$D41)="","",INDEX(Rules!$F$2:$F$60,$D41))} | W41: {=IF(INDEX(Rules!$I$2:$I$60,$D41)="","",INDEX(Rules!$I$2:$I$60,$D41))} | X41: {=IF(R41="","",INDEX($F41:$Q41,MATCH(INDEX(Rules!$D$2:$D$60,$D41),$F$1:$Q$1,0)))} -> 10000 | Y41: {=IF(S41="","",INDEX($F41:$Q41,MATCH(INDEX(Rules!$G$2:$G$60,$D41),$F$1:$Q$1,0)))} | Z41: {=IF(T41="","",INDEX($F41:$Q41,MATCH(INDEX(Rules!$J$2:$J$60,$D41),$F$1:$Q$1,0)))} | AA41: {=IF(INDEX(Rules!$K$2:$K$60,$D41)="","",INDEX(Rules!$K$2:$K$60,$D41))} -> rentals done and paid | AB41: =IF(SUMPRODUCT((R41:W41<>"")*(ISNUMBER(SEARCH(Raw_Data!E41,R41:W41))+ISNUMBER(SEARCH(R41:W41,Raw_Data!E41))))>0,"OK","CHECK") -> OK
A42: =Raw_Data!A42 -> VVV-2024-041 | B42: =Raw_Data!D42 -> 8000 | C42: =LOWER(Raw_Data!C42&" | "&Raw_Data!F42) -> purchased additional retail inventory | bank transfer; settled | D42: {=MATCH(1,ISNUMBER(SEARCH(Rules!$A$2:$A$60,C42))*(Rules!$A$2:$A$60<>""),0)} -> 10 | E42: {=INDEX(Rules!$A$2:$A$60,D42)} -> inventory | F42: =B42 -> 8000 | G42: =IFERROR(__xludf.DUMMYFUNCTION("IFERROR(VALUE(SUBSTITUTE(REGEXEXTRACT(Raw_Data!J42,""Cost of goods sold: \$([\d,]+)""),"","","""")),0)"),0.0) -> 0 | H42: =IFERROR(__xludf.DUMMYFUNCTION("IFERROR(VALUE(SUBSTITUTE(REGEXEXTRACT(Raw_Data!J42,""withheld a \$([\d,]+) fee""),"","","""")),0)"),0.0) -> 0 | I42: =F42-H42 -> 8000 | J42: =IFERROR(__xludf.DUMMYFUNCTION("IFERROR(VALUE(SUBSTITUTE(REGEXEXTRACT(Raw_Data!J42,""(?i)interest \$([\d,]+)""),"","","""")),0)"),0.0) -> 0 | K42: =F42-J42 -> 8000 | L42: =IFERROR(__xludf.DUMMYFUNCTION("IFERROR(VALUE(SUBSTITUTE(REGEXEXTRACT(Raw_Data!F42,""\$([\d,]+) prior deposit applied""),"","","""")),0)"),0.0) -> 0 | M42: =F42-L42 -> 8000 | N42: =IFERROR(__xludf.DUMMYFUNCTION("IFERROR(VALUE(SUBSTITUTE(REGEXEXTRACT(Raw_Data!F42,""^\$([\d,]+) cash""),"","","""")),0)"),0.0) -> 0 | O42: =F42-N42 -> 8000 | P42: =IFERROR(__xludf.DUMMYFUNCTION("IFERROR(VALUE(SUBSTITUTE(REGEXEXTRACT(Raw_Data!J42,""labour \d+ h at \$\d+/h: \$([\d,]+)""),"","","""")),0)"),0.0) -> 0 | Q42: =F42-P42 -> 8000 | R42: {=IF(INDEX(Rules!$B$2:$B$60,$D42)="","",INDEX(Rules!$B$2:$B$60,$D42))} -> Inventory | S42: {=IF(INDEX(Rules!$E$2:$E$60,$D42)="","",INDEX(Rules!$E$2:$E$60,$D42))} | T42: {=IF(INDEX(Rules!$H$2:$H$60,$D42)="","",INDEX(Rules!$H$2:$H$60,$D42))} | U42: {=IF(INDEX(Rules!$C$2:$C$60,$D42)="","",INDEX(Rules!$C$2:$C$60,$D42))} -> Cash | V42: {=IF(INDEX(Rules!$F$2:$F$60,$D42)="","",INDEX(Rules!$F$2:$F$60,$D42))} | W42: {=IF(INDEX(Rules!$I$2:$I$60,$D42)="","",INDEX(Rules!$I$2:$I$60,$D42))} | X42: {=IF(R42="","",INDEX($F42:$Q42,MATCH(INDEX(Rules!$D$2:$D$60,$D42),$F$1:$Q$1,0)))} -> 8000 | Y42: {=IF(S42="","",INDEX($F42:$Q42,MATCH(INDEX(Rules!$G$2:$G$60,$D42),$F$1:$Q$1,0)))} | Z42: {=IF(T42="","",INDEX($F42:$Q42,MATCH(INDEX(Rules!$J$2:$J$60,$D42),$F$1:$Q$1,0)))} | AA42: {=IF(INDEX(Rules!$K$2:$K$60,$D42)="","",INDEX(Rules!$K$2:$K$60,$D42))} -> stuff to resell, paid cash | AB42: =IF(SUMPRODUCT((R42:W42<>"")*(ISNUMBER(SEARCH(Raw_Data!E42,R42:W42))+ISNUMBER(SEARCH(R42:W42,Raw_Data!E42))))>0,"OK","CHECK") -> OK
A43: =Raw_Data!A43 -> VVV-2024-042 | B43: =Raw_Data!D43 -> 6500 | C43: =LOWER(Raw_Data!C43&" | "&Raw_Data!F43) -> retail camping-supply sales | cash and card receipts; settled | D43: {=MATCH(1,ISNUMBER(SEARCH(Rules!$A$2:$A$60,C43))*(Rules!$A$2:$A$60<>""),0)} -> 12 | E43: {=INDEX(Rules!$A$2:$A$60,D43)} -> camping-supply sales | F43: =B43 -> 6500 | G43: =IFERROR(__xludf.DUMMYFUNCTION("IFERROR(VALUE(SUBSTITUTE(REGEXEXTRACT(Raw_Data!J43,""Cost of goods sold: \$([\d,]+)""),"","","""")),0)"),3900.0) -> 3900 | H43: =IFERROR(__xludf.DUMMYFUNCTION("IFERROR(VALUE(SUBSTITUTE(REGEXEXTRACT(Raw_Data!J43,""withheld a \$([\d,]+) fee""),"","","""")),0)"),0.0) -> 0 | I43: =F43-H43 -> 6500 | J43: =IFERROR(__xludf.DUMMYFUNCTION("IFERROR(VALUE(SUBSTITUTE(REGEXEXTRACT(Raw_Data!J43,""(?i)interest \$([\d,]+)""),"","","""")),0)"),0.0) -> 0 | K43: =F43-J43 -> 6500 | L43: =IFERROR(__xludf.DUMMYFUNCTION("IFERROR(VALUE(SUBSTITUTE(REGEXEXTRACT(Raw_Data!F43,""\$([\d,]+) prior deposit applied""),"","","""")),0)"),0.0) -> 0 | M43: =F43-L43 -> 6500 | N43: =IFERROR(__xludf.DUMMYFUNCTION("IFERROR(VALUE(SUBSTITUTE(REGEXEXTRACT(Raw_Data!F43,""^\$([\d,]+) cash""),"","","""")),0)"),0.0) -> 0 | O43: =F43-N43 -> 6500 | P43: =IFERROR(__xludf.DUMMYFUNCTION("IFERROR(VALUE(SUBSTITUTE(REGEXEXTRACT(Raw_Data!J43,""labour \d+ h at \$\d+/h: \$([\d,]+)""),"","","""")),0)"),0.0) -> 0 | Q43: =F43-P43 -> 6500 | R43: {=IF(INDEX(Rules!$B$2:$B$60,$D43)="","",INDEX(Rules!$B$2:$B$60,$D43))} -> Cash | S43: {=IF(INDEX(Rules!$E$2:$E$60,$D43)="","",INDEX(Rules!$E$2:$E$60,$D43))} -> Cost of Goods Sold | T43: {=IF(INDEX(Rules!$H$2:$H$60,$D43)="","",INDEX(Rules!$H$2:$H$60,$D43))} | U43: {=IF(INDEX(Rules!$C$2:$C$60,$D43)="","",INDEX(Rules!$C$2:$C$60,$D43))} -> Retail Sales Revenue | V43: {=IF(INDEX(Rules!$F$2:$F$60,$D43)="","",INDEX(Rules!$F$2:$F$60,$D43))} -> Inventory | W43: {=IF(INDEX(Rules!$I$2:$I$60,$D43)="","",INDEX(Rules!$I$2:$I$60,$D43))} | X43: {=IF(R43="","",INDEX($F43:$Q43,MATCH(INDEX(Rules!$D$2:$D$60,$D43),$F$1:$Q$1,0)))} -> 6500 | Y43: {=IF(S43="","",INDEX($F43:$Q43,MATCH(INDEX(Rules!$G$2:$G$60,$D43),$F$1:$Q$1,0)))} -> 3900 | Z43: {=IF(T43="","",INDEX($F43:$Q43,MATCH(INDEX(Rules!$J$2:$J$60,$D43),$F$1:$Q$1,0)))} | AA43: {=IF(INDEX(Rules!$K$2:$K$60,$D43)="","",INDEX(Rules!$K$2:$K$60,$D43))} -> sale + cost of the goods comes out of inventory (COGS) | AB43: =IF(SUMPRODUCT((R43:W43<>"")*(ISNUMBER(SEARCH(Raw_Data!E43,R43:W43))+ISNUMBER(SEARCH(R43:W43,Raw_Data!E43))))>0,"OK","CHECK") -> OK
A44: =Raw_Data!A44 -> VVV-2024-043 | B44: =Raw_Data!D44 -> 7000 | C44: =LOWER(Raw_Data!C44&" | "&Raw_Data!F44) -> guided tour revenue | cash and card receipts; settled | D44: {=MATCH(1,ISNUMBER(SEARCH(Rules!$A$2:$A$60,C44))*(Rules!$A$2:$A$60<>""),0)} -> 32 | E44: {=INDEX(Rules!$A$2:$A$60,D44)} -> tour revenue | F44: =B44 -> 7000 | G44: =IFERROR(__xludf.DUMMYFUNCTION("IFERROR(VALUE(SUBSTITUTE(REGEXEXTRACT(Raw_Data!J44,""Cost of goods sold: \$([\d,]+)""),"","","""")),0)"),0.0) -> 0 | H44: =IFERROR(__xludf.DUMMYFUNCTION("IFERROR(VALUE(SUBSTITUTE(REGEXEXTRACT(Raw_Data!J44,""withheld a \$([\d,]+) fee""),"","","""")),0)"),0.0) -> 0 | I44: =F44-H44 -> 7000 | J44: =IFERROR(__xludf.DUMMYFUNCTION("IFERROR(VALUE(SUBSTITUTE(REGEXEXTRACT(Raw_Data!J44,""(?i)interest \$([\d,]+)""),"","","""")),0)"),0.0) -> 0 | K44: =F44-J44 -> 7000 | L44: =IFERROR(__xludf.DUMMYFUNCTION("IFERROR(VALUE(SUBSTITUTE(REGEXEXTRACT(Raw_Data!F44,""\$([\d,]+) prior deposit applied""),"","","""")),0)"),0.0) -> 0 | M44: =F44-L44 -> 7000 | N44: =IFERROR(__xludf.DUMMYFUNCTION("IFERROR(VALUE(SUBSTITUTE(REGEXEXTRACT(Raw_Data!F44,""^\$([\d,]+) cash""),"","","""")),0)"),0.0) -> 0 | O44: =F44-N44 -> 7000 | P44: =IFERROR(__xludf.DUMMYFUNCTION("IFERROR(VALUE(SUBSTITUTE(REGEXEXTRACT(Raw_Data!J44,""labour \d+ h at \$\d+/h: \$([\d,]+)""),"","","""")),0)"),0.0) -> 0 | Q44: =F44-P44 -> 7000 | R44: {=IF(INDEX(Rules!$B$2:$B$60,$D44)="","",INDEX(Rules!$B$2:$B$60,$D44))} -> Cash | S44: {=IF(INDEX(Rules!$E$2:$E$60,$D44)="","",INDEX(Rules!$E$2:$E$60,$D44))} | T44: {=IF(INDEX(Rules!$H$2:$H$60,$D44)="","",INDEX(Rules!$H$2:$H$60,$D44))} | U44: {=IF(INDEX(Rules!$C$2:$C$60,$D44)="","",INDEX(Rules!$C$2:$C$60,$D44))} -> Tour Revenue | V44: {=IF(INDEX(Rules!$F$2:$F$60,$D44)="","",INDEX(Rules!$F$2:$F$60,$D44))} | W44: {=IF(INDEX(Rules!$I$2:$I$60,$D44)="","",INDEX(Rules!$I$2:$I$60,$D44))} | X44: {=IF(R44="","",INDEX($F44:$Q44,MATCH(INDEX(Rules!$D$2:$D$60,$D44),$F$1:$Q$1,0)))} -> 7000 | Y44: {=IF(S44="","",INDEX($F44:$Q44,MATCH(INDEX(Rules!$G$2:$G$60,$D44),$F$1:$Q$1,0)))} | Z44: {=IF(T44="","",INDEX($F44:$Q44,MATCH(INDEX(Rules!$J$2:$J$60,$D44),$F$1:$Q$1,0)))} | AA44: {=IF(INDEX(Rules!$K$2:$K$60,$D44)="","",INDEX(Rules!$K$2:$K$60,$D44))} -> tours done and paid | AB44: =IF(SUMPRODUCT((R44:W44<>"")*(ISNUMBER(SEARCH(Raw_Data!E44,R44:W44))+ISNUMBER(SEARCH(R44:W44,Raw_Data!E44))))>0,"OK","CHECK") -> OK
A45: =Raw_Data!A45 -> VVV-2024-044 | B45: =Raw_Data!D45 -> 1800 | C45: =LOWER(Raw_Data!C45&" | "&Raw_Data!F45) -> seasonal guide safety course | business debit card; settled | D45: {=MATCH(1,ISNUMBER(SEARCH(Rules!$A$2:$A$60,C45))*(Rules!$A$2:$A$60<>""),0)} -> 25 | E45: {=INDEX(Rules!$A$2:$A$60,D45)} -> safety course | F45: =B45 -> 1800 | G45: =IFERROR(__xludf.DUMMYFUNCTION("IFERROR(VALUE(SUBSTITUTE(REGEXEXTRACT(Raw_Data!J45,""Cost of goods sold: \$([\d,]+)""),"","","""")),0)"),0.0) -> 0 | H45: =IFERROR(__xludf.DUMMYFUNCTION("IFERROR(VALUE(SUBSTITUTE(REGEXEXTRACT(Raw_Data!J45,""withheld a \$([\d,]+) fee""),"","","""")),0)"),0.0) -> 0 | I45: =F45-H45 -> 1800 | J45: =IFERROR(__xludf.DUMMYFUNCTION("IFERROR(VALUE(SUBSTITUTE(REGEXEXTRACT(Raw_Data!J45,""(?i)interest \$([\d,]+)""),"","","""")),0)"),0.0) -> 0 | K45: =F45-J45 -> 1800 | L45: =IFERROR(__xludf.DUMMYFUNCTION("IFERROR(VALUE(SUBSTITUTE(REGEXEXTRACT(Raw_Data!F45,""\$([\d,]+) prior deposit applied""),"","","""")),0)"),0.0) -> 0 | M45: =F45-L45 -> 1800 | N45: =IFERROR(__xludf.DUMMYFUNCTION("IFERROR(VALUE(SUBSTITUTE(REGEXEXTRACT(Raw_Data!F45,""^\$([\d,]+) cash""),"","","""")),0)"),0.0) -> 0 | O45: =F45-N45 -> 1800 | P45: =IFERROR(__xludf.DUMMYFUNCTION("IFERROR(VALUE(SUBSTITUTE(REGEXEXTRACT(Raw_Data!J45,""labour \d+ h at \$\d+/h: \$([\d,]+)""),"","","""")),0)"),0.0) -> 0 | Q45: =F45-P45 -> 1800 | R45: {=IF(INDEX(Rules!$B$2:$B$60,$D45)="","",INDEX(Rules!$B$2:$B$60,$D45))} -> Training Expense | S45: {=IF(INDEX(Rules!$E$2:$E$60,$D45)="","",INDEX(Rules!$E$2:$E$60,$D45))} | T45: {=IF(INDEX(Rules!$H$2:$H$60,$D45)="","",INDEX(Rules!$H$2:$H$60,$D45))} | U45: {=IF(INDEX(Rules!$C$2:$C$60,$D45)="","",INDEX(Rules!$C$2:$C$60,$D45))} -> Cash | V45: {=IF(INDEX(Rules!$F$2:$F$60,$D45)="","",INDEX(Rules!$F$2:$F$60,$D45))} | W45: {=IF(INDEX(Rules!$I$2:$I$60,$D45)="","",INDEX(Rules!$I$2:$I$60,$D45))} | X45: {=IF(R45="","",INDEX($F45:$Q45,MATCH(INDEX(Rules!$D$2:$D$60,$D45),$F$1:$Q$1,0)))} -> 1800 | Y45: {=IF(S45="","",INDEX($F45:$Q45,MATCH(INDEX(Rules!$G$2:$G$60,$D45),$F$1:$Q$1,0)))} | Z45: {=IF(T45="","",INDEX($F45:$Q45,MATCH(INDEX(Rules!$J$2:$J$60,$D45),$F$1:$Q$1,0)))} | AA45: {=IF(INDEX(Rules!$K$2:$K$60,$D45)="","",INDEX(Rules!$K$2:$K$60,$D45))} -> guide training | AB45: =IF(SUMPRODUCT((R45:W45<>"")*(ISNUMBER(SEARCH(Raw_Data!E45,R45:W45))+ISNUMBER(SEARCH(R45:W45,Raw_Data!E45))))>0,"OK","CHECK") -> OK
A46: =Raw_Data!A46 -> VVV-2024-045 | B46: =Raw_Data!D46 -> 10200 | C46: =LOWER(Raw_Data!C46&" | "&Raw_Data!F46) -> employee payroll settlement | payroll and claims paid from business bank account | D46: {=MATCH(1,ISNUMBER(SEARCH(Rules!$A$2:$A$60,C46))*(Rules!$A$2:$A$60<>""),0)} -> 23 | E46: {=INDEX(Rules!$A$2:$A$60,D46)} -> payroll | F46: =B46 -> 10200 | G46: =IFERROR(__xludf.DUMMYFUNCTION("IFERROR(VALUE(SUBSTITUTE(REGEXEXTRACT(Raw_Data!J46,""Cost of goods sold: \$([\d,]+)""),"","","""")),0)"),0.0) -> 0 | H46: =IFERROR(__xludf.DUMMYFUNCTION("IFERROR(VALUE(SUBSTITUTE(REGEXEXTRACT(Raw_Data!J46,""withheld a \$([\d,]+) fee""),"","","""")),0)"),0.0) -> 0 | I46: =F46-H46 -> 10200 | J46: =IFERROR(__xludf.DUMMYFUNCTION("IFERROR(VALUE(SUBSTITUTE(REGEXEXTRACT(Raw_Data!J46,""(?i)interest \$([\d,]+)""),"","","""")),0)"),0.0) -> 0 | K46: =F46-J46 -> 10200 | L46: =IFERROR(__xludf.DUMMYFUNCTION("IFERROR(VALUE(SUBSTITUTE(REGEXEXTRACT(Raw_Data!F46,""\$([\d,]+) prior deposit applied""),"","","""")),0)"),0.0) -> 0 | M46: =F46-L46 -> 10200 | N46: =IFERROR(__xludf.DUMMYFUNCTION("IFERROR(VALUE(SUBSTITUTE(REGEXEXTRACT(Raw_Data!F46,""^\$([\d,]+) cash""),"","","""")),0)"),0.0) -> 0 | O46: =F46-N46 -> 10200 | P46: =IFERROR(__xludf.DUMMYFUNCTION("IFERROR(VALUE(SUBSTITUTE(REGEXEXTRACT(Raw_Data!J46,""labour \d+ h at \$\d+/h: \$([\d,]+)""),"","","""")),0)"),0.0) -> 0 | Q46: =F46-P46 -> 10200 | R46: {=IF(INDEX(Rules!$B$2:$B$60,$D46)="","",INDEX(Rules!$B$2:$B$60,$D46))} -> Wages Expense | S46: {=IF(INDEX(Rules!$E$2:$E$60,$D46)="","",INDEX(Rules!$E$2:$E$60,$D46))} | T46: {=IF(INDEX(Rules!$H$2:$H$60,$D46)="","",INDEX(Rules!$H$2:$H$60,$D46))} | U46: {=IF(INDEX(Rules!$C$2:$C$60,$D46)="","",INDEX(Rules!$C$2:$C$60,$D46))} -> Cash | V46: {=IF(INDEX(Rules!$F$2:$F$60,$D46)="","",INDEX(Rules!$F$2:$F$60,$D46))} | W46: {=IF(INDEX(Rules!$I$2:$I$60,$D46)="","",INDEX(Rules!$I$2:$I$60,$D46))} | X46: {=IF(R46="","",INDEX($F46:$Q46,MATCH(INDEX(Rules!$D$2:$D$60,$D46),$F$1:$Q$1,0)))} -> 10200 | Y46: {=IF(S46="","",INDEX($F46:$Q46,MATCH(INDEX(Rules!$G$2:$G$60,$D46),$F$1:$Q$1,0)))} | Z46: {=IF(T46="","",INDEX($F46:$Q46,MATCH(INDEX(Rules!$J$2:$J$60,$D46),$F$1:$Q$1,0)))} | AA46: {=IF(INDEX(Rules!$K$2:$K$60,$D46)="","",INDEX(Rules!$K$2:$K$60,$D46))} -> wages, includes E04's $200 travel claim | AB46: =IF(SUMPRODUCT((R46:W46<>"")*(ISNUMBER(SEARCH(Raw_Data!E46,R46:W46))+ISNUMBER(SEARCH(R46:W46,Raw_Data!E46))))>0,"OK","CHECK") -> OK
A47: =Raw_Data!A47 -> VVV-2024-046 | B47: =Raw_Data!D47 -> 3000 | C47: =LOWER(Raw_Data!C47&" | "&Raw_Data!F47) -> customer deposits for june solstice event | cash and card receipts; event scheduled for june | D47: {=MATCH(1,ISNUMBER(SEARCH(Rules!$A$2:$A$60,C47))*(Rules!$A$2:$A$60<>""),0)} -> 31 | E47: {=INDEX(Rules!$A$2:$A$60,D47)} -> deposit | F47: =B47 -> 3000 | G47: =IFERROR(__xludf.DUMMYFUNCTION("IFERROR(VALUE(SUBSTITUTE(REGEXEXTRACT(Raw_Data!J47,""Cost of goods sold: \$([\d,]+)""),"","","""")),0)"),0.0) -> 0 | H47: =IFERROR(__xludf.DUMMYFUNCTION("IFERROR(VALUE(SUBSTITUTE(REGEXEXTRACT(Raw_Data!J47,""withheld a \$([\d,]+) fee""),"","","""")),0)"),0.0) -> 0 | I47: =F47-H47 -> 3000 | J47: =IFERROR(__xludf.DUMMYFUNCTION("IFERROR(VALUE(SUBSTITUTE(REGEXEXTRACT(Raw_Data!J47,""(?i)interest \$([\d,]+)""),"","","""")),0)"),0.0) -> 0 | K47: =F47-J47 -> 3000 | L47: =IFERROR(__xludf.DUMMYFUNCTION("IFERROR(VALUE(SUBSTITUTE(REGEXEXTRACT(Raw_Data!F47,""\$([\d,]+) prior deposit applied""),"","","""")),0)"),0.0) -> 0 | M47: =F47-L47 -> 3000 | N47: =IFERROR(__xludf.DUMMYFUNCTION("IFERROR(VALUE(SUBSTITUTE(REGEXEXTRACT(Raw_Data!F47,""^\$([\d,]+) cash""),"","","""")),0)"),0.0) -> 0 | O47: =F47-N47 -> 3000 | P47: =IFERROR(__xludf.DUMMYFUNCTION("IFERROR(VALUE(SUBSTITUTE(REGEXEXTRACT(Raw_Data!J47,""labour \d+ h at \$\d+/h: \$([\d,]+)""),"","","""")),0)"),0.0) -> 0 | Q47: =F47-P47 -> 3000 | R47: {=IF(INDEX(Rules!$B$2:$B$60,$D47)="","",INDEX(Rules!$B$2:$B$60,$D47))} -> Cash | S47: {=IF(INDEX(Rules!$E$2:$E$60,$D47)="","",INDEX(Rules!$E$2:$E$60,$D47))} | T47: {=IF(INDEX(Rules!$H$2:$H$60,$D47)="","",INDEX(Rules!$H$2:$H$60,$D47))} | U47: {=IF(INDEX(Rules!$C$2:$C$60,$D47)="","",INDEX(Rules!$C$2:$C$60,$D47))} -> Unearned Revenue | V47: {=IF(INDEX(Rules!$F$2:$F$60,$D47)="","",INDEX(Rules!$F$2:$F$60,$D47))} | W47: {=IF(INDEX(Rules!$I$2:$I$60,$D47)="","",INDEX(Rules!$I$2:$I$60,$D47))} | X47: {=IF(R47="","",INDEX($F47:$Q47,MATCH(INDEX(Rules!$D$2:$D$60,$D47),$F$1:$Q$1,0)))} -> 3000 | Y47: {=IF(S47="","",INDEX($F47:$Q47,MATCH(INDEX(Rules!$G$2:$G$60,$D47),$F$1:$Q$1,0)))} | Z47: {=IF(T47="","",INDEX($F47:$Q47,MATCH(INDEX(Rules!$J$2:$J$60,$D47),$F$1:$Q$1,0)))} | AA47: {=IF(INDEX(Rules!$K$2:$K$60,$D47)="","",INDEX(Rules!$K$2:$K$60,$D47))} -> paid before the service -> not earned yet (unearned) | AB47: =IF(SUMPRODUCT((R47:W47<>"")*(ISNUMBER(SEARCH(Raw_Data!E47,R47:W47))+ISNUMBER(SEARCH(R47:W47,Raw_Data!E47))))>0,"OK","CHECK") -> OK
A48: =Raw_Data!A48 -> VVV-2024-047 | B48: =Raw_Data!D48 -> 898 | C48: =LOWER(Raw_Data!C48&" | "&Raw_Data!F48) -> monthly utility settlement | paid from business bank account | D48: {=MATCH(1,ISNUMBER(SEARCH(Rules!$A$2:$A$60,C48))*(Rules!$A$2:$A$60<>""),0)} -> 24 | E48: {=INDEX(Rules!$A$2:$A$60,D48)} -> utility | F48: =B48 -> 898 | G48: =IFERROR(__xludf.DUMMYFUNCTION("IFERROR(VALUE(SUBSTITUTE(REGEXEXTRACT(Raw_Data!J48,""Cost of goods sold: \$([\d,]+)""),"","","""")),0)"),0.0) -> 0 | H48: =IFERROR(__xludf.DUMMYFUNCTION("IFERROR(VALUE(SUBSTITUTE(REGEXEXTRACT(Raw_Data!J48,""withheld a \$([\d,]+) fee""),"","","""")),0)"),0.0) -> 0 | I48: =F48-H48 -> 898 | J48: =IFERROR(__xludf.DUMMYFUNCTION("IFERROR(VALUE(SUBSTITUTE(REGEXEXTRACT(Raw_Data!J48,""(?i)interest \$([\d,]+)""),"","","""")),0)"),0.0) -> 0 | K48: =F48-J48 -> 898 | L48: =IFERROR(__xludf.DUMMYFUNCTION("IFERROR(VALUE(SUBSTITUTE(REGEXEXTRACT(Raw_Data!F48,""\$([\d,]+) prior deposit applied""),"","","""")),0)"),0.0) -> 0 | M48: =F48-L48 -> 898 | N48: =IFERROR(__xludf.DUMMYFUNCTION("IFERROR(VALUE(SUBSTITUTE(REGEXEXTRACT(Raw_Data!F48,""^\$([\d,]+) cash""),"","","""")),0)"),0.0) -> 0 | O48: =F48-N48 -> 898 | P48: =IFERROR(__xludf.DUMMYFUNCTION("IFERROR(VALUE(SUBSTITUTE(REGEXEXTRACT(Raw_Data!J48,""labour \d+ h at \$\d+/h: \$([\d,]+)""),"","","""")),0)"),0.0) -> 0 | Q48: =F48-P48 -> 898 | R48: {=IF(INDEX(Rules!$B$2:$B$60,$D48)="","",INDEX(Rules!$B$2:$B$60,$D48))} -> Utilities Expense | S48: {=IF(INDEX(Rules!$E$2:$E$60,$D48)="","",INDEX(Rules!$E$2:$E$60,$D48))} | T48: {=IF(INDEX(Rules!$H$2:$H$60,$D48)="","",INDEX(Rules!$H$2:$H$60,$D48))} | U48: {=IF(INDEX(Rules!$C$2:$C$60,$D48)="","",INDEX(Rules!$C$2:$C$60,$D48))} -> Cash | V48: {=IF(INDEX(Rules!$F$2:$F$60,$D48)="","",INDEX(Rules!$F$2:$F$60,$D48))} | W48: {=IF(INDEX(Rules!$I$2:$I$60,$D48)="","",INDEX(Rules!$I$2:$I$60,$D48))} | X48: {=IF(R48="","",INDEX($F48:$Q48,MATCH(INDEX(Rules!$D$2:$D$60,$D48),$F$1:$Q$1,0)))} -> 898 | Y48: {=IF(S48="","",INDEX($F48:$Q48,MATCH(INDEX(Rules!$G$2:$G$60,$D48),$F$1:$Q$1,0)))} | Z48: {=IF(T48="","",INDEX($F48:$Q48,MATCH(INDEX(Rules!$J$2:$J$60,$D48),$F$1:$Q$1,0)))} | AA48: {=IF(INDEX(Rules!$K$2:$K$60,$D48)="","",INDEX(Rules!$K$2:$K$60,$D48))} -> monthly utilities | AB48: =IF(SUMPRODUCT((R48:W48<>"")*(ISNUMBER(SEARCH(Raw_Data!E48,R48:W48))+ISNUMBER(SEARCH(R48:W48,Raw_Data!E48))))>0,"OK","CHECK") -> OK
A49: =Raw_Data!A49 -> VVV-2024-048 | B49: =Raw_Data!D49 -> 5400 | C49: =LOWER(Raw_Data!C49&" | "&Raw_Data!F49) -> monthly facility rent | automatic bank transfer; settled | D49: {=MATCH(1,ISNUMBER(SEARCH(Rules!$A$2:$A$60,C49))*(Rules!$A$2:$A$60<>""),0)} -> 15 | E49: {=INDEX(Rules!$A$2:$A$60,D49)} -> facility rent | F49: =B49 -> 5400 | G49: =IFERROR(__xludf.DUMMYFUNCTION("IFERROR(VALUE(SUBSTITUTE(REGEXEXTRACT(Raw_Data!J49,""Cost of goods sold: \$([\d,]+)""),"","","""")),0)"),0.0) -> 0 | H49: =IFERROR(__xludf.DUMMYFUNCTION("IFERROR(VALUE(SUBSTITUTE(REGEXEXTRACT(Raw_Data!J49,""withheld a \$([\d,]+) fee""),"","","""")),0)"),0.0) -> 0 | I49: =F49-H49 -> 5400 | J49: =IFERROR(__xludf.DUMMYFUNCTION("IFERROR(VALUE(SUBSTITUTE(REGEXEXTRACT(Raw_Data!J49,""(?i)interest \$([\d,]+)""),"","","""")),0)"),0.0) -> 0 | K49: =F49-J49 -> 5400 | L49: =IFERROR(__xludf.DUMMYFUNCTION("IFERROR(VALUE(SUBSTITUTE(REGEXEXTRACT(Raw_Data!F49,""\$([\d,]+) prior deposit applied""),"","","""")),0)"),0.0) -> 0 | M49: =F49-L49 -> 5400 | N49: =IFERROR(__xludf.DUMMYFUNCTION("IFERROR(VALUE(SUBSTITUTE(REGEXEXTRACT(Raw_Data!F49,""^\$([\d,]+) cash""),"","","""")),0)"),0.0) -> 0 | O49: =F49-N49 -> 5400 | P49: =IFERROR(__xludf.DUMMYFUNCTION("IFERROR(VALUE(SUBSTITUTE(REGEXEXTRACT(Raw_Data!J49,""labour \d+ h at \$\d+/h: \$([\d,]+)""),"","","""")),0)"),0.0) -> 0 | Q49: =F49-P49 -> 5400 | R49: {=IF(INDEX(Rules!$B$2:$B$60,$D49)="","",INDEX(Rules!$B$2:$B$60,$D49))} -> Rent Expense | S49: {=IF(INDEX(Rules!$E$2:$E$60,$D49)="","",INDEX(Rules!$E$2:$E$60,$D49))} | T49: {=IF(INDEX(Rules!$H$2:$H$60,$D49)="","",INDEX(Rules!$H$2:$H$60,$D49))} | U49: {=IF(INDEX(Rules!$C$2:$C$60,$D49)="","",INDEX(Rules!$C$2:$C$60,$D49))} -> Cash | V49: {=IF(INDEX(Rules!$F$2:$F$60,$D49)="","",INDEX(Rules!$F$2:$F$60,$D49))} | W49: {=IF(INDEX(Rules!$I$2:$I$60,$D49)="","",INDEX(Rules!$I$2:$I$60,$D49))} | X49: {=IF(R49="","",INDEX($F49:$Q49,MATCH(INDEX(Rules!$D$2:$D$60,$D49),$F$1:$Q$1,0)))} -> 5400 | Y49: {=IF(S49="","",INDEX($F49:$Q49,MATCH(INDEX(Rules!$G$2:$G$60,$D49),$F$1:$Q$1,0)))} | Z49: {=IF(T49="","",INDEX($F49:$Q49,MATCH(INDEX(Rules!$J$2:$J$60,$D49),$F$1:$Q$1,0)))} | AA49: {=IF(INDEX(Rules!$K$2:$K$60,$D49)="","",INDEX(Rules!$K$2:$K$60,$D49))} -> monthly rent | AB49: =IF(SUMPRODUCT((R49:W49<>"")*(ISNUMBER(SEARCH(Raw_Data!E49,R49:W49))+ISNUMBER(SEARCH(R49:W49,Raw_Data!E49))))>0,"OK","CHECK") -> OK
A50: =Raw_Data!A50 -> VVV-2024-049 | B50: =Raw_Data!D50 -> 4000 | C50: =LOWER(Raw_Data!C50&" | "&Raw_Data!F50) -> collected part of march corporate tour receivable | bank transfer received | D50: {=MATCH(1,ISNUMBER(SEARCH(Rules!$A$2:$A$60,C50))*(Rules!$A$2:$A$60<>""),0)} -> 30 | E50: {=INDEX(Rules!$A$2:$A$60,D50)} -> collected | F50: =B50 -> 4000 | G50: =IFERROR(__xludf.DUMMYFUNCTION("IFERROR(VALUE(SUBSTITUTE(REGEXEXTRACT(Raw_Data!J50,""Cost of goods sold: \$([\d,]+)""),"","","""")),0)"),0.0) -> 0 | H50: =IFERROR(__xludf.DUMMYFUNCTION("IFERROR(VALUE(SUBSTITUTE(REGEXEXTRACT(Raw_Data!J50,""withheld a \$([\d,]+) fee""),"","","""")),0)"),0.0) -> 0 | I50: =F50-H50 -> 4000 | J50: =IFERROR(__xludf.DUMMYFUNCTION("IFERROR(VALUE(SUBSTITUTE(REGEXEXTRACT(Raw_Data!J50,""(?i)interest \$([\d,]+)""),"","","""")),0)"),0.0) -> 0 | K50: =F50-J50 -> 4000 | L50: =IFERROR(__xludf.DUMMYFUNCTION("IFERROR(VALUE(SUBSTITUTE(REGEXEXTRACT(Raw_Data!F50,""\$([\d,]+) prior deposit applied""),"","","""")),0)"),0.0) -> 0 | M50: =F50-L50 -> 4000 | N50: =IFERROR(__xludf.DUMMYFUNCTION("IFERROR(VALUE(SUBSTITUTE(REGEXEXTRACT(Raw_Data!F50,""^\$([\d,]+) cash""),"","","""")),0)"),0.0) -> 0 | O50: =F50-N50 -> 4000 | P50: =IFERROR(__xludf.DUMMYFUNCTION("IFERROR(VALUE(SUBSTITUTE(REGEXEXTRACT(Raw_Data!J50,""labour \d+ h at \$\d+/h: \$([\d,]+)""),"","","""")),0)"),0.0) -> 0 | Q50: =F50-P50 -> 4000 | R50: {=IF(INDEX(Rules!$B$2:$B$60,$D50)="","",INDEX(Rules!$B$2:$B$60,$D50))} -> Cash | S50: {=IF(INDEX(Rules!$E$2:$E$60,$D50)="","",INDEX(Rules!$E$2:$E$60,$D50))} | T50: {=IF(INDEX(Rules!$H$2:$H$60,$D50)="","",INDEX(Rules!$H$2:$H$60,$D50))} | U50: {=IF(INDEX(Rules!$C$2:$C$60,$D50)="","",INDEX(Rules!$C$2:$C$60,$D50))} -> Accounts Receivable | V50: {=IF(INDEX(Rules!$F$2:$F$60,$D50)="","",INDEX(Rules!$F$2:$F$60,$D50))} | W50: {=IF(INDEX(Rules!$I$2:$I$60,$D50)="","",INDEX(Rules!$I$2:$I$60,$D50))} | X50: {=IF(R50="","",INDEX($F50:$Q50,MATCH(INDEX(Rules!$D$2:$D$60,$D50),$F$1:$Q$1,0)))} -> 4000 | Y50: {=IF(S50="","",INDEX($F50:$Q50,MATCH(INDEX(Rules!$G$2:$G$60,$D50),$F$1:$Q$1,0)))} | Z50: {=IF(T50="","",INDEX($F50:$Q50,MATCH(INDEX(Rules!$J$2:$J$60,$D50),$F$1:$Q$1,0)))} | AA50: {=IF(INDEX(Rules!$K$2:$K$60,$D50)="","",INDEX(Rules!$K$2:$K$60,$D50))} -> customer pays what they owed | AB50: =IF(SUMPRODUCT((R50:W50<>"")*(ISNUMBER(SEARCH(Raw_Data!E50,R50:W50))+ISNUMBER(SEARCH(R50:W50,Raw_Data!E50))))>0,"OK","CHECK") -> OK
A51: =Raw_Data!A51 -> VVV-2024-050 | B51: =Raw_Data!D51 -> 600 | C51: =LOWER(Raw_Data!C51&" | "&Raw_Data!F51) -> monthly business insurance premium | automatic bank transfer; settled | D51: {=MATCH(1,ISNUMBER(SEARCH(Rules!$A$2:$A$60,C51))*(Rules!$A$2:$A$60<>""),0)} -> 20 | E51: {=INDEX(Rules!$A$2:$A$60,D51)} -> insurance | F51: =B51 -> 600 | G51: =IFERROR(__xludf.DUMMYFUNCTION("IFERROR(VALUE(SUBSTITUTE(REGEXEXTRACT(Raw_Data!J51,""Cost of goods sold: \$([\d,]+)""),"","","""")),0)"),0.0) -> 0 | H51: =IFERROR(__xludf.DUMMYFUNCTION("IFERROR(VALUE(SUBSTITUTE(REGEXEXTRACT(Raw_Data!J51,""withheld a \$([\d,]+) fee""),"","","""")),0)"),0.0) -> 0 | I51: =F51-H51 -> 600 | J51: =IFERROR(__xludf.DUMMYFUNCTION("IFERROR(VALUE(SUBSTITUTE(REGEXEXTRACT(Raw_Data!J51,""(?i)interest \$([\d,]+)""),"","","""")),0)"),0.0) -> 0 | K51: =F51-J51 -> 600 | L51: =IFERROR(__xludf.DUMMYFUNCTION("IFERROR(VALUE(SUBSTITUTE(REGEXEXTRACT(Raw_Data!F51,""\$([\d,]+) prior deposit applied""),"","","""")),0)"),0.0) -> 0 | M51: =F51-L51 -> 600 | N51: =IFERROR(__xludf.DUMMYFUNCTION("IFERROR(VALUE(SUBSTITUTE(REGEXEXTRACT(Raw_Data!F51,""^\$([\d,]+) cash""),"","","""")),0)"),0.0) -> 0 | O51: =F51-N51 -> 600 | P51: =IFERROR(__xludf.DUMMYFUNCTION("IFERROR(VALUE(SUBSTITUTE(REGEXEXTRACT(Raw_Data!J51,""labour \d+ h at \$\d+/h: \$([\d,]+)""),"","","""")),0)"),0.0) -> 0 | Q51: =F51-P51 -> 600 | R51: {=IF(INDEX(Rules!$B$2:$B$60,$D51)="","",INDEX(Rules!$B$2:$B$60,$D51))} -> Insurance Expense | S51: {=IF(INDEX(Rules!$E$2:$E$60,$D51)="","",INDEX(Rules!$E$2:$E$60,$D51))} | T51: {=IF(INDEX(Rules!$H$2:$H$60,$D51)="","",INDEX(Rules!$H$2:$H$60,$D51))} | U51: {=IF(INDEX(Rules!$C$2:$C$60,$D51)="","",INDEX(Rules!$C$2:$C$60,$D51))} -> Cash | V51: {=IF(INDEX(Rules!$F$2:$F$60,$D51)="","",INDEX(Rules!$F$2:$F$60,$D51))} | W51: {=IF(INDEX(Rules!$I$2:$I$60,$D51)="","",INDEX(Rules!$I$2:$I$60,$D51))} | X51: {=IF(R51="","",INDEX($F51:$Q51,MATCH(INDEX(Rules!$D$2:$D$60,$D51),$F$1:$Q$1,0)))} -> 600 | Y51: {=IF(S51="","",INDEX($F51:$Q51,MATCH(INDEX(Rules!$G$2:$G$60,$D51),$F$1:$Q$1,0)))} | Z51: {=IF(T51="","",INDEX($F51:$Q51,MATCH(INDEX(Rules!$J$2:$J$60,$D51),$F$1:$Q$1,0)))} | AA51: {=IF(INDEX(Rules!$K$2:$K$60,$D51)="","",INDEX(Rules!$K$2:$K$60,$D51))} -> monthly insurance | AB51: =IF(SUMPRODUCT((R51:W51<>"")*(ISNUMBER(SEARCH(Raw_Data!E51,R51:W51))+ISNUMBER(SEARCH(R51:W51,Raw_Data!E51))))>0,"OK","CHECK") -> OK
A52: =Raw_Data!A52 -> VVV-2024-051 | B52: =Raw_Data!D52 -> 13000 | C52: =LOWER(Raw_Data!C52&" | "&Raw_Data!F52) -> equipment rental receipts batch | cash and card receipts; settled | D52: {=MATCH(1,ISNUMBER(SEARCH(Rules!$A$2:$A$60,C52))*(Rules!$A$2:$A$60<>""),0)} -> 26 | E52: {=INDEX(Rules!$A$2:$A$60,D52)} -> rental receipts | F52: =B52 -> 13000 | G52: =IFERROR(__xludf.DUMMYFUNCTION("IFERROR(VALUE(SUBSTITUTE(REGEXEXTRACT(Raw_Data!J52,""Cost of goods sold: \$([\d,]+)""),"","","""")),0)"),0.0) -> 0 | H52: =IFERROR(__xludf.DUMMYFUNCTION("IFERROR(VALUE(SUBSTITUTE(REGEXEXTRACT(Raw_Data!J52,""withheld a \$([\d,]+) fee""),"","","""")),0)"),0.0) -> 0 | I52: =F52-H52 -> 13000 | J52: =IFERROR(__xludf.DUMMYFUNCTION("IFERROR(VALUE(SUBSTITUTE(REGEXEXTRACT(Raw_Data!J52,""(?i)interest \$([\d,]+)""),"","","""")),0)"),0.0) -> 0 | K52: =F52-J52 -> 13000 | L52: =IFERROR(__xludf.DUMMYFUNCTION("IFERROR(VALUE(SUBSTITUTE(REGEXEXTRACT(Raw_Data!F52,""\$([\d,]+) prior deposit applied""),"","","""")),0)"),0.0) -> 0 | M52: =F52-L52 -> 13000 | N52: =IFERROR(__xludf.DUMMYFUNCTION("IFERROR(VALUE(SUBSTITUTE(REGEXEXTRACT(Raw_Data!F52,""^\$([\d,]+) cash""),"","","""")),0)"),0.0) -> 0 | O52: =F52-N52 -> 13000 | P52: =IFERROR(__xludf.DUMMYFUNCTION("IFERROR(VALUE(SUBSTITUTE(REGEXEXTRACT(Raw_Data!J52,""labour \d+ h at \$\d+/h: \$([\d,]+)""),"","","""")),0)"),0.0) -> 0 | Q52: =F52-P52 -> 13000 | R52: {=IF(INDEX(Rules!$B$2:$B$60,$D52)="","",INDEX(Rules!$B$2:$B$60,$D52))} -> Cash | S52: {=IF(INDEX(Rules!$E$2:$E$60,$D52)="","",INDEX(Rules!$E$2:$E$60,$D52))} | T52: {=IF(INDEX(Rules!$H$2:$H$60,$D52)="","",INDEX(Rules!$H$2:$H$60,$D52))} | U52: {=IF(INDEX(Rules!$C$2:$C$60,$D52)="","",INDEX(Rules!$C$2:$C$60,$D52))} -> Equipment Rental Revenue | V52: {=IF(INDEX(Rules!$F$2:$F$60,$D52)="","",INDEX(Rules!$F$2:$F$60,$D52))} | W52: {=IF(INDEX(Rules!$I$2:$I$60,$D52)="","",INDEX(Rules!$I$2:$I$60,$D52))} | X52: {=IF(R52="","",INDEX($F52:$Q52,MATCH(INDEX(Rules!$D$2:$D$60,$D52),$F$1:$Q$1,0)))} -> 13000 | Y52: {=IF(S52="","",INDEX($F52:$Q52,MATCH(INDEX(Rules!$G$2:$G$60,$D52),$F$1:$Q$1,0)))} | Z52: {=IF(T52="","",INDEX($F52:$Q52,MATCH(INDEX(Rules!$J$2:$J$60,$D52),$F$1:$Q$1,0)))} | AA52: {=IF(INDEX(Rules!$K$2:$K$60,$D52)="","",INDEX(Rules!$K$2:$K$60,$D52))} -> rentals done and paid | AB52: =IF(SUMPRODUCT((R52:W52<>"")*(ISNUMBER(SEARCH(Raw_Data!E52,R52:W52))+ISNUMBER(SEARCH(R52:W52,Raw_Data!E52))))>0,"OK","CHECK") -> OK
A53: =Raw_Data!A53 -> VVV-2024-052 | B53: =Raw_Data!D53 -> 8000 | C53: =LOWER(Raw_Data!C53&" | "&Raw_Data!F53) -> retail camping-supply sales | card processor; fee withheld | D53: {=MATCH(1,ISNUMBER(SEARCH(Rules!$A$2:$A$60,C53))*(Rules!$A$2:$A$60<>""),0)} -> 11 | E53: {=INDEX(Rules!$A$2:$A$60,D53)} -> fee withheld | F53: =B53 -> 8000 | G53: =IFERROR(__xludf.DUMMYFUNCTION("IFERROR(VALUE(SUBSTITUTE(REGEXEXTRACT(Raw_Data!J53,""Cost of goods sold: \$([\d,]+)""),"","","""")),0)"),4800.0) -> 4800 | H53: =IFERROR(__xludf.DUMMYFUNCTION("IFERROR(VALUE(SUBSTITUTE(REGEXEXTRACT(Raw_Data!J53,""withheld a \$([\d,]+) fee""),"","","""")),0)"),240.0) -> 240 | I53: =F53-H53 -> 7760 | J53: =IFERROR(__xludf.DUMMYFUNCTION("IFERROR(VALUE(SUBSTITUTE(REGEXEXTRACT(Raw_Data!J53,""(?i)interest \$([\d,]+)""),"","","""")),0)"),0.0) -> 0 | K53: =F53-J53 -> 8000 | L53: =IFERROR(__xludf.DUMMYFUNCTION("IFERROR(VALUE(SUBSTITUTE(REGEXEXTRACT(Raw_Data!F53,""\$([\d,]+) prior deposit applied""),"","","""")),0)"),0.0) -> 0 | M53: =F53-L53 -> 8000 | N53: =IFERROR(__xludf.DUMMYFUNCTION("IFERROR(VALUE(SUBSTITUTE(REGEXEXTRACT(Raw_Data!F53,""^\$([\d,]+) cash""),"","","""")),0)"),0.0) -> 0 | O53: =F53-N53 -> 8000 | P53: =IFERROR(__xludf.DUMMYFUNCTION("IFERROR(VALUE(SUBSTITUTE(REGEXEXTRACT(Raw_Data!J53,""labour \d+ h at \$\d+/h: \$([\d,]+)""),"","","""")),0)"),0.0) -> 0 | Q53: =F53-P53 -> 8000 | R53: {=IF(INDEX(Rules!$B$2:$B$60,$D53)="","",INDEX(Rules!$B$2:$B$60,$D53))} -> Cash | S53: {=IF(INDEX(Rules!$E$2:$E$60,$D53)="","",INDEX(Rules!$E$2:$E$60,$D53))} -> Office and Admin Expense | T53: {=IF(INDEX(Rules!$H$2:$H$60,$D53)="","",INDEX(Rules!$H$2:$H$60,$D53))} -> Cost of Goods Sold | U53: {=IF(INDEX(Rules!$C$2:$C$60,$D53)="","",INDEX(Rules!$C$2:$C$60,$D53))} -> Retail Sales Revenue | V53: {=IF(INDEX(Rules!$F$2:$F$60,$D53)="","",INDEX(Rules!$F$2:$F$60,$D53))} -> Retail Sales Revenue | W53: {=IF(INDEX(Rules!$I$2:$I$60,$D53)="","",INDEX(Rules!$I$2:$I$60,$D53))} -> Inventory | X53: {=IF(R53="","",INDEX($F53:$Q53,MATCH(INDEX(Rules!$D$2:$D$60,$D53),$F$1:$Q$1,0)))} -> 7760 | Y53: {=IF(S53="","",INDEX($F53:$Q53,MATCH(INDEX(Rules!$G$2:$G$60,$D53),$F$1:$Q$1,0)))} -> 240 | Z53: {=IF(T53="","",INDEX($F53:$Q53,MATCH(INDEX(Rules!$J$2:$J$60,$D53),$F$1:$Q$1,0)))} -> 4800 | AA53: {=IF(INDEX(Rules!$K$2:$K$60,$D53)="","",INDEX(Rules!$K$2:$K$60,$D53))} -> full 8000 is revenue, processor kept 240 (fee expense), goods leave inventory | AB53: =IF(SUMPRODUCT((R53:W53<>"")*(ISNUMBER(SEARCH(Raw_Data!E53,R53:W53))+ISNUMBER(SEARCH(R53:W53,Raw_Data!E53))))>0,"OK","CHECK") -> OK
A54: =Raw_Data!A54 -> VVV-2024-053 | B54: =Raw_Data!D54 -> 9000 | C54: =LOWER(Raw_Data!C54&" | "&Raw_Data!F54) -> corporate guided tour delivered; deposit applied | $4,000 prior deposit applied; $5,000 invoiced | D54: {=MATCH(1,ISNUMBER(SEARCH(Rules!$A$2:$A$60,C54))*(Rules!$A$2:$A$60<>""),0)} -> 27 | E54: {=INDEX(Rules!$A$2:$A$60,D54)} -> tour delivered; deposit applied | F54: =B54 -> 9000 | G54: =IFERROR(__xludf.DUMMYFUNCTION("IFERROR(VALUE(SUBSTITUTE(REGEXEXTRACT(Raw_Data!J54,""Cost of goods sold: \$([\d,]+)""),"","","""")),0)"),0.0) -> 0 | H54: =IFERROR(__xludf.DUMMYFUNCTION("IFERROR(VALUE(SUBSTITUTE(REGEXEXTRACT(Raw_Data!J54,""withheld a \$([\d,]+) fee""),"","","""")),0)"),0.0) -> 0 | I54: =F54-H54 -> 9000 | J54: =IFERROR(__xludf.DUMMYFUNCTION("IFERROR(VALUE(SUBSTITUTE(REGEXEXTRACT(Raw_Data!J54,""(?i)interest \$([\d,]+)""),"","","""")),0)"),0.0) -> 0 | K54: =F54-J54 -> 9000 | L54: =IFERROR(__xludf.DUMMYFUNCTION("IFERROR(VALUE(SUBSTITUTE(REGEXEXTRACT(Raw_Data!F54,""\$([\d,]+) prior deposit applied""),"","","""")),0)"),4000.0) -> 4000 | M54: =F54-L54 -> 5000 | N54: =IFERROR(__xludf.DUMMYFUNCTION("IFERROR(VALUE(SUBSTITUTE(REGEXEXTRACT(Raw_Data!F54,""^\$([\d,]+) cash""),"","","""")),0)"),0.0) -> 0 | O54: =F54-N54 -> 9000 | P54: =IFERROR(__xludf.DUMMYFUNCTION("IFERROR(VALUE(SUBSTITUTE(REGEXEXTRACT(Raw_Data!J54,""labour \d+ h at \$\d+/h: \$([\d,]+)""),"","","""")),0)"),0.0) -> 0 | Q54: =F54-P54 -> 9000 | R54: {=IF(INDEX(Rules!$B$2:$B$60,$D54)="","",INDEX(Rules!$B$2:$B$60,$D54))} -> Unearned Revenue | S54: {=IF(INDEX(Rules!$E$2:$E$60,$D54)="","",INDEX(Rules!$E$2:$E$60,$D54))} -> Accounts Receivable | T54: {=IF(INDEX(Rules!$H$2:$H$60,$D54)="","",INDEX(Rules!$H$2:$H$60,$D54))} | U54: {=IF(INDEX(Rules!$C$2:$C$60,$D54)="","",INDEX(Rules!$C$2:$C$60,$D54))} -> Tour Revenue | V54: {=IF(INDEX(Rules!$F$2:$F$60,$D54)="","",INDEX(Rules!$F$2:$F$60,$D54))} -> Tour Revenue | W54: {=IF(INDEX(Rules!$I$2:$I$60,$D54)="","",INDEX(Rules!$I$2:$I$60,$D54))} | X54: {=IF(R54="","",INDEX($F54:$Q54,MATCH(INDEX(Rules!$D$2:$D$60,$D54),$F$1:$Q$1,0)))} -> 4000 | Y54: {=IF(S54="","",INDEX($F54:$Q54,MATCH(INDEX(Rules!$G$2:$G$60,$D54),$F$1:$Q$1,0)))} -> 5000 | Z54: {=IF(T54="","",INDEX($F54:$Q54,MATCH(INDEX(Rules!$J$2:$J$60,$D54),$F$1:$Q$1,0)))} | AA54: {=IF(INDEX(Rules!$K$2:$K$60,$D54)="","",INDEX(Rules!$K$2:$K$60,$D54))} -> no cash today: feb deposit now earned + rest billed (AR) | AB54: =IF(SUMPRODUCT((R54:W54<>"")*(ISNUMBER(SEARCH(Raw_Data!E54,R54:W54))+ISNUMBER(SEARCH(R54:W54,Raw_Data!E54))))>0,"OK","CHECK") -> CHECK
A55: =Raw_Data!A55 -> VVV-2024-054 | B55: =Raw_Data!D55 -> 11240 | C55: =LOWER(Raw_Data!C55&" | "&Raw_Data!F55) -> employee payroll settlement | payroll and claims paid from business bank account | D55: {=MATCH(1,ISNUMBER(SEARCH(Rules!$A$2:$A$60,C55))*(Rules!$A$2:$A$60<>""),0)} -> 23 | E55: {=INDEX(Rules!$A$2:$A$60,D55)} -> payroll | F55: =B55 -> 11240 | G55: =IFERROR(__xludf.DUMMYFUNCTION("IFERROR(VALUE(SUBSTITUTE(REGEXEXTRACT(Raw_Data!J55,""Cost of goods sold: \$([\d,]+)""),"","","""")),0)"),0.0) -> 0 | H55: =IFERROR(__xludf.DUMMYFUNCTION("IFERROR(VALUE(SUBSTITUTE(REGEXEXTRACT(Raw_Data!J55,""withheld a \$([\d,]+) fee""),"","","""")),0)"),0.0) -> 0 | I55: =F55-H55 -> 11240 | J55: =IFERROR(__xludf.DUMMYFUNCTION("IFERROR(VALUE(SUBSTITUTE(REGEXEXTRACT(Raw_Data!J55,""(?i)interest \$([\d,]+)""),"","","""")),0)"),0.0) -> 0 | K55: =F55-J55 -> 11240 | L55: =IFERROR(__xludf.DUMMYFUNCTION("IFERROR(VALUE(SUBSTITUTE(REGEXEXTRACT(Raw_Data!F55,""\$([\d,]+) prior deposit applied""),"","","""")),0)"),0.0) -> 0 | M55: =F55-L55 -> 11240 | N55: =IFERROR(__xludf.DUMMYFUNCTION("IFERROR(VALUE(SUBSTITUTE(REGEXEXTRACT(Raw_Data!F55,""^\$([\d,]+) cash""),"","","""")),0)"),0.0) -> 0 | O55: =F55-N55 -> 11240 | P55: =IFERROR(__xludf.DUMMYFUNCTION("IFERROR(VALUE(SUBSTITUTE(REGEXEXTRACT(Raw_Data!J55,""labour \d+ h at \$\d+/h: \$([\d,]+)""),"","","""")),0)"),0.0) -> 0 | Q55: =F55-P55 -> 11240 | R55: {=IF(INDEX(Rules!$B$2:$B$60,$D55)="","",INDEX(Rules!$B$2:$B$60,$D55))} -> Wages Expense | S55: {=IF(INDEX(Rules!$E$2:$E$60,$D55)="","",INDEX(Rules!$E$2:$E$60,$D55))} | T55: {=IF(INDEX(Rules!$H$2:$H$60,$D55)="","",INDEX(Rules!$H$2:$H$60,$D55))} | U55: {=IF(INDEX(Rules!$C$2:$C$60,$D55)="","",INDEX(Rules!$C$2:$C$60,$D55))} -> Cash | V55: {=IF(INDEX(Rules!$F$2:$F$60,$D55)="","",INDEX(Rules!$F$2:$F$60,$D55))} | W55: {=IF(INDEX(Rules!$I$2:$I$60,$D55)="","",INDEX(Rules!$I$2:$I$60,$D55))} | X55: {=IF(R55="","",INDEX($F55:$Q55,MATCH(INDEX(Rules!$D$2:$D$60,$D55),$F$1:$Q$1,0)))} -> 11240 | Y55: {=IF(S55="","",INDEX($F55:$Q55,MATCH(INDEX(Rules!$G$2:$G$60,$D55),$F$1:$Q$1,0)))} | Z55: {=IF(T55="","",INDEX($F55:$Q55,MATCH(INDEX(Rules!$J$2:$J$60,$D55),$F$1:$Q$1,0)))} | AA55: {=IF(INDEX(Rules!$K$2:$K$60,$D55)="","",INDEX(Rules!$K$2:$K$60,$D55))} -> wages, includes E04's $200 travel claim | AB55: =IF(SUMPRODUCT((R55:W55<>"")*(ISNUMBER(SEARCH(Raw_Data!E55,R55:W55))+ISNUMBER(SEARCH(R55:W55,Raw_Data!E55))))>0,"OK","CHECK") -> OK
A56: =Raw_Data!A56 -> VVV-2024-055 | B56: =Raw_Data!D56 -> 9000 | C56: =LOWER(Raw_Data!C56&" | "&Raw_Data!F56) -> purchased retail inventory on account | supplier invoice; payment by agreed instalments | D56: {=MATCH(1,ISNUMBER(SEARCH(Rules!$A$2:$A$60,C56))*(Rules!$A$2:$A$60<>""),0)} -> 9 | E56: {=INDEX(Rules!$A$2:$A$60,D56)} -> inventory on account | F56: =B56 -> 9000 | G56: =IFERROR(__xludf.DUMMYFUNCTION("IFERROR(VALUE(SUBSTITUTE(REGEXEXTRACT(Raw_Data!J56,""Cost of goods sold: \$([\d,]+)""),"","","""")),0)"),0.0) -> 0 | H56: =IFERROR(__xludf.DUMMYFUNCTION("IFERROR(VALUE(SUBSTITUTE(REGEXEXTRACT(Raw_Data!J56,""withheld a \$([\d,]+) fee""),"","","""")),0)"),0.0) -> 0 | I56: =F56-H56 -> 9000 | J56: =IFERROR(__xludf.DUMMYFUNCTION("IFERROR(VALUE(SUBSTITUTE(REGEXEXTRACT(Raw_Data!J56,""(?i)interest \$([\d,]+)""),"","","""")),0)"),0.0) -> 0 | K56: =F56-J56 -> 9000 | L56: =IFERROR(__xludf.DUMMYFUNCTION("IFERROR(VALUE(SUBSTITUTE(REGEXEXTRACT(Raw_Data!F56,""\$([\d,]+) prior deposit applied""),"","","""")),0)"),0.0) -> 0 | M56: =F56-L56 -> 9000 | N56: =IFERROR(__xludf.DUMMYFUNCTION("IFERROR(VALUE(SUBSTITUTE(REGEXEXTRACT(Raw_Data!F56,""^\$([\d,]+) cash""),"","","""")),0)"),0.0) -> 0 | O56: =F56-N56 -> 9000 | P56: =IFERROR(__xludf.DUMMYFUNCTION("IFERROR(VALUE(SUBSTITUTE(REGEXEXTRACT(Raw_Data!J56,""labour \d+ h at \$\d+/h: \$([\d,]+)""),"","","""")),0)"),0.0) -> 0 | Q56: =F56-P56 -> 9000 | R56: {=IF(INDEX(Rules!$B$2:$B$60,$D56)="","",INDEX(Rules!$B$2:$B$60,$D56))} -> Inventory | S56: {=IF(INDEX(Rules!$E$2:$E$60,$D56)="","",INDEX(Rules!$E$2:$E$60,$D56))} | T56: {=IF(INDEX(Rules!$H$2:$H$60,$D56)="","",INDEX(Rules!$H$2:$H$60,$D56))} | U56: {=IF(INDEX(Rules!$C$2:$C$60,$D56)="","",INDEX(Rules!$C$2:$C$60,$D56))} -> Accounts Payable | V56: {=IF(INDEX(Rules!$F$2:$F$60,$D56)="","",INDEX(Rules!$F$2:$F$60,$D56))} | W56: {=IF(INDEX(Rules!$I$2:$I$60,$D56)="","",INDEX(Rules!$I$2:$I$60,$D56))} | X56: {=IF(R56="","",INDEX($F56:$Q56,MATCH(INDEX(Rules!$D$2:$D$60,$D56),$F$1:$Q$1,0)))} -> 9000 | Y56: {=IF(S56="","",INDEX($F56:$Q56,MATCH(INDEX(Rules!$G$2:$G$60,$D56),$F$1:$Q$1,0)))} | Z56: {=IF(T56="","",INDEX($F56:$Q56,MATCH(INDEX(Rules!$J$2:$J$60,$D56),$F$1:$Q$1,0)))} | AA56: {=IF(INDEX(Rules!$K$2:$K$60,$D56)="","",INDEX(Rules!$K$2:$K$60,$D56))} -> stuff to resell, bought on credit | AB56: =IF(SUMPRODUCT((R56:W56<>"")*(ISNUMBER(SEARCH(Raw_Data!E56,R56:W56))+ISNUMBER(SEARCH(R56:W56,Raw_Data!E56))))>0,"OK","CHECK") -> OK
